Workbook

Sheet BS
A1: DIAGO CO-OPERATIVE HOUSING SOCIETY
A2: 186-A, Baudi Cross Lane, Orlem, Malad (West), Mumbai, Maharashtra - 400064
A3: Society Reg No : BOM/(WP)/HSG(TC) 1007/84-85 dated.13/07/1984
A4: Balance Sheet as at March 31, 2025
A5: March 31, 2024 | B5: LIABILITIES | D5: March 31, 2025 | E5: =+A5 -> March 31, 2024 | F5: ASSETS | H5: =+D5 -> March 31, 2025
B6: Authorised Share Capital | F6: Cash and Bank Balances:
A7: =4460*50 -> 223000 | B7: 4460 Share of ₹ 50/- each | D7: 223000 | E7: 3958 | F7: Cash in Hand | G7: 2056
E8: 157174.32 | F8: Saraswat Co-op Bank | G8: 257877.75
B9: Issued, Subscribed and Fully Paid-up: | E9: 2685.86 | F9: Mumbai District Central Co-op Bank | G9: 2777.86
A10: 18000 | B10: 360 Shares of ₹ 50/- each | D10: 18000 | E10: 3348.56 | F10: Bank of Baroda | G10: 3441.85 | H10: =SUM(G7:G10) -> 266153.46
A12: 1065039 | B12: Reserves and Surplus: | D12: ='Fund Sch_1'!D45 -> 1260442 | F12: Investments:
B13: (Refer Schedule 1) | E13: 1000 | F13: Share of MDCC Bank | G13: 1000
E14: 1118249 | F14: Fixed Deposits: (Refer Schedule 2) | G14: ='FD Sch_2'!D79 -> 1228170
B15: Members Contributions Towards | E15: 58644 | F15: Accrued Interest | G15: ='FD Sch_2'!H79 -> 67712 | H15: =SUM(G13:G15) -> 1296882
A16: 2227750 | B16: Land and Building | D16: 2227750
F17: Deposits:
B18: Current Liabilities: | E18: 33319 | F18: Deposit with BMC | G18: 33319
A19: 39416 | B19: Advance from Members (Sch 5) | C19: ='Advance n Refundable Sch 4&5'!E19 -> 31930 | E19: 4430 | F19: Deposit with Tata Power | G19: 4430
A20: 20000 | B20: Refundable Deposit (Sch 6) | C20: ='Advance n Refundable Sch 4&5'!E33 -> 20000 | D20: =SUM(C19:C20) -> 51930 | E20: 0 | F20: Advance Income Tax - FY. 2022-23 | G20: 0 | H20: =SUM(G18:G20) -> 37749
B22: Provisions: | F22: Sundry Debtors:
A23: 3600 | B23: Audit Fees Payable | C23: 3600 | E23: 0 | F23: Member's Due (Refer Schedule 4) | H23: ='Advance n Refundable Sch 4&5'!E6 -> 6921
A24: 18480 | B24: Water Charges Payable | C24: 18026
A25: 3540 | B25: Professional Fee Payable | C25: =1770+1770+1770 -> 5310 | F25: Prepaid Expenses:
A26: 20970 | B26: Payables (Refer Schedule 7) | C26: ='Advance n Refundable Sch 4&5'!J7 -> 9694 | E26: 7268 | F26: Insurance Charges | G26: 7269
A27: 54400 | B27: Retention - Ecotech Exterior and Interior | C27: 54400 | D27: =SUM(C23:C27) -> 91030 | E27: 14430 | F27: Pest Control Charges | G27: 9802
E28: 2510 | F28: CCTV AMC | G28: 0 | H28: =SUM(G26:G28) -> 17071
B29: Income and Expenditure Account: | F29: Fixed Assets
A30: 170573.31 | B30: Balance as per last balance sheet | C30: =SUM(A30:A32) -> 236930.74 | E30: 2291324 | F30: (Refer Schedule 3) | H30: ='FA Sch_3'!H15 -> 2287010
A31: 0 | B31: Add: Excess Prof. Fees Prov. written back | C31: 1770 | E31: 9785 | F31: TDS Receivable | H31: 6995
A32: 66357.43 | B32: Add: Surplus/(Defecit) for the year | C32: =IE!D47 -> 30928.72 | D32: =SUM(C30:C32) -> 269629.46
A33: =SUM(A10:A32) -> 3708125.7 | B33: Total | D33: =SUM(D10:D32) -> 3918781.5 | E33: =SUM(E6:E32) -> 3708125.7 | F33: Total | H33: =SUM(H6:H32) -> 3918781.5 | I33: =D33-H33 -> 0 | J33: =D33-H33 -> 0
A34: As per my Report of Even date | E34: ="For "&A1 -> For DIAGO CO-OPERATIVE HOUSING SOCIETY
A35: For Amish S. Sangoi & Co.
A36: Chartered Accountant
A39: [CA Amish S. Sangoi]
A40: M. No. 126151
A41: FRN : 0132656W | B41: Panel No. 1015787
A42: Place : Mumbai | B42: Date : | E42: Chairman Secretary Treasurer
A43: UDIN :
B45: to change FY 24-25 figures

Sheet IE
A1: =BS!A1 -> DIAGO CO-OPERATIVE HOUSING SOCIETY
A2: =BS!A2 -> 186-A, Baudi Cross Lane, Orlem, Malad (West), Mumbai, Maharashtra - 400064
A3: =BS!A3 -> Society Reg No : BOM/(WP)/HSG(TC) 1007/84-85 dated.13/07/1984
A4: Income and Expenditure Account for the year ended March 31, 2025
A5: March 31, 2024 | B5: EXPENDITURE | D5: March 31, 2025 | E5: =+A5 -> March 31, 2024 | F5: INCOME | H5: =+D5 -> March 31, 2025
B6: Property Tax | F6: Maintenance Income
A7: 11172 | B7: Property Tax | C7: 13333 | E7: 11176 | F7: Property Tax | G7: 13330
A8: 0 | B8: Property Tax Rebate Recovery | C8: 0 | D8: =SUM(C7:C8) -> 13333 | E8: 226080 | F8: Maintenance Charges | G8: 226080
E9: 55008 | F9: Electricity Charges | G9: 55008
B10: Water Expenses | E10: 75312 | F10: Water Charges | G10: 75312
A11: 78029 | B11: Water Expenses | C11: 76693 | E11: 10747 | F11: Non Occupancy Charges | G11: =9589+83 -> 9672
A12: 0 | B12: Water Tank Cleaning Expenses | C12: 4000 | D12: =SUM(C11:C12) -> 80693 | E12: 20550 | F12: Parking Charges | G12: =12200+15200+1600 -> 29000
E13: 820 | F13: Interest on Delayed Payments | G13: 781
A14: 70390 | B14: Common Electricity Charges | D14: 75021 | E14: 13172 | F14: Insurance Charges | G14: 13172
E15: 100 | F15: Fines | G15: 200
A16: 30000 | B16: Salary Expenses | D16: 40500 | E16: 3200 | F16: Guest Parking Charges | G16: 2925 | H16: =SUM(G7:G16) -> 425480
B18: Repair and Maintenance Expenses | F18: Interest Income
A19: 5102 | B19: Electrical Repairs | C19: 8240 | E19: 5612 | F19: Interest Income from Savings Deposits | H19: 6310
A20: 21442 | B20: Plumbing Repairs | C20: 47219 | E20: 0 | F20: Interest on Income Tax Refund | H20: 751
A21: 31320 | B21: Other Repairs | C21: 58875 | E21: 61479 | F21: Interest Income from Fixed Deposits | G21: 84529
A22: 2740 | B22: CCTV AMC Expense | C22: 2510 | E22: -8687 | F22: Less: trf to Sinking Fund | G22: -10936
A23: 0 | B23: Fire Fighting Expenses | C23: 1300 | E23: -9458 | F23: Less: trf to Painting Fund | G23: -9156
A24: 9359 | B24: Pest Control Expenses | C24: 9028 | E24: -14296 | F24: Less: trf to Legal Fund | G24: -17335
A25: -9359 | B25: Less: trf to Pest Control Fund | C25: =-C24 -> -9028 | D25: =SUM(C19:C25) -> 118144 | E25: -7052 | F25: Less: trf to Common Amenity Fund | G25: -9159
E26: -8843 | F26: Less: trf to General Fund | G26: -12681
B27: Service Charges | E27: -5612 | F27: Less: trf to Pest Control Fund | G27: -10495
A28: 7782 | B28: Insurance Expense | C28: 7780 | E28: -3441 | F28: Less: trf to Redevelopment Fund | G28: -10095
A29: 3600 | B29: Audit Fees | C29: 3600 | E29: -1760 | F29: Less: trf to Education & Training Fund | G29: -2205 | H29: =SUM(G21:G29) -> 2467
A30: 20000 | B30: Structural Audit Fees | C30: 0
A31: 826 | B31: Subscription Federation | C31: 826 | F31: Other Income
A32: 20392 | B32: Accounting Charges | C32: 20392 | D32: =SUM(C28:C32) -> 32598 | E32: 0 | F32: Miscellaneous Income | G32: 7
E33: 51 | F33: Dividend Income | G33: 0 | H33: =SUM(G32:G33) -> 7
B34: Other Expenses
A35: 5056 | B35: Depreciation | C35: ='FA Sch_3'!G15 -> 4314
A36: 4547 | B36: Printing and Stationary | C36: 998
A37: 2873 | B37: Meeting Expenses | C37: 10406
A38: 3726 | B38: Conveyance Expense | C38: 4751
A39: 15350 | B39: Professional Fees | C39: =3540+1770+1770 -> 7080
A40: 0 | B40: Legal Fees | C40: 2500
A41: 659.57 | B41: Bank Charges | C41: 403.28
A42: 675 | B42: Income Tax | C42: 36
A43: 0 | B43: Misc. Expenses | C43: 3000 | D43: =SUM(C35:C43) -> 33488.28
B45: Excess of Income over Expenditure
A46: 22119 | B46: Less: 25% Surplus trfd. to Reserves | D46: =ROUND((H48-SUM(D6:D45))*0.25,) -> 10309 | J46: 25% entry not passed now, will pass once audit is finalized.
A47: 66357.43 | B47: Surplus/(Deficit) for the year | D47: =H48-SUM(D6:D46) -> 30928.72
A48: =SUM(A6:A47) -> 424158 | B48: Total | D48: =SUM(D6:D47) -> 435015 | E48: =SUM(E6:E47) -> 424158 | F48: Total | H48: =SUM(H6:H47) -> 435015 | I48: =A48-E48 -> 0 | J48: =D48-H48 -> 0
A49: As per my Report of Even date | E49: =BS!E34 -> For DIAGO CO-OPERATIVE HOUSING SOCIETY
A50: For Amish S. Sangoi & Co.
A51: Chartered Accountant
A54: [CA Amish S. Sangoi]
A55: M. No. 126151
A56: FRN : 0132656W | B56: Panel No. 1015787
A57: Place : Mumbai | B57: Date : | E57: Chairman Secretary Treasurer
A58: UDIN :

Sheet Fund Sch_1
A1: DIAGO CO-OP HOUSING SOCIETY LIMITED.
A2: Schedule 1 - Liability - Funds as at 31st March 2025
A3: FY 23-24 | B3: Particulars | D3: FY 24-25
B4: General Fund
A5: 84304 | B5: As per last Balance Sheet | C5: =SUM(A5:A8) -> 116266
A6: 1000 | B6: Add: Addition during the year | C6: 54200
A7: 22119 | B7: Add: 25% surplus trfd from Income/Expend. | C7: =IE!D46 -> 10309
A8: 8843 | B8: Add: Accrued interest | C8: 12681 | D8: =SUM(C5:C8) -> 193456
B10: Common Amenity Fund
A11: 121823 | B11: As per last Balance Sheet | C11: =SUM(A11:A12) -> 128875
A12: 7052 | B12: Add: Accrued interest | C12: 9159 | D12: =SUM(C11:C12) -> 138034
B14: Redevelopment Fund
A15: 43276 | B15: As per last Balance Sheet | C15: =SUM(A15:A17) -> 133117
A16: 86400 | B16: Add: Additions during the year | C16: 0
A17: 3441 | B17: Add: Interest received/accrued | C17: 10095 | D17: =SUM(C15:C17) -> 143212
B19: Sinking Fund
A20: 148885 | B20: As per last Balance Sheet | C20: =SUM(A20:A22) -> 165556
A21: 7984 | B21: Add: Additions during the year | C21: 7984
A22: 8687 | B22: Add: Interest received/accrued | C22: 10936 | D22: =SUM(C20:C22) -> 184476
B24: Repair & Maintenance/Painting Fund
A25: 99997 | B25: As per last Balance Sheet | C25: =SUM(A25:A27) -> 133411
A26: 23956 | B26: Add: Additions during the year | C26: 23956
A27: 9458 | B27: Add: Interest received/accrued | C27: 9156 | D27: =SUM(C25:C27) -> 166523
B29: Pest Control Fund
A30: 140127 | B30: As per last Balance Sheet | C30: =SUM(A30:A32) -> 136380
A31: -9359 | B31: Less: Expenses incurred for the year | C31: =IE!C25 -> -9028
A32: 5612 | B32: Add: Interest received/accrued | C32: 10495 | D32: =SUM(C30:C32) -> 137847
B34: Legal Fund
A35: 185917 | B35: As per last Balance Sheet | C35: =SUM(A35:A38) -> 221813
A36: 21600 | B36: Add: Additions during the year | C36: 21600
A37: 14296 | B37: Add: Interest received/accrued | C37: 17335
A38: 0 | B38: Less: Expenses incurred for the year | C38: 0 | D38: =SUM(C35:C38) -> 260748
B40: Education & Training Fund
A41: 23541 | B41: As per last Balance Sheet | C41: =SUM(A41:A43) -> 29621
A42: 4320 | B42: Add: Additions during the year | C42: 4320
A43: 1760 | B43: Add: Interest received/accrued | C43: 2205 | D43: =SUM(C41:C43) -> 36146
A45: =SUM(A5:A44) -> 1065039 | B45: Total | D45: =SUM(D5:D44) -> 1260442

Sheet FD Sch_2
A1: =BS!A1 -> DIAGO CO-OPERATIVE HOUSING SOCIETY
A2: Schedule 2 - Details of Fixed Deposits as on 31st March 2025
A3: Sr. | B3: Certificate No. | C3: Date | D3: Amount Invested | E3: Accrued Int 22-23 | F3: Accrued Int 23-24 | G3: Accrued Int 24-25 | H3: Total Accrued Int | I3: Total | J3: Maturity Date | K3: Maturity Value | L3: Interest % | M3: Bank
B4: Sinking Fund
A5: 1 | B5: TD1000182883_01 | C5: 04.12.24 | D5: 13194 | E5: 0 | F5: 0 | G5: =302-30 -> 272 | H5: =+E5+F5+G5 -> 272 | I5: =D5+H5 -> 13466 | J5: 04.12.27 | K5: 16248 | L5: 0.07 | M5: SCB
A6: 2 | B6: TD1001116944 | C6: 08.03.24 | D6: 6537 | E6: 0 | F6: =32-3 -> 29 | G6: =505-51 -> 454 | H6: =+E6+F6+G6 -> 483 | I6: =D6+H6 -> 7020 | J6: 08.06.25 | K6: 7173 | L6: 0.075 | M6: SCB
A7: 3 | B7: TD0000415625_01 | C7: 20.03.24 | D7: 5671 | E7: 0 | F7: =14-2 -> 12 | G7: =437-44 -> 393 | H7: =+E7+F7+G7 -> 405 | I7: =D7+H7 -> 6076 | J7: 20.06.25 | K7: 6223 | L7: 0.075 | M7: SCB
A8: 4 | B8: TD0000415687_02 | C8: 05.06.24 | D8: 7366 | E8: 0 | F8: 0 | G8: =432-44 -> 388 | H8: =+E8+F8+G8 -> 388 | I8: =D8+H8 -> 7754 | J8: 05.06.27 | K8: 9071 | L8: 0.07 | M8: SCB
A9: 5 | B9: TD0000415693_02 | C9: 25.06.24 | D9: 7281 | E9: 0 | F9: 0 | G9: =398-39 -> 359 | H9: =+E9+F9+G9 -> 359 | I9: =D9+H9 -> 7640 | J9: 25.06.27 | K9: 8966 | L9: 0.07 | M9: SCB
A10: 6 | B10: TD0000415690_02 | C10: 22.06.24 | D10: 19266 | E10: 0 | F10: 0 | G10: =1065-107 -> 958 | H10: =+E10+F10+G10 -> 958 | I10: =D10+H10 -> 20224 | J10: 22.06.27 | K10: 23725 | L10: 0.07 | M10: SCB
A11: 7 | B11: TD1001583749 | C11: 28.03.25 | D11: 11492 | E11: 0 | F11: 0 | G11: =9-1 -> 8 | H11: =+E11+F11+G11 -> 8 | I11: =D11+H11 -> 11500 | J11: 28.07.26 | K11: 12688 | L11: 0.075 | M11: SCB
A12: 8 | B12: TD1001583745 | C12: 28.03.25 | D12: 26590 | E12: 0 | F12: 0 | G12: =21-3 -> 18 | H12: =+E12+F12+G12 -> 18 | I12: =D12+H12 -> 26608 | J12: 28.07.26 | K12: 29358 | L12: 0.075 | M12: SCB
A13: 9 | B13: TD0000415655_01 | C13: 28.03.25 | D13: 3663 | E13: 0 | F13: 0 | G13: =3-0 -> 3 | H13: =+E13+F13+G13 -> 3 | I13: =D13+H13 -> 3666 | M13: SCB
A14: 10 | B14: TD1000721256 | C14: 22.03.23 | D14: 3150 | E14: 6 | F14: =226-22 -> 204 | G14: =241-24 -> 217 | H14: =+E14+F14+G14 -> 427 | I14: =D14+H14 -> 3577 | J14: 22.03.26 | K14: 3879 | L14: 0.07 | M14: SCB
A15: 11 | B15: TD1000106181_01 | C15: 08.09.24 | D15: 6063 | E15: 0 | F15: 0 | G15: =242-25 -> 217 | H15: =+E15+F15+G15 -> 217 | I15: =D15+H15 -> 6280 | J15: 08.09.27 | K15: 7466 | L15: 0.07 | M15: SCB
A16: 12 | B16: TD0000415677_02 | C16: 18.09.23 | D16: 7437 | E16: 0 | F16: =293-30 -> 263 | G16: =572-57 -> 515 | H16: =+E16+F16+G16 -> 778 | I16: =D16+H16 -> 8215 | J16: 18.09.25 | K16: 8586 | L16: 0.0725 | M16: SCB
A17: 13 | B17: TD1001583757 | C17: 28.03.25 | D17: 3345 | E17: 0 | F17: 0 | G17: =3-1 -> 2 | H17: =+E17+F17+G17 -> 2 | I17: =D17+H17 -> 3347 | J17: 28.07.26 | K17: 3693 | L17: 0.075 | M17: SCB
A18: 14 | B18: TD0000415611_01 | C18: 23.03.23 | D18: 10031 | E18: 17 | F18: =720-74 -> 646 | G18: =767-77 -> 690 | H18: =+E18+F18+G18 -> 1353 | I18: =D18+H18 -> 11384 | J18: 23.03.26 | K18: 12353 | L18: 0.07 | M18: SCB
A19: 15 | B19: TD0000415622_01 | C19: 20.03.24 | D19: 9301 | E19: 0 | F19: =23-2 -> 21 | G19: =717-73 -> 644 | H19: =+E19+F19+G19 -> 665 | I19: =D19+H19 -> 9966 | J19: 20.06.25 | K19: 10206 | L19: 0.075 | M19: SCB
A20: 16 | B20: TD1000772667 | C20: 29.03.23 | D20: 8435 | E20: 0 | F20: =578-58 -> 520 | G20: =666-65 -> 601 | H20: =+E20+F20+G20 -> 1121 | I20: =D20+H20 -> 9556 | J20: 29.04.25 | K20: 9739 | L20: 0.0725 | M20: SCB
A21: 17 | B21: TD1000717518 | C21: 23.03.23 | D21: 7984 | E21: 14 | F21: =573-57 -> 516 | G21: =610-61 -> 549 | H21: =+E21+F21+G21 -> 1079 | I21: =D21+H21 -> 9063 | J21: 23.03.26 | K21: 9832 | L21: 0.07 | M21: SCB
A22: 18 | B22: TD1001126336 | C22: 19.03.24 | D22: 8541 | F22: =22-3 -> 19 | G22: =659-66 -> 593 | H22: =+E22+F22+G22 -> 612 | I22: =D22+H22 -> 9153 | J22: 19.06.25 | K22: 9372 | L22: 0.075 | M22: SCB
A23: 19 | B23: TD1001583325 | C23: 28.03.25 | D23: 8879 | E23: 0 | F23: 0 | G23: =7-1 -> 6 | H23: =+E23+F23+G23 -> 6 | I23: =D23+H23 -> 8885 | J23: 28.07.26 | K23: 9803 | L23: 0.075 | M23: SCB
D24: =SUM(D5:D23) -> 174226 | E24: =SUM(E5:E23) -> 37 | F24: =SUM(F5:F23) -> 2230 | G24: =SUM(G5:G23) -> 6887 | H24: =SUM(H5:H23) -> 9154 | I24: =SUM(I5:I23) -> 183380 | K24: =SUM(K5:K23) -> 198381
B25: General Fund
A26: 20 | B26: 6605300013705_01 | C26: 02.02.24 | D26: 60918 | E26: 0 | F26: 717 | G26: 4657 | H26: =+E26+F26+G26 -> 5374 | I26: =D26+H26 -> 66292 | J26: 02.05.25 | K26: 66724 | L26: 0.0725 | M26: MDCC
A27: 21 | B27: TD1000784123 | C27: 09.05.23 | D27: 75000 | E27: 0 | F27: =4974-498 -> 4476 | G27: =5904-590 -> 5314 | H27: =+E27+F27+G27 -> 9790 | I27: =D27+H27 -> 84790 | J27: 09.05.25 | K27: 86590 | L27: 0.0725 | M27: SCB
A28: 22 | B28: TD1001126359 | C28: 19.03.24 | D28: 27466 | E28: 0 | F28: =72-7 -> 65 | G28: =2118-212 -> 1906 | H28: =+E28+F28+G28 -> 1971 | I28: =D28+H28 -> 29437 | J28: 19.06.25 | K28: 30139 | L28: 0.075 | M28: SCB
A29: 23 | B29: TD1001583375 | C29: 28.03.25 | D29: 2528 | E29: 0 | F29: 0 | G29: =2-0 -> 2 | H29: =+E29+F29+G29 -> 2 | I29: =D29+H29 -> 2530 | J29: 28.07.26 | K29: 2791 | L29: 0.075 | M29: SCB
D30: =SUM(D26:D29) -> 165912 | E30: =SUM(E26:E29) -> 0 | F30: =SUM(F26:F29) -> 5258 | G30: =SUM(G26:G29) -> 11879 | H30: =SUM(H26:H29) -> 17137 | I30: =SUM(I26:I29) -> 183049 | K30: =SUM(K26:K29) -> 186244
B31: Pest Control Fund
A32: 24 | B32: TD1001583788 | C32: 28.03.25 | D32: 10374 | E32: 0 | F32: 0 | G32: =8-1 -> 7 | H32: =+E32+F32+G32 -> 7 | I32: =D32+H32 -> 10381 | J32: 28.07.26 | K32: 11454 | L32: 0.075 | M32: SCB
A33: 25 | B33: 6605300016121_01 | C33: 27.11.24 | D33: 136606 | E33: 0 | F33: 0 | G33: 3640 | H33: =+E33+F33+G33 -> 3640 | I33: =D33+H33 -> 140246 | J33: 27.11.25 | K33: 147432 | L33: 0.077 | M33: MDCC
D34: =SUM(D32:D33) -> 146980 | E34: =SUM(E32:E33) -> 0 | F34: =SUM(F32:F33) -> 0 | G34: =SUM(G32:G33) -> 3647 | H34: =SUM(H32:H33) -> 3647 | I34: =SUM(I32:I33) -> 150627 | K34: =SUM(K32:K33) -> 158886
B35: Painting Fund
A36: 26 | B36: TD0000415696_02 | C36: 05.06.24 | D36: 22099 | E36: 0 | F36: 0 | G36: =1296-130 -> 1166 | H36: =+E36+F36+G36 -> 1166 | I36: =D36+H36 -> 23265 | J36: 05.06.27 | K36: 27214 | L36: 0.07 | M36: SCB
A37: 27 | B37: TD0000415681_02 | C37: 04.12.24 | D37: 10790 | E37: 0 | F37: 0 | G37: =247-25 -> 222 | H37: =+E37+F37+G37 -> 222 | I37: =D37+H37 -> 11012 | J37: 04.12.27 | K37: 13287 | L37: 0.07 | M37: SCB
A38: 28 | B38: TD1000721221 | C38: 27.03.23 | D38: 19030 | E38: 36 | F38: =1366-137 -> 1229 | G38: =1455-145 -> 1310 | H38: =+E38+F38+G38 -> 2575 | I38: =D38+H38 -> 21605 | J38: 27.03.26 | K38: 23434 | L38: 0.07 | M38: SCB
A39: 29 | B39: TD1000106202_01 | C39: 08.09.24 | D39: 18192 | E39: 0 | F39: 0 | G39: =727-73 -> 654 | H39: =+E39+F39+G39 -> 654 | I39: =D39+H39 -> 18846 | J39: 08.09.27 | K39: 22402 | L39: 0.07 | M39: SCB
A40: 30 | B40: TD1001126438 | C40: 17.03.24 | D40: 9530 | E40: 0 | F40: =29-3 -> 26 | G40: =735-71 -> 664 | H40: =+E40+F40+G40 -> 690 | I40: =D40+H40 -> 10220 | J40: 17.06.25 | K40: 10458 | L40: 0.075 | M40: SCB
A41: 31 | B41: TD1000717527 | C41: 23.03.23 | D41: 23956 | E41: 41 | F41: =1719-172 -> 1547 | G41: =1831-183 -> 1648 | H41: =+E41+F41+G41 -> 3236 | I41: =D41+H41 -> 27192 | J41: 23.03.26 | K41: 29500 | L41: 0.07 | M41: SCB
A42: 32 | B42: TD1001126341 | C42: 19.03.24 | D42: 23956 | E42: 0 | F42: =63-6 -> 57 | G42: =1847-185 -> 1662 | H42: =+E42+F42+G42 -> 1719 | I42: =D42+H42 -> 25675 | J42: 19.06.25 | K42: 26288 | L42: 0.075 | M42: SCB
A43: 33 | B43: TD1001583354 | C43: 28.03.25 | D43: 27774 | E43: 0 | F43: 0 | G43: =22-2 -> 20 | H43: =+E43+F43+G43 -> 20 | I43: =D43+H43 -> 27794 | J43: 28.07.26 | K43: 30665 | L43: 0.075 | M43: SCB
D44: =SUM(D36:D43) -> 155327 | E44: =SUM(E36:E43) -> 77 | F44: =SUM(F36:F43) -> 2859 | G44: =SUM(G36:G43) -> 7346 | H44: =SUM(H36:H43) -> 10282 | I44: =SUM(I36:I43) -> 165609 | K44: =SUM(K36:K43) -> 183248
B45: Share Capital
A46: 34 | B46: TD0000400904_02 | C46: 21.01.24 | D46: 9000 | E46: 0 | F46: 0 | G46: 0 | H46: =+E46+F46+G46 -> 0 | I46: =D46+H46 -> 9000 | J46: 21.01.28 | K46: 9000 | L46: 0.07 | M46: SCB
A47: 35 | B47: TD1000225977_01 | C47: 24.01.24 | D47: 9000 | E47: 0 | F47: 0 | G47: 0 | H47: =+E47+F47+G47 -> 0 | I47: =D47+H47 -> 9000 | J47: 24.01.28 | K47: 9000 | L47: 0.07 | M47: SCB
D48: =SUM(D46:D47) -> 18000 | E48: =SUM(E46:E47) -> 0 | F48: =SUM(F46:F47) -> 0 | G48: =SUM(G46:G47) -> 0 | H48: =SUM(H46:H47) -> 0 | I48: =SUM(I46:I47) -> 18000 | K48: =SUM(K46:K47) -> 18000
B49: Common Amenity Fund
A50: 36 | B50: TD1000106230_01 | C50: 08.09.24 | D50: 37901 | E50: 0 | F50: 0 | G50: =1514-151 -> 1363 | H50: =+E50+F50+G50 -> 1363 | I50: =D50+H50 -> 39264 | J50: 08.09.27 | K50: 46673 | L50: 0.07 | M50: SCB
A51: 37 | B51: TD0000415675_02 | C51: 30.10.23 | D51: 50515 | E51: 0 | F51: =1524-152 -> 1372 | G51: =3773-377 -> 3396 | H51: =+E51+F51+G51 -> 4768 | I51: =D51+H51 -> 55283 | J51: 30.10.25 | K51: 58150 | L51: 0.071 | M51: SCB
A52: 38 | B52: TD1001101183 | C52: 24.02.24 | D52: 38882 | E52: 0 | F52: =306-31 -> 275 | G52: =3012-302 -> 2710 | H52: =+E52+F52+G52 -> 2985 | I52: =D52+H52 -> 41867 | J52: 24.05.25 | K52: 42666 | L52: 0.075 | M52: SCB
D53: =SUM(D50:D52) -> 127298 | E53: =SUM(E50:E52) -> 0 | F53: =SUM(F50:F52) -> 1647 | G53: =SUM(G50:G52) -> 7469 | H53: =SUM(H50:H52) -> 9116 | I53: =SUM(I50:I52) -> 136414 | K53: =SUM(K50:K52) -> 147489
B54: Legal Fund
A55: 39 | B55: TD0000415698_02 | C55: 22.06.24 | D55: 8940 | E55: 0 | F55: 0 | G55: =494-51 -> 443 | H55: =+E55+F55+G55 -> 443 | I55: =D55+H55 -> 9383 | J55: 22.06.27 | K55: 11009 | L55: 0.07 | M55: SCB
A56: 40 | B56: TD1000182911_01 | C56: 04.12.24 | D56: 28279 | E56: 0 | F56: 0 | G56: =646-65 -> 581 | H56: =+E56+F56+G56 -> 581 | I56: =D56+H56 -> 28860 | J56: 04.12.27 | K56: 34824 | L56: 0.07 | M56: SCB
A57: 41 | B57: TD1000106216_01 | C57: 08.09.24 | D57: 16371 | E57: 0 | F57: 0 | G57: =654-65 -> 589 | H57: =+E57+F57+G57 -> 589 | I57: =D57+H57 -> 16960 | J57: 08.09.27 | K57: 20160 | L57: 0.07 | M57: SCB
A58: 42 | B58: TD1000290759_02 | C58: 17.05.24 | D58: 140920 | E58: 0 | F58: 0 | G58: =8794-879 -> 7915 | H58: =+E58+F58+G58 -> 7915 | I58: =D58+H58 -> 148835 | J58: 17.06.25 | K58: 151944 | L58: 0.07 | M58: SCB
A59: 43 | B59: TD1001126443 | C59: 17.03.24 | D59: 8580 | E59: 0 | F59: =26-2 -> 24 | G59: =662-66 -> 596 | H59: =+E59+F59+G59 -> 620 | I59: =D59+H59 -> 9200 | J59: 17.06.25 | K59: 9415 | L59: 0.075 | M59: SCB
A60: 44 | B60: TD1000717533_01 | C60: 23.03.25 | D60: 24590 | E60: 0 | F60: 0 | G60: =45-4 -> 41 | H60: =+E60+F60+G60 -> 41 | I60: =D60+H60 -> 24631 | J60: 23.07.26 | K60: 27150 | L60: 0.075 | M60: SCB
A61: 45 | B61: TD1001126389 | C61: 19.03.24 | D61: 21600 | E61: 0 | F61: =57-6 -> 51 | G61: =1665-166 -> 1499 | H61: =+E61+F61+G61 -> 1550 | I61: =D61+H61 -> 23150 | J61: 19.06.25 | K61: 23702 | L61: 0.075 | M61: SCB
D62: =SUM(D55:D61) -> 249280 | E62: =SUM(E55:E61) -> 0 | F62: =SUM(F55:F61) -> 75 | G62: =SUM(G55:G61) -> 11664 | H62: =SUM(H55:H61) -> 11739 | I62: =SUM(I55:I61) -> 261019 | K62: =SUM(K55:K61) -> 278204
B63: Leave and Licence Deposit
A64: 46 | B64: TD1000295859 | C64: 31.03.24 | D64: 8000 | E64: 0 | F64: 0 | G64: 0 | H64: =+E64+F64+G64 -> 0 | I64: =D64+H64 -> 8000 | J64: 30.06.25 | K64: 8000 | L64: 0.075 | M64: SCB
A65: 47 | B65: TD1000346250_01 | C65: 23.05.24 | D65: 4000 | E65: 0 | F65: 0 | G65: 0 | H65: =+E65+F65+G65 -> 0 | I65: =D65+H65 -> 4000 | J65: 23.05.26 | K65: 4000 | L65: 0.07 | M65: SCB
A66: 48 | B66: TD1000772659 | C66: 29.04.23 | D66: 2000 | E66: 0 | F66: 0 | G66: 0 | H66: =+E66+F66+G66 -> 0 | I66: =D66+H66 -> 2000 | J66: 29.04.25 | K66: 2000 | L66: 0.0725 | M66: SCB
A67: 49 | B67: TD1000717591_01 | C67: 23.03.25 | D67: 6000 | E67: 0 | F67: 0 | G67: 0 | H67: =+E67+F67+G67 -> 0 | I67: =D67+H67 -> 6000 | J67: 23.07.26 | K67: 6000 | L67: 0.075 | M67: SCB
D68: =SUM(D64:D67) -> 20000 | E68: =SUM(E64:E67) -> 0 | F68: =SUM(F64:F67) -> 0 | G68: =SUM(G64:G67) -> 0 | H68: =SUM(H64:H67) -> 0 | I68: =SUM(I64:I67) -> 20000 | K68: =SUM(K64:K67) -> 20000
B69: Redevelopment Fund
A70: 50 | B70: TD1000717573_01 | C70: 23.03.25 | D70: 49178 | E70: 0 | F70: 0 | G70: =89-9 -> 80 | H70: =+E70+F70+G70 -> 80 | I70: =D70+H70 -> 49258 | J70: 23.07.26 | K70: 54297 | L70: 0.075 | M70: SCB
A71: 51 | B71: TD1001126321 | C71: 19.03.24 | D71: 86400 | F71: =226-22 -> 204 | G71: =6662-667 -> 5995 | H71: =+E71+F71+G71 -> 6199 | I71: =D71+H71 -> 92599 | J71: 19.06.25 | K71: 94809 | L71: 0.075 | M71: SCB
D72: =SUM(D70:D71) -> 135578 | E72: =SUM(E70:E71) -> 0 | F72: =SUM(F70:F71) -> 204 | G72: =SUM(G70:G71) -> 6075 | H72: =SUM(H70:H71) -> 6279 | I72: =SUM(I70:I71) -> 141857 | K72: =SUM(K70:K71) -> 149106
B73: Education & Training Fund
A74: 52 | B74: TD1000717580_01 | C74: 23.03.25 | D74: 26753 | E74: 0 | F74: 0 | G74: =49-4 -> 45 | H74: =+E74+F74+G74 -> 45 | I74: =D74+H74 -> 26798 | J74: 23.07.26 | K74: 29538 | L74: 0.075 | M74: SCB
A75: 53 | B75: TD1001126346 | C75: 19.03.24 | D75: 4320 | E75: 0 | F75: =11-1 -> 10 | G75: =333-33 -> 300 | H75: =+E75+F75+G75 -> 310 | I75: =D75+H75 -> 4630 | J75: 19.06.25 | K75: 4740 | L75: 0.075 | M75: SCB
A76: 54 | B76: TD1001583365 | C76: 28.03.25 | D76: 4496 | E76: 0 | F76: 0 | G76: =4-1 -> 3 | H76: =+E76+F76+G76 -> 3 | I76: =D76+H76 -> 4499 | J76: 28.07.26 | K76: 4964 | L76: 0.075 | M76: SCB
D77: =SUM(D74:D76) -> 35569 | E77: =SUM(E74:E76) -> 0 | F77: =SUM(F74:F76) -> 10 | G77: =SUM(G74:G76) -> 348 | H77: =SUM(H74:H76) -> 358 | I77: =SUM(I74:I76) -> 35927 | K77: =SUM(K74:K76) -> 39242
B79: Grand Total | D79: =D24+D30+D34+D44+D48+D53+D62+D68+D72+D77 -> 1228170 | E79: =E24+E30+E34+E44+E48+E53+E62+E68+E72+E77 -> 114 | F79: =F24+F30+F34+F44+F48+F53+F62+F68+F72+F77 -> 12283 | G79: =G24+G30+G34+G44+G48+G53+G62+G68+G72+G77 -> 55315 | H79: =H24+H30+H34+H44+H48+H53+H62+H68+H72+H77 -> 67712 | I79: =I24+I30+I34+I44+I48+I53+I62+I68+I72+I77 -> 1295882 | K79: =K24+K30+K34+K44+K48+K53+K62+K68+K72+K77 -> 1378800

Sheet FA Sch_3
A1: =BS!A1 -> DIAGO CO-OPERATIVE HOUSING SOCIETY
A2: Schedule 3 - Details of Fixed Assets as on 31st March 2025
A3: Particulars | B3: Rate % | C3: Opening W.D.V as on 01.04.2024 | D3: Additions during the year before 30.09.2024 | E3: Additions during the year after 30.09.2024 | F3: Gross Block (at cost) as on 31.03.2025 | G3: Depreciation for the year | H3: Closing W.D.V as on 31.03.2025
A4: Land and Building | B4: 0 | C4: 45000 | D4: 0 | E4: 0 | F4: =+C4+D4+E4 -> 45000 | G4: =ROUND((C4*B4)+(D4*B4)+(E4*B4/2),0) -> 0 | H4: =F4-G4 -> 45000
A6: Building | B6: 0 | C6: 2182750 | D6: 0 | E6: 0 | F6: =+C6+D6+E6 -> 2182750 | G6: =ROUND((C6*B6)+(D6*B6)+(E6*B6/2),0) -> 0 | H6: =F6-G6 -> 2182750
A8: Office Premises | B8: 0 | C8: 33797 | D8: 0 | E8: 0 | F8: =+C8+D8+E8 -> 33797 | G8: =ROUND((C8*B8)+(D8*B8)+(E8*B8/2),0) -> 0 | H8: =F8-G8 -> 33797
A10: Furniture and Fixture | B10: 0.1 | C10: 3043 | D10: 0 | E10: 0 | F10: =+C10+D10+E10 -> 3043 | G10: =ROUND((C10*B10)+(D10*B10)+(E10*B10/2),0) -> 304 | H10: =F10-G10 -> 2739
A12: Water Pump | B12: 0.15 | C12: 2999 | D12: 0 | E12: 0 | F12: =+C12+D12+E12 -> 2999 | G12: =ROUND((C12*B12)+(D12*B12)+(E12*B12/2),0) -> 450 | H12: =F12-G12 -> 2549
A14: CCTV | B14: 0.15 | C14: 23735 | D14: 0 | E14: 0 | F14: =+C14+D14+E14 -> 23735 | G14: =ROUND((C14*B14)+(D14*B14)+(E14*B14/2),0) -> 3560 | H14: =F14-G14 -> 20175
A15: Total | C15: =SUM(C4:C14) -> 2291324 | D15: =SUM(D4:D14) -> 0 | E15: =SUM(E4:E14) -> 0 | F15: =SUM(F4:F14) -> 2291324 | G15: =SUM(G4:G14) -> 4314 | H15: =SUM(H4:H14) -> 2287010

Sheet Advance n Refundable Sch 4&5
A1: =BS!A1 -> DIAGO CO-OPERATIVE HOUSING SOCIETY
A2: Schedule 4: Member's Due as on 31st March 2025 | G2: Schedule 7: Payables as on 31st March 2025
A3: Sr | B3: Wing | C3: Flat | D3: Name of Member | E3: Amount | G3: Sl.No | H3: Vendor | I3: Expense Head | J3: Amt
A4: 1 | B4: A | C4: 002 | D4: Ms. Valentine D'Souza | E4: 6912 | G4: 1 | H4: Ecotech Exteriror & Interior Co. | I4: Major Repairs | J4: 5000
A5: 2 | B5: A | C5: 401 | D5: Mr. Jose Baretto | E5: 9 | G5: 2 | H5: Tata Power | I5: Electricity Expenses | J5: 3394
A6: Total | E6: =SUM(E4:E5) -> 6921 | G6: 3 | H6: Jiya Fire Protection | I6: Fire Extinguishers | J6: 1300
G7: Total | J7: =SUM(J4:J6) -> 9694 | K7: A
A8: Schedule 5: Advance from Members as on 31st March 2025
A9: Sr | B9: Wing | C9: Flat | D9: Name of Member | E9: Amount | G9: Sl.No | H9: Account Head | I9: Description | J9: Amt
A10: 1 | B10: A | C10: 102 | D10: Mrs. Rita D'Souza | E10: 8607 | G10: 1 | H10: Professional Fees | I10: Uploading FY 23-24 & FY 24-25 | J10: =1770*2 -> 3540
A11: 2 | B11: A | C11: 103 | D11: Mrs. Maria Pereira | E11: 150 | G11: 2 | H11: Professional Fees | I11: I. Tax Returns FY 24-25 | J11: 1770
A12: 3 | B12: A | C12: 203 | D12: Mr. Robert D'Souza | E12: 83 | G12: Total | J12: =SUM(J9:J11) -> 5310 | K12: B
A13: 4 | B13: A | C13: 403 | D13: Mrs. Dorothy Fernandes | E13: 3994
A14: 5 | B14: B | C14: 102 | D14: Mrs. Teresa Lobo | E14: 6401 | I14: Total | J14: =J7+J12 -> 15004 | K14: A+B
A15: 6 | B15: B | C15: 201 | D15: Mr. Egyptcio Coelho | E15: 597
A16: 7 | B16: B | C16: 303 | D16: Mr. Sydney Joe Lobo | E16: 11389
A17: 8 | B17: B | C17: 304 | D17: Mrs. Jasmine Fernandes | E17: 600
A18: 9 | B18: B | C18: 402 | D18: Mr. Francis Pais | E18: 109
A19: Total | E19: =SUM(E10:E18) -> 31930
A21: Schedule 6: Refundable Deposit as on 31st March 2025
A22: Sr | B22: Wing | C22: Flat | D22: Name of Member | E22: Amount
A23: 1 | B23: A | C23: 101 | D23: Mr. Simon P. Pereira & Mr. Anthony J. Pereira | E23: 2000
A24: 2 | B24: A | C24: 102 | D24: Ms. Rita H. D'Souza | E24: 2000
A25: 3 | B25: A | C25: 203 | D25: Mr. Robert D'Souza | E25: 2000
A26: 4 | B26: A | C26: 303 | D26: Mrs. Chinnamma Joseph | E26: 2000
A27: 5 | B27: A | C27: 403 | D27: Mrs. Dorothy Fernandes | E27: 2000
A28: 6 | B28: B | C28: 1 | D28: Mr. Lovette Remedios | E28: 2000
A29: 7 | B29: B | C29: 4 | D29: Mr. Cedric Rebello | E29: 2000
A30: 8 | B30: B | C30: 301 | D30: Mrs. Fatima A. Mascarenhas | E30: 2000
A31: 9 | B31: B | C31: 303 | D31: Mr. Sydney Joe Lobo | E31: 2000
A32: 10 | B32: C | C32: 1 | D32: Mr. Nigel P. A. Rodrigues | E32: 2000
A33: Total | E33: =SUM(E23:E32) -> 20000

Sheet BRS
A1: =BS!A1 -> DIAGO CO-OPERATIVE HOUSING SOCIETY
A2: Saraswat Bank Reconciliation Statement as on 31st March 2025
C3: Amount
A4: Balance as per System (Book Balance) | C4: 257877.75 | F4: Cheq. # | G4: Date | H4: Cleared | I4: Vendor | J4: Amount
A5: Add: | B5: Cheque issued but not cleared | C5: 1250 | F5: 187353 | G5: 26.03.25 | H5: 03.04.25 | I5: Prakash Electric | J5: 1250
A8: Balance as per bank confirmation statement | C8: =C4+C5-C6 -> 259127.75
A11: MDCC Bank Reconciliation Statement as on 31st March 2025
C12: Amount
A13: Balance as per System (Book Balance) | C13: 2777.86
A17: Balance as per bank confirmation statement | C17: =C13+C14-C15 -> 2777.86
A20: Bank of Baroda Reconciliation Statement as on 31st March 2025
C21: Amount
A22: Balance as per System (Book Balance) | C22: 3441.85
A26: Balance as per bank confirmation statement | C26: =C22+C23-C24 -> 3441.85

Sheet Workings
B2: Note: Workings Page is not to be printed
E3: 0 | F3: 12319 | G3: 5000
B4: Water Charges: | E4: PNK0790005 | F4: PNH3790004 | G4: PNG7340003 | L4: PNK0790005 | M4: PNH3790004 | N4: PNG7340003
B5: 45661 | C5: 46024 | D5: =+C5-B5+1 -> 364 | E5: =6699+6733+6732+6718 -> 26882 | F5: =11169+11193+11247+11379 -> 44988 | G5: =1416+1447+1469+1526 -> 5858 | I5: 46024 | J5: 46114 | K5: =31-2+28+31+2 -> 90 | L5: 6548 | M5: 11212 | N5: 1438
B6: 46025 | C6: 46112 | D6: =31-2+28+31 -> 88 | E6: =L6 -> 6402 | F6: =M6 -> 10963 | G6: =N6 -> 1406 | H6: Provision | I6: 46025 | J6: 46112 | K6: =31-2+28+31 -> 88 | L6: =ROUND($K$6*L5/$K$5,0) -> 6402 | M6: =ROUND($K$6*M5/$K$5,0) -> 10963 | N6: =ROUND($K$6*N5/$K$5,0) -> 1406
B7: =C5 -> 46024 | C7: 45747 | D7: =SUM(D5:D6) -> 452 | E7: =SUM(E5:E6) -> 33284 | F7: =SUM(F5:F6) -> 55951 | G7: =SUM(G5:G6) -> 7264 | H7: =SUM(E7:G7) -> 96499
B10: Pest Control:
B11: 45505 | C11: 45869 | D11: =C11-B11+1 -> 365 | E11: 4400
B12: =B11 -> 45505 | C12: 45747 | D12: =C12-B12+1 -> 243 | E12: =ROUND(E11*D12/D11,0) -> 2929
B13: 45748 | C13: =C11 -> 45869 | D13: =C13-B13+1 -> 122 | E13: =ROUND(E11*D13/D11,0) -> 1471 | F13: Prepaid
B15: Insurance
B16: 45724 | C16: 46088 | D16: =C16-B16+1 -> 365 | E16: 7781
B17: =B16 -> 45724 | C17: 45747 | D17: =C17-B17+1 -> 24 | E17: =ROUND(E16*D17/D16,0) -> 512
B18: 45748 | C18: =C16 -> 46088 | D18: =C18-B18+1 -> 341 | E18: =ROUND(E16*D18/D16,0) -> 7269 | F18: Prepaid
B20: CA Amish Sangoi
B21: Rs.3,600 provision for FY 24-25

Sheet Interest Workings
A1: Note: Workings Page is not to be printed
A2: Journal No. | B2: Posted Date | C2: Comments | D2: Credit | F2: Fund | H2: LF | I2: 17335
A3: JE-2024-0000123 | B3: 17-05-2024 | C3: Being FD TD1000290759 01 renewed on maturity - LF SCB | D3: 1239 | F3: LF | H3: SF | I3: 10936
A4: JE-2024-0000001 | B4: 23-05-2024 | C4: Being recd int. on FD TD1000346250 LL SCB | D4: 32 | F4: LL | H4: CAF | I4: 9159
A5: JE-2024-0000105 | B5: 05-06-2024 | C5: Being FD TD0000415687 01 renewed on maturity - SF SCB | D5: 69 | F5: SF | H5: PC | I5: 10495
A6: JE-2024-0000114 | B6: 05-06-2024 | C6: Being FD TD0000415696 01 renewed on maturity - PF SCB | D6: 206 | F6: PF | H6: GF | I6: 12681
A7: JE-2024-0000107 | B7: 22-06-2024 | C7: Being FD TD0000415690 01 renewed on maturity - SF SCB | D7: 225 | F7: SF | H7: PF | I7: 9156
A8: JE-2024-0000121 | B8: 22-06-2024 | C8: Being FD TD0000415698 01 renewed on maturity - LF SCB | D8: 104 | F8: LF | H8: ETF | I8: 2205
A9: JE-2024-0000106 | B9: 25-06-2024 | C9: Being FD TD0000415693 01 renewed on maturity - SF SCB | D9: 88 | F9: SF | H9: RDF | I9: 10095
A10: JE-2024-0000012 | B10: 30-06-2024 | C10: Being Interest Received on Fixed Deposit TD0000400904 SCB | D10: 119 | F10: SC | H10: LL | I10: 1454
A11: JE-2024-0000013 | B11: 30-06-2024 | C11: Being Interest Received on Fixed Deposit TD1000225977 SCB | D11: 119 | F11: SC | H11: SC | I11: 1013
A12: JE-2024-0000014 | B12: 30-06-2024 | C12: Being Interest Received on Fixed Deposit TD1000295859 LL - SCB | D12: 152 | F12: LL
A13: JE-2024-0000015 | B13: 30-06-2024 | C13: Being Interest Received on Fixed Deposit TD1000346250 LL - SCB | D13: 30 | F13: LL | I13: =SUM(I2:I12) -> 84529
A14: JE-2024-0000016 | B14: 30-06-2024 | C14: Being Interest Received on Fixed Deposit TD1000717591 LL - SCB | D14: 108 | F14: LL | I14: =-I10-I11 -> -2467 | J14: LL + SC
A15: JE-2024-0000017 | B15: 30-06-2024 | C15: being interest on fixed deposit TD 1000772659 LL - SCB | D15: 36 | F15: LL | I15: =SUM(I13:I14) -> 82062
A16: JE-2024-0000111 | B16: 08-09-2024 | C16: Being FD TD1000106181 renewed on maturity - SF SCB | D16: 137 | F16: SF
A17: JE-2024-0000116 | B17: 08-09-2024 | C17: Being FD TD1000106202 renewed on maturity - PF SCB | D17: 413 | F17: PF
A18: JE-2024-0000117 | B18: 08-09-2024 | C18: Being FD TD1000106230 renewed on maturity - CAF SCB | D18: 860 | F18: CAF
A19: JE-2024-0000120 | B19: 08-09-2024 | C19: Being FD TD1000106216 renewed on maturity - LF SCB | D19: 371 | F19: LF
A20: JE-2024-0000019 | B20: 30-09-2024 | C20: being interest on fixed deposit TD 0000400904 SCB | D20: 119 | F20: SC
A21: JE-2024-0000021 | B21: 30-09-2024 | C21: being interest on fixed deposit TD 1000717591 LL - SCB | D21: 109 | F21: LL
A22: JE-2024-0000022 | B22: 30-09-2024 | C22: being interest on fixed deposit TD 1000346250 LL - SCB | D22: 70 | F22: LL
A23: JE-2024-0000023 | B23: 30-09-2024 | C23: being interest on fixed deposit TD 1000772659 LL - SCB | D23: 36 | F23: LL
A24: JE-2024-0000024 | B24: 30-09-2024 | C24: being interest on fixed deposit TD000225977 SCB | D24: 119 | F24: SC
A25: JE-2024-0000025 | B25: 30-09-2024 | C25: Being Interest Received on Fixed Deposit TD1000295859 LL - SCB | D25: 150 | F25: LL
A26: JE-2024-0000150 | B26: 27-11-2024 | C26: Being FD 6605300016121 01 renewed on maturity PC - MDCC | D26: 6282 | F26: PC
A27: JE-2024-0000104 | B27: 04-12-2024 | C27: Being FD TD1000182883 renewed on maturity n new FD made - SF SCB | D27: 462 | F27: SF
... A104: JE-2024-0000186 | B104: 31-03-2025 | C104: Being accrued interest recd on FD TD1001583788 PC - SCB | D104: 8 | F104: PC
D105: =SUM(D3:D104) -> 84529
C106: Saraswat | D106: 69950
C107: MDCC | D107: 14579

Sheet FD working Sheet
A1: Note: Workings Page is not to be printed
A2: =BS!A1 -> DIAGO CO-OPERATIVE HOUSING SOCIETY
A3: Schedule 2 - Details of Fixed Deposits as on 31st March 2025 | O3: to work on this sheet
A4: Sr. | B4: Certificate No. | C4: Date | D4: Amount Invested | E4: Accrued Int 21-22 | F4: Accrued Int 22-23 | G4: Accrued Int 23-24 | H4: Total Accrued Int | I4: Total | J4: Maturity Date | K4: Maturity Value | L4: Interest % | M4: Bank | N4: Acc | O4: Int | P4: TDS | Q4: New FD | R4: Acc | S4: A/c #
B5: Sinking Fund
A6: 1 | B6: TD1000182883 | C6: 04.12.21 | D6: 11366 | E6: 197 | F6: 625 | G6: =657-67 -> 590 | H6: =+E6+F6+G6 -> 1412 | I6: =D6+H6 -> 12778 | J6: 04.12.24 | K6: 13311 | L6: 0.053 | M6: SCB | N6: =O6-P6 -> 416 | O6: 462 | P6: 46 | Q6: 13194 | R6: =H6 -> 1412 | S6: 109299
A7: 2 | B7: TD1001116944 | C7: 08.03.24 | D7: 6537 | E7: 0 | F7: 0 | G7: =32-3 -> 29 | H7: =+E7+F7+G7 -> 29 | I7: =D7+H7 -> 6566 | J7: 08.06.25 | K7: 7173 | L7: 0.075 | M7: SCB | N7: =O7-P7 -> 454 | O7: 505 | P7: 51
A8: 3 | B8: TD0000415625_01 | C8: 20.03.24 | D8: 5671 | E8: 0 | F8: 0 | G8: =14-2 -> 12 | H8: =+E8+F8+G8 -> 12 | I8: =D8+H8 -> 5683 | J8: 20.06.25 | K8: 6223 | L8: 0.075 | M8: SCB | N8: =O8-P8 -> 393 | O8: 437 | P8: 44
A9: 4 | B9: TD0000415687_01 | C9: 05.06.21 | D9: 6328 | E9: 280 | F9: 357 | G9: =376-38 -> 338 | H9: =+E9+F9+G9 -> 975 | I9: =D9+H9 -> 7303 | J9: 05.06.24 | K9: 7411 | L9: 0.053 | M9: SCB | N9: =O9-P9 -> 63 | O9: 69 | P9: 6 | Q9: 7366 | R9: =H9 -> 975 | S9: 109300
A10: 5 | B10: TD0000415693_01 | C10: 25.06.21 | D10: 6257 | E10: 259 | F10: 352 | G10: =370-36 -> 334 | H10: =+E10+F10+G10 -> 945 | I10: =D10+H10 -> 7202 | J10: 25.06.24 | K10: 7328 | L10: 0.053 | M10: SCB | N10: =O10-P10 -> 79 | O10: 88 | P10: 9 | Q10: 7281 | R10: =H10 -> 945 | S10: 109301
A11: 6 | B11: TD0000415690_01 | C11: 22.06.21 | D11: 16557 | E11: 691 | F11: 933 | G11: =981-98 -> 883 | H11: =+E11+F11+G11 -> 2507 | I11: =D11+H11 -> 19064 | J11: 22.06.24 | K11: 19390 | L11: 0.053 | M11: SCB | N11: =O11-P11 -> 202 | O11: 225 | P11: 23 | Q11: 19266 | R11: =H11 -> 2507 | S11: 109302
A12: 7 | B12: TD0000415658 | C12: 14.03.22 | D12: 9901 | E12: 25 | F12: 537 | G12: =565-56 -> 509 | H12: =+E12+F12+G12 -> 1071 | I12: =D12+H12 -> 10972 | J12: 14.03.25 | K12: 11595 | L12: 0.053 | M12: SCB | N12: =O12-P12 -> 506 | O12: 562 | P12: 56 | Q12: 11478 | R12: =H12 -> 1071 | S12: 109303
A13: 8 | B13: TD0000415651_01 | C13: 14.03.22 | D13: 22910 | E13: 59 | F13: 1242 | G13: =1306-130 -> 1176 | H13: =+E13+F13+G13 -> 2477 | I13: =D13+H13 -> 25387 | J13: 14.03.25 | K13: 26830 | L13: 0.053 | M13: SCB | N13: =O13-P13 -> 1171 | O13: 1301 | P13: 130 | Q13: 26558 | R13: =H13 -> 2477 | S13: 109304
A14: 9 | B14: TD0000415655 | C14: 28.03.22 | D14: 3121 | E14: 2 | F14: 183 | G14: =194-19 -> 175 | H14: =+E14+F14+G14 -> 360 | I14: =D14+H14 -> 3481 | J14: 28.03.25 | K14: 3704 | L14: 0.0575 | M14: SCB | N14: =O14-P14 -> 182 | O14: 202 | P14: 20 | Q14: 3663 | R14: =H14 -> 360 | S14: 109305
A15: 10 | B15: TD1000721256 | C15: 22.03.23 | D15: 3150 | E15: 0 | F15: 6 | G15: =226-22 -> 204 | H15: =+E15+F15+G15 -> 210 | I15: =D15+H15 -> 3360 | J15: 22.03.26 | K15: 3879 | L15: 0.07 | M15: SCB | N15: =O15-P15 -> 217 | O15: 241 | P15: 24
A16: 11 | B16: TD1000106181 | C16: 08.09.21 | D16: 5217 | E16: 157 | F16: 291 | G16: =306-31 -> 275 | H16: =+E16+F16+G16 -> 723 | I16: =D16+H16 -> 5940 | J16: 08.09.24 | K16: 6110 | L16: 0.053 | M16: SCB | N16: =O16-P16 -> 123 | O16: 137 | P16: 14 | Q16: 6063 | R16: =H16 -> 723 | S16: 109306
A17: 12 | B17: TD0000415677_02 | C17: 18.09.23 | D17: 7437 | E17: 0 | F17: 0 | G17: =293-30 -> 263 | H17: =+E17+F17+G17 -> 263 | I17: =D17+H17 -> 7700 | J17: 18.09.25 | K17: 8586 | L17: 0.0725 | M17: SCB | N17: =O17-P17 -> 515 | O17: 572 | P17: 57
A18: 13 | B18: TD1000290489 | C18: 17.03.21 | D18: 2847 | E18: 7 | F18: 167 | G18: =177-18 -> 159 | H18: =+E18+F18+G18 -> 333 | I18: =D18+H18 -> 3180 | J18: 17.03.25 | K18: 3379 | L18: 0.0575 | M18: SCB | N18: =O18-P18 -> 162 | O18: 179 | P18: 17 | Q18: 3342 | R18: =H18 -> 333 | S18: 109307
A19: 14 | B19: TD0000415611_01 | C19: 23.03.23 | D19: 10031 | E19: 0 | F19: 17 | G19: =720-74 -> 646 | H19: =+E19+F19+G19 -> 663 | I19: =D19+H19 -> 10694 | J19: 23.03.26 | K19: 12353 | L19: 0.07 | M19: SCB | N19: =O19-P19 -> 690 | O19: 767 | P19: 77
A20: 15 | B20: TD0000415622_01 | C20: 20.03.24 | D20: 9301 | E20: 0 | F20: 0 | G20: =23-2 -> 21 | H20: =+E20+F20+G20 -> 21 | I20: =D20+H20 -> 9322 | J20: 20.06.25 | K20: 10206 | L20: 0.075 | M20: SCB | N20: =O20-P20 -> 644 | O20: 717 | P20: 73
A21: 16 | B21: TD1000772667 | C21: 29.03.23 | D21: 8435 | E21: 0 | F21: 0 | G21: =578-58 -> 520 | H21: =+E21+F21+G21 -> 520 | I21: =D21+H21 -> 8955 | J21: 29.04.25 | K21: 9739 | L21: 0.0725 | M21: SCB | N21: =O21-P21 -> 601 | O21: 666 | P21: 65
A22: 17 | B22: TD1000717518 | C22: 23.03.23 | D22: 7984 | E22: 0 | F22: 14 | G22: =573-57 -> 516 | H22: =+E22+F22+G22 -> 530 | I22: =D22+H22 -> 8514 | J22: 23.03.26 | K22: 9832 | L22: 0.07 | M22: SCB | N22: =O22-P22 -> 549 | O22: 610 | P22: 61
A23: 18 | B23: TD1001126336 | C23: 19.03.24 | D23: 8541 | G23: =22-3 -> 19 | H23: =+E23+F23+G23 -> 19 | I23: =D23+H23 -> 8560 | J23: 19.06.25 | K23: 9372 | L23: 0.075 | M23: SCB | N23: =O23-P23 -> 593 | O23: 659 | P23: 66
D24: =SUM(D6:D23) -> 151591 | E24: =SUM(E6:E23) -> 1677 | F24: =SUM(F6:F23) -> 4724 | G24: =SUM(G6:G23) -> 6669 | H24: =SUM(H6:H23) -> 13070 | I24: =SUM(I6:I23) -> 164661 | K24: =SUM(K6:K23) -> 176421
B25: General Fund
A26: 19 | B26: 6605300013705_01 | C26: 02.02.24 | D26: 60918 | E26: 0 | F26: 0 | G26: 717 | H26: =+E26+F26+G26 -> 717 | I26: =D26+H26 -> 61635 | J26: 02.05.25 | K26: 66724 | L26: 0.0725 | M26: MDCC
A27: 20 | B27: TD1000784123 | C27: 09.05.23 | D27: 75000 | E27: 0 | F27: 0 | G27: =4974-498 -> 4476 | H27: =+E27+F27+G27 -> 4476 | I27: =D27+H27 -> 79476 | J27: 09.05.25 | K27: 86590 | L27: 0.0725 | M27: SCB | N27: =O27-P27 -> 5314 | O27: 5904 | P27: 590
A28: 21 | B28: TD1001126359 | C28: 19.03.24 | D28: 27466 | E28: 0 | F28: 0 | G28: =72-7 -> 65 | H28: =+E28+F28+G28 -> 65 | I28: =D28+H28 -> 27531 | J28: 19.06.25 | K28: 30139 | L28: 0.075 | M28: SCB | N28: =O28-P28 -> 1906 | O28: 2118 | P28: 212
D29: =SUM(D26:D28) -> 163384 | E29: =SUM(E26:E28) -> 0 | F29: =SUM(F26:F28) -> 0 | G29: =SUM(G26:G28) -> 5258 | H29: =SUM(H26:H28) -> 5258 | I29: =SUM(I26:I28) -> 168642 | K29: =SUM(K26:K28) -> 183453
B30: Pest Control Fund
A31: 22 | B31: TD1000290468 | C31: 17.03.22 | D31: 8831 | E31: 20 | F31: 521 | G31: =549-55 -> 494 | H31: =+E31+F31+G31 -> 1035 | I31: =D31+H31 -> 9866 | J31: 17.03.25 | K31: 10481 | L31: 0.0575 | M31: SCB | N31: =O31-P31 -> 498 | O31: 554 | P31: 56 | Q31: 10364 | R31: =H31 -> 1035 | S31: 109308 | T31: New FD | U31: Dr | V31: =W36-V32 -> 37901
A32: 23 | B32: 6605300016121_01 | C32: 27.11.23 | D32: 127135 | E32: 0 | F32: 0 | G32: 3189 | H32: =+E32+F32+G32 -> 3189 | I32: =D32+H32 -> 130324 | J32: 27.11.24 | K32: 136606 | L32: 0.0725 | M32: MDCC | O32: 6282 | Q32: 136606 | R32: =H32 -> 3189 | S32: 109322 | T32: TDS | U32: Dr | V32: 86
D33: =SUM(D31:D32) -> 135966 | E33: =SUM(E31:E32) -> 20 | F33: =SUM(F31:F32) -> 521 | G33: =SUM(G31:G32) -> 3683 | H33: =SUM(H31:H32) -> 4224 | I33: =SUM(I31:I32) -> 140190 | K33: =SUM(K31:K32) -> 147087 | T33: Old FD | U33: Cr | W33: 32606
B34: Painting Fund | T34: Int on FD | U34: Cr | W34: 860
A35: 24 | B35: TD0000415696_01 | C35: 05.06.21 | D35: 18987 | E35: 841 | F35: 1072 | G35: =1127-113 -> 1014 | H35: =+E35+F35+G35 -> 2927 | I35: =D35+H35 -> 21914 | J35: 05.06.24 | K35: 22236 | L35: 0.053 | M35: SCB | N35: =O35-P35 -> 185 | O35: 206 | P35: 21 | Q35: 22099 | R35: =H35 -> 2927 | S35: 109309 | T35: Acc | U35: Cr | W35: 4521
A36: 25 | B36: TD0000415681_01 | C36: 04.12.21 | D36: 9295 | E36: 161 | F36: 511 | G36: =538-54 -> 484 | H36: =+E36+F36+G36 -> 1156 | I36: =D36+H36 -> 10451 | J36: 04.12.24 | K36: 10886 | L36: 0.053 | M36: SCB | N36: =O36-P36 -> 339 | O36: 377 | P36: 38 | Q36: 10790 | R36: =H36 -> 1156 | S36: 109310 | V36: =SUM(V31:V35) -> 37987 | W36: =SUM(W33:W35) -> 37987
A37: 26 | B37: TD1000721221 | C37: 27.03.23 | D37: 19030 | E37: 0 | F37: 36 | G37: =1366-137 -> 1229 | H37: =+E37+F37+G37 -> 1265 | I37: =D37+H37 -> 20295 | J37: 27.03.26 | K37: 23434 | L37: 0.07 | M37: SCB | N37: =O37-P37 -> 1310 | O37: 1455 | P37: 145
A38: 27 | B38: TD1000106202 | C38: 08.09.21 | D38: 15651 | E38: 472 | F38: 872 | G38: =917-92 -> 825 | H38: =+E38+F38+G38 -> 2169 | I38: =D38+H38 -> 17820 | J38: 08.09.24 | K38: 18329 | L38: 0.053 | M38: SCB | N38: =O38-P38 -> 372 | O38: 413 | P38: 41 | Q38: 18192 | R38: =H38 -> 2169 | S38: 109311
A39: 28 | B39: TD1001126438 | C39: 17.03.24 | D39: 9530 | E39: 0 | F39: 0 | G39: =29-3 -> 26 | H39: =+E39+F39+G39 -> 26 | I39: =D39+H39 -> 9556 | J39: 17.06.25 | K39: 10458 | L39: 0.075 | M39: SCB | N39: =O39-P39 -> 664 | O39: 735 | P39: 71
A40: 29 | B40: TD1000717527 | C40: 23.03.23 | D40: 23956 | E40: 0 | F40: 41 | G40: =1719-172 -> 1547 | H40: =+E40+F40+G40 -> 1588 | I40: =D40+H40 -> 25544 | J40: 23.03.26 | K40: 29500 | L40: 0.07 | M40: SCB | N40: =O40-P40 -> 1648 | O40: 1831 | P40: 183
A41: 30 | B41: TD1001126341 | C41: 19.03.24 | D41: 23956 | E41: 0 | F41: 0 | G41: =63-6 -> 57 | H41: =+E41+F41+G41 -> 57 | I41: =D41+H41 -> 24013 | J41: 19.06.25 | K41: 26288 | L41: 0.075 | M41: SCB | N41: =O41-P41 -> 1662 | O41: 1847 | P41: 185
D42: =SUM(D35:D41) -> 120405 | E42: =SUM(E35:E41) -> 1474 | F42: =SUM(F35:F41) -> 2532 | G42: =SUM(G35:G41) -> 5182 | H42: =SUM(H35:H41) -> 9188 | I42: =SUM(I35:I41) -> 129593 | K42: =SUM(K35:K41) -> 141131
B43: Share Capital
A44: 31 | B44: TD0000400904_01 | C44: 21.01.2022 | D44: 9000 | H44: =+E44+F44+G44 -> 0 | I44: =D44+H44 -> 9000 | J44: 21.01.25 | K44: 9000 | L44: 0.053 | M44: SCB
A45: 32 | B45: TD1000225977 | C45: 24.01.2022 | D45: 9000 | H45: =+E45+F45+G45 -> 0 | I45: =D45+H45 -> 9000 | J45: 24.01.25 | K45: 9000 | L45: 0.053 | M45: SCB
D46: =SUM(D44:D45) -> 18000 | E46: =SUM(E44:E45) -> 0 | F46: =SUM(F44:F45) -> 0 | G46: =SUM(G44:G45) -> 0 | H46: =SUM(H44:H45) -> 0 | I46: =SUM(I44:I45) -> 18000 | K46: =SUM(K44:K45) -> 18000
B47: Common Amenity Fund
A48: 33 | B48: TD1000106230 | C48: 08.09.21 | D48: 32606 | E48: 984 | F48: 1816 | G48: =1911-190 -> 1721 | H48: =+E48+F48+G48 -> 4521 | I48: =D48+H48 -> 37127 | J48: 08.09.24 | K48: 38185 | L48: 0.053 | M48: SCB | N48: =O48-P48 -> 774 | O48: 860 | P48: 86 | Q48: 37901 | R48: =H48 -> 4521 | S48: 109312
A49: 34 | B49: TD0000415675_02 | C49: 30.10.23 | D49: 50515 | E49: 0 | F49: 0 | G49: =1524-152 -> 1372 | H49: =+E49+F49+G49 -> 1372 | I49: =D49+H49 -> 51887 | J49: 30.10.25 | K49: 58150 | L49: 0.071 | M49: SCB | N49: =O49-P49 -> 3396 | O49: 3773 | P49: 377
A50: 35 | B50: TD1001101183 | C50: 24.02.24 | D50: 38882 | E50: 0 | F50: 0 | G50: =306-31 -> 275 | H50: =+E50+F50+G50 -> 275 | I50: =D50+H50 -> 39157 | J50: 24.05.25 | K50: 42666 | L50: 0.075 | M50: SCB | N50: =O50-P50 -> 2710 | O50: 3012 | P50: 302
D51: =SUM(D48:D50) -> 122003 | E51: =SUM(E48:E50) -> 984 | F51: =SUM(F48:F50) -> 1816 | G51: =SUM(G48:G50) -> 3368 | H51: =SUM(H48:H50) -> 6168 | I51: =SUM(I48:I50) -> 128171 | K51: =SUM(K48:K50) -> 139001
B52: Legal Fund
A53: 36 | B53: TD0000415698_01 | C53: 22.06.21 | D53: 7682 | E53: 321 | F53: 432 | G53: =456-45 -> 411 | H53: =+E53+F53+G53 -> 1164 | I53: =D53+H53 -> 8846 | J53: 22.06.24 | K53: 8996 | L53: 0.053 | M53: SCB | N53: =O53-P53 -> 94 | O53: 104 | P53: 10 | Q53: 8940 | R53: =H53 -> 1164 | S53: 109313
A54: 37 | B54: TD1000182911 | C54: 04.12.21 | D54: 24359 | E54: 421 | F54: 1340 | G54: =1409-140 -> 1269 | H54: =+E54+F54+G54 -> 3030 | I54: =D54+H54 -> 27389 | J54: 04.12.24 | K54: 28527 | L54: 0.053 | M54: SCB | N54: =O54-P54 -> 890 | O54: 989 | P54: 99 | Q54: 28279 | R54: =H54 -> 3030 | S54: 109314
A55: 38 | B55: TD1000106216 | C55: 08.09.21 | D55: 14086 | E55: 425 | F55: 785 | G55: =825-83 -> 742 | H55: =+E55+F55+G55 -> 1952 | I55: =D55+H55 -> 16038 | J55: 08.09.24 | K55: 16496 | L55: 0.053 | M55: SCB | N55: =O55-P55 -> 333 | O55: 371 | P55: 38 | Q55: 16371 | R55: =H55 -> 1952 | S55: 109315
A56: 39 | B56: TD1000290759_01 | C56: 17.04.23 | D56: 131573 | E56: 0 | F56: 0 | G56: =9147-915 -> 8232 | H56: =+E56+F56+G56 -> 8232 | I56: =D56+H56 -> 139805 | J56: 17.05.24 | K56: 141990 | L56: 0.071 | M56: SCB | N56: =O56-P56 -> 1115 | O56: 1239 | P56: 124 | Q56: 140920 | R56: =H56 -> 8232 | S56: 109316
A57: 40 | B57: TD1001126443 | C57: 17.03.24 | D57: 8580 | E57: 0 | F57: 0 | G57: =26-2 -> 24 | H57: =+E57+F57+G57 -> 24 | I57: =D57+H57 -> 8604 | J57: 17.06.25 | K57: 9415 | L57: 0.075 | M57: SCB | N57: =O57-P57 -> 596 | O57: 662 | P57: 66
A58: 41 | B58: TD1000717533 | C58: 23.03.23 | D58: 21600 | E58: 0 | F58: 38 | G58: =1607-160 -> 1447 | H58: =+E58+F58+G58 -> 1485 | I58: =D58+H58 -> 23085 | J58: 23.03.25 | K58: 24938 | L58: 0.0725 | M58: SCB | N58: =O58-P58 -> 1505 | O58: 1672 | P58: 167 | Q58: 24590 | R58: =H58 -> 1485 | S58: 109317
A59: 42 | B59: TD1001126389 | C59: 19.03.24 | D59: 21600 | E59: 0 | F59: 0 | G59: =57-6 -> 51 | H59: =+E59+F59+G59 -> 51 | I59: =D59+H59 -> 21651 | J59: 19.06.25 | K59: 23702 | L59: 0.075 | M59: SCB | N59: =O59-P59 -> 1499 | O59: 1665 | P59: 166
D60: =SUM(D53:D59) -> 229480 | E60: =SUM(E53:E59) -> 1167 | F60: =SUM(F53:F59) -> 2595 | G60: =SUM(G53:G59) -> 12176 | H60: =SUM(H53:H59) -> 15938 | I60: =SUM(I53:I59) -> 245418 | K60: =SUM(K53:K59) -> 254064
B61: Leave and Licence Deposit
A62: 43 | B62: TD1000295859 | C62: 31.03.24 | D62: 8000 | E62: 0 | F62: 0 | H62: =+E62+F62+G62 -> 0 | I62: =D62+H62 -> 8000 | J62: 30.06.25 | K62: 8000 | L62: 0.075 | M62: SCB
A63: 44 | B63: TD1000346250 | C63: 23.05.22 | D63: 4000 | E63: 0 | F63: 0 | H63: =+E63+F63+G63 -> 0 | I63: =D63+H63 -> 4000 | J63: 23.05.24 | K63: 4000 | L63: 0.0565 | M63: SCB | Q63: 4000 | S63: 109318
A64: 45 | B64: TD1000772659 | C64: 29.04.23 | D64: 2000 | E64: 0 | F64: 0 | H64: =+E64+F64+G64 -> 0 | I64: =D64+H64 -> 2000 | J64: 29.04.25 | K64: 2000 | L64: 0.0725 | M64: SCB
A65: 46 | B65: TD1000717591 | C65: 23.03.24 | D65: 6000 | E65: 0 | F65: 0 | H65: =+E65+F65+G65 -> 0 | I65: =D65+H65 -> 6000 | J65: 23.03.25 | K65: 6000 | L65: 0.0725 | M65: SCB | Q65: 6000 | S65: 109319
D66: =SUM(D62:D65) -> 20000 | E66: =SUM(E62:E65) -> 0 | F66: =SUM(F62:F65) -> 0 | G66: =SUM(G62:G65) -> 0 | H66: =SUM(H62:H65) -> 0 | I66: =SUM(I62:I65) -> 20000 | K66: =SUM(K62:K65) -> 20000
B67: Redevelopment Fund
A68: 47 | B68: TD1000717573 | C68: 23.03.23 | D68: 43200 | E68: 0 | F68: 76 | G68: =3215-322 -> 2893 | H68: =+E68+F68+G68 -> 2969 | I68: =D68+H68 -> 46169 | J68: 23.03.25 | K68: 49876 | L68: 0.0725 | M68: SCB | N68: =O68-P68 -> 3009 | O68: 3344 | P68: 335 | Q68: 49178 | R68: =H68 -> 2969 | S68: 109320
A69: 48 | B69: TD1001126321 | C69: 19.03.24 | D69: 86400 | G69: =226-22 -> 204 | H69: =+E69+F69+G69 -> 204 | I69: =D69+H69 -> 86604 | J69: 19.06.25 | K69: 94809 | L69: 0.075 | M69: SCB | N69: =O69-P69 -> 5995 | O69: 6662 | P69: 667
D70: =SUM(D68:D69) -> 129600 | E70: =SUM(E68:E69) -> 0 | F70: =SUM(F68:F69) -> 76 | G70: =SUM(G68:G69) -> 3097 | H70: =SUM(H68:H69) -> 3173 | I70: =SUM(I68:I69) -> 132773 | K70: =SUM(K68:K69) -> 144685
B71: Education & Training Fund
A72: 49 | B72: TD1000717580 | C72: 23.03.23 | D72: 23500 | E72: 0 | F72: 41 | G72: =1749-175 -> 1574 | H72: =+E72+F72+G72 -> 1615 | I72: =D72+H72 -> 25115 | J72: 23.03.25 | K72: 27132 | L72: 0.0725 | M72: SCB | N72: =O72-P72 -> 1638 | O72: 1819 | P72: 181 | Q72: 26753 | R72: =H72 -> 1615 | S72: 109321
A73: 50 | B73: TD1001126346 | C73: 19.03.24 | D73: 4320 | G73: =11-1 -> 10 | H73: =+E73+F73+G73 -> 10 | I73: =D73+H73 -> 4330 | J73: 19.06.25 | K73: 4740 | L73: 0.075 | M73: SCB | N73: =O73-P73 -> 300 | O73: 333 | P73: 33
D74: =SUM(D72:D73) -> 27820 | E74: =SUM(E72:E73) -> 0 | F74: =SUM(F72:F73) -> 41 | G74: =SUM(G72:G73) -> 1584 | H74: =SUM(H72:H73) -> 1625 | I74: =SUM(I72:I73) -> 29445 | K74: =SUM(K72:K73) -> 31872
B76: Grand Total | D76: =D24+D29+D33+D42+D46+D51+D60+D66+D70+D74 -> 1118249 | E76: =E24+E29+E33+E42+E46+E51+E60+E66+E70+E74 -> 5322 | F76: =F24+F29+F33+F42+F46+F51+F60+F66+F70+F74 -> 12305 | G76: =G24+G29+G33+G42+G46+G51+G60+G66+G70+G74 -> 41017 | H76: =H24+H29+H33+H42+H46+H51+H60+H66+H70+H74 -> 58644 | I76: =I24+I29+I33+I42+I46+I51+I60+I66+I70+I74 -> 1176893 | K76: =K24+K29+K33+K42+K46+K51+K60+K66+K70+K74 -> 1255714
