Workbook
Name __sch2: #REF!
Name __sch2: #REF!
Name __sch2: #REF!
Name __sch2: #REF!
Name __sch2: #REF!
Name __sch2: #REF!
Name _123: #REF!
Name _123: #REF!
Name _123: #REF!
Name _123: #REF!
Name _4: #REF!
Name _4: #REF!
Name _4: #REF!
Name _4: #REF!
Name _4: #REF!
Name _jG1: #REF!
Name _jG1: #REF!
Name _jG1: #REF!
Name _jG1: #REF!
Name _jG1: #REF!
Name _jG1: #REF!
Name _sch2: #REF!
Name _sch2: #REF!
Name _sch2: #REF!
Name _sch2: #REF!
Name _sch2: #REF!
Name _sch2: #REF!
Name a: #REF!
Name a: #REF!
Name a: #REF!
Name a: #REF!
Name a: #REF!
Name a: #REF!
Name DATA1: #REF!
Name DATA1: #REF!
Name DATA1: #REF!
Name DATA1: #REF!
Name DATA1: #REF!
Name DATA1: #REF!
Name DATA10: #REF!
Name DATA10: #REF!
Name DATA10: #REF!
Name DATA10: #REF!
Name DATA10: #REF!
Name DATA10: #REF!
Name DATA11: #REF!
Name DATA11: #REF!
Name DATA11: #REF!
Name DATA11: #REF!
Name DATA11: #REF!
Name DATA11: #REF!
Name DATA12: #REF!
Name DATA12: #REF!
Name DATA12: #REF!
Name DATA12: #REF!
Name DATA12: #REF!
Name DATA12: #REF!
Name DATA13: #REF!
Name DATA13: #REF!
Name DATA13: #REF!

Sheet TIT
A2: Name | D2: NAVANAND CO-OPERATIVE. HOUSING SOCIETY LTD. | L2: Navanand Co-Op. Housing Society Ltd.
A3: Registration No. | D3: BOM/WR/HSG/TC/11905 DT. 06/01/2003
A4: Date of Registration | D4: 37627
A5: Area of operation | D5: Dahisar (East), Mumbai
A6: Address | D6: Maratha Colony Road, Dahisar - East, Mumbai - 400 068
A7: Accounting Year | B7: from | D7: 1st April, 2025
B8: to | D8: 31st March, 2026
A9: Auditor | B9: Name | D9: Shri. Bharat C. Boridkar | F9: Govt. Certified Panel Auditor
A10: Panel No. | D10: Mumbai-4/C1/1011404
B11: Address | D11: Boridkar House, Pandurang Bhoir Road, Dahisar - West, Mumbai, Mumbai - 400 068
A12: Place & Date of Report | D12: =+D16 -> 46275
A13: Sr.No. of the audit memo
A14: Date of commencment | D14: 46266
A15: Date of completion | D15: 45909
A16: Audit memo submitted. | D16: 46275
A17: Annual General Meeting | D17: 45928 | E17: Attendance:-
A18: Special General Meeting | D18: 16-11-2024 & 16-02-2025
A19: M C Meetings | D19: 10
A20: Rectification of Reports: | D20: Not submitted
A21: Date of submission | D21: Not applicable
A22: Audit Fees | B22: Amt | D22: 3000
B23: Period | D23: 01-04-202 | E23: 45382
B24: Paid on
A25: Secretary | B25: Name | D25: Shri. Dilip Kalgutkar
A26: Pay drawn:
A27: Cash verification | B27: Amt | D27: Nil
B28: Date
B29: Name | D29: =+D25 -> Shri. Dilip Kalgutkar
B30: Designation | D30: Secretary
B37: 1 | D37: 42848
B38: 2 | D38: 42883
B39: 3 | D39: 42912
B40: 4 | D40: 42939
B41: 5 | D41: 42967
B42: 6 | D42: 43037
B43: 7 | D43: 43065
B44: 8 | D44: 43094
B45: 9 | D45: 43128
B46: 10 | D46: 43156
B47: 11 | D47: 43189
B48: 12
B49: 13

Sheet First Page
A3: STATUTORY AUDIT REPORT
A13: =+TIT!D2 -> NAVANAND CO-OPERATIVE. HOUSING SOCIETY LTD.
A15: =+TIT!D3 -> BOM/WR/HSG/TC/11905 DT. 06/01/2003
A16: =+TIT!D6 -> Maratha Colony Road, Dahisar - East, Mumbai - 400 068
A19: STATEMENT OF AUDIT REPORTS & ACCOUNTS STATEMENTS FOR THE YEAR ENDED 31ST MARCH,2026
A33: ===============================================================================
A34: =+TIT!D9 -> Shri. Bharat C. Boridkar
A35: Govt. Certified Panel Auditor
A36: =+TIT!D11 -> Boridkar House, Pandurang Bhoir Road, Dahisar - West, Mumbai, Mumbai - 400 068
A38: ===============================================================================

Sheet Ltr to Soct.
A2: =+TIT!D9 -> Shri. Bharat C. Boridkar
A3: Govt. Certified Panel Auditor
A4: =+TIT!D11 -> Boridkar House, Pandurang Bhoir Road, Dahisar - West, Mumbai, Mumbai - 400 068
A7: To,
A8: The Chairman, Members
A9: =+TIT!D2 -> NAVANAND CO-OPERATIVE. HOUSING SOCIETY LTD. | O9: Name : | P9: =+TIT!D2 -> NAVANAND CO-OPERATIVE. HOUSING SOCIETY LTD.
A10: =+TIT!D6 -> Maratha Colony Road, Dahisar - East, Mumbai - 400 068 | O10: Reg.No | P10: =+TIT!D3 -> BOM/WR/HSG/TC/11905 DT. 06/01/2003
O11: DDR Order | P11: 30/10/2018 20:34:57
A12: Sub :-Statutory audit of your society for Financial Year ending on31-Mar-2026
A15: Enclosed please find 3 [Three only] sets of duly audited, signed and sealed comprising Audit Report in Form-N2, Form -1 along with Sch 1 to 6, Form - 28, General Remarks, Balance Sheet, Income and Expendire Account along with Schedules forming integral part of the same, Audit Report [Executive Summary] for the Financial Year ended on 31-Mar-2026 for record of the Society.
A16: It is advised that one set to be submitted to the Deputy Registrar of Co operative Societies,R Ward, 2nd floor, C wing, Municipal Godown Bldg, Nr St Lwarence School, 90 feet Road, Sanskruiti Complex,, Kandivali East,, Mumbai- 400101 under the Societies covering letter at your earliest. | P16: It is advised that one set to be submitted to the Deputy Registrar of Co operative Societies, Ward P, 2nd floor, C wing, Municipal Godown Bldg, Nr St Lwarence School, 90 feet Road, Sanskruiti Complex,, Kandivali East,, Mumbai- 400101 under the Societies covering letter at your earliest.
A17: You are requested to upload mandory returns as prescribed u/s 79 of the MCS Act i.e. 1] Annual Report of Activities, 2] Abridged Audit Report, 3] Balance Sheet, 4] Income and Expenditure Account, 5] Plan for Surplus Distribution, 6] List of Amendment to ByLaws, if any, 7] Date of holding AGBM and Election and 8] Name of Auditor for year ended 31-03-2026 and Return Consent on "www.mahasahakar.maharashtra.gov.in" within the time prescribed.
A18: I am also enclosing Invoice for audit fees with a request to settle the same at your earliest.
A19: Please Note that the Audit rectification report in Form O duly approved by the managing committee to be submitted to the Registering Authorities within the time permitted i.e. 3 months from the date of audit report under section 82 of the MCS Act. Please make sure that authenticated copy of the same along with soft copy to be provided to me for my comments thereon and uploading thereafter on "www.mahasahakar.maharashtra.gov.in".
A20: In any case, any further information is required, feel free to contact me at your convenience.
A21: Inconvenience, if any, is regretted.
A22: Thanks a lot.
A23: Yours faithfully,
A27: =+TIT!D9 -> Shri. Bharat C. Boridkar
A28: Govt. Certified Panel Auditor
A29: Co-op Soc Empanelment Number : A-2 / 13395
A30: Co-op Soc Empanelment Number : Mumbai-4/C1/1011404
A31: =+TIT!D12 -> 46275
A33: Encl: | B33: 1] 3 [three only] sets as above
B34: 2] Original Invoice of Audit Fees

Sheet AR
A2: =+TIT!D9 -> Shri. Bharat C. Boridkar
A3: Govt. Certified Panel Auditor
A4: =+TIT!D11 -> Boridkar House, Pandurang Bhoir Road, Dahisar - West, Mumbai, Mumbai - 400 068
A6: INDEPENDENT AUDITOR'S REPORT
A7: [As prescribed under section 81 of the Maharashtra Co-operative Societies Act, 1960 and rule 69 (3) of the Maharashtra Co op Societies Rules.]
A9: To,
A10: The Chairman, Members | N10: Chairman
A11: =+TIT!D2 -> NAVANAND CO-OPERATIVE. HOUSING SOCIETY LTD.
A12: =+TIT!D6 -> Maratha Colony Road, Dahisar - East, Mumbai - 400 068
A14: Sub :-Statutory audit of your society for Financial Year ending on31-Mar-2026
N15: Navanand Co-Op. Housing Society Ltd.
B17: Report on the Financial Statements as a Statutory Auditor | N17: NAVANAND CO-OP. HOUSING SOCIETY LTD. | S17: =PROPER(N17) -> Navanand Co-Op. Housing Society Ltd.
A19: 1. | B19: I have audited the accompanying financial statements of Navanand Co-Operative Housing Society Ltd., which comprise the Balance Sheet as at 31st MARCH, 2026 and the Statement of Income and Expenditure for the year ended on that date, and a summary of significant accounting policies and other explanatory information incorporated in these financial statements of the Society. | N19: Income and Expenditure | S19: 24/11/2016 8:50:34 PM
B21: Management’s Responsibility for the Financial Statements
A22: 2 | B22: Management is responsible for the preparation of these financial statements in accordance with Maharashtra Co-operative Societies Act, 1960 & Rules there under. This responsibility includes the design, implementation and maintenance of internal control relevant to the preparation of the financial statements that are free from material misstatement, whether due to fraud or error.
B24: Auditor’s Responsibility
A25: 3 | B25: My responsibility is to express an opinion on these financial statements based on my audit. I conducted my audit in accordance with the applicable Standards issued by The Institute of Chartered Accountants of India and under the Maharashtra Co-operative Societies Act, 1960. Those Standards require that I comply with ethical requirements and plan and perform the audit to obtain reasonable assurance about whether the financial statements are free from material misstatement.
A27: 4 | B27: An audit involves performing procedures to obtain audit evidence about the amounts and disclosures in the financial statements. The procedures selected depend on the auditor’s judgment, including the assessment of the risks of material misstatement of the financial statements, whether due to fraud or error. In making those risk assessments, the auditor considers internal control relevant to the Society’s preparation and fair presentation of the financial statements in order to design audit procedures that are appropriate in the circumstances. An audit also includes evaluating the appropriateness of accounting policies used and the reasonableness of the accounting estimates made by management, as well as evaluating the overall presentation of the financial statements.
A29: 5. | B29: I believe that the audit evidence I have obtained is sufficient and appropriate to provide a basis for my audit opinion.
B32: Opinion
A33: 6. | B33: In my opinion and to the best of my information and according to the explanations given to me, the said accounts together with the notes thereon and remarks incorporated in the Audit Memorandum No. 1 and No. 28 and general remarks, give the information required as per the Maharashtra Co-operative Societies Act, 1960 and the Maharashtra Co-operative Societies Rules, 1961, and any other applicable Acts, and or circulars issued by the Registrar, in the manner so required for the society gives a true and fair view in conformity with the accounting principles generally accepted in India:
B35: i. | C35: In the case of the Balance Sheet, of the state of affairs of the Society as at 31st MARCH, 2026; | N35: Change Year
B37: ii. | C37: ="In the case of the Statement of "&N19&", of the "&'F-1'!I132&" of the Society for the year ended on that date; and" -> In the case of the Statement of Income and Expenditure, of the Excess of Income Over Expenditure of the Society for the year ended on that date; and | N37: Surplus / Deficit see F1 I132
B40: Report on Other Legal and Regulatory Matters
A41: 7. | B41: The Balance Sheet and the Income and Expenditure Account have been drawn up in accordance with the provisions of the Maharashtra State Co-operative Act, 1960.
A43: 8. | B43: I report that :
B44: (a) | C44: I have obtained all the information and explanations which, to the best of my knowledge and belief, were necessary for the purpose of my audit and have found them to be satisfactory.
B46: (b) | C46: The transactions of the Society, which have come to my notice, have been within the powers of the Society.
B48: (c) | C48: The Society does not have any branch. | M48: 0 | N48: The Society does not have any branch. | O48: The returns received from the offices and branches of the Society have been found adequate for the purposes of our audit.
A50: 9. | B50: In my opinion, the Balance Sheet and Income and Expenditure Account comply with applicable Accounting Standards.
A52: 10. | B52: We further report that : | N52: Mandatory rtns filed?
B53: i. | C53: The Balance Sheet and Income and Expenditure Account dealt with by this report, are in agreement with the books of account. | N53: N | O53: The Balance Sheet and Income and Expenditure Account dealt with by this report, are in agreement with the books of account and the returns. | P53: The Balance Sheet and Income and Expenditure Account dealt with by this report, are in agreement with the books of account.
B55: ii. | C55: In my opinion, proper books of account as required by law have been kept by the Society so far as appears from my examination of these books.
B57: iii | C57: The Society does not have any branch. | M57: 0 | N57: The Society does not have any branch. | O57: The reports on the accounts of the branches audited by branch auditors have been dealt with in preparing my report in the manner considered necessary by me.
B59: iv | C59: For the year under audit, the society has been awarded B classification. | N59: B
B65: =+TIT!D9 -> Shri. Bharat C. Boridkar
B66: Govt. Certified Panel Auditor
B67: [Panel No.: Mumbai-4/B3/1011404]
B68: Co-op Soc Empanelment Number : Mumbai-4/C1/1011404
B69: =+TIT!D12 -> 46275

Sheet F-1
A1: FORM NO. 1
A2: Audit Memo (For all types of Co-op.Societies)
A3: Part-I
A5: Name of the Society | I5: =+TIT!D2 -> NAVANAND CO-OPERATIVE. HOUSING SOCIETY LTD.
A7: Sr.No. of the audit memo as per audit register | I7: 2023-2024/
A8: Full registered address | I8: =+TIT!D6 -> Maratha Colony Road, Dahisar - East, Mumbai - 400 068
A9: Taluka or Block
A10: District | I10: Mumbai, Subarban District.
A11: Registration No. | I11: =+TIT!D3 -> BOM/WR/HSG/TC/11905 DT. 06/01/2003
A12: Date of Registration | I12: =+TIT!D4 -> 37627
A13: Area of operation | I13: =+TIT!D5 -> Dahisar (East), Mumbai
A14: No. of branches, depots and shops | I14: Nil
A15: (Give separate figures)
A16: (i) | B16: Audit classification | I16: ‘B’
A17: (ii) | B17: Audit classification given during the last three audits | I17: ‘B’
A18: 1 | B18: Audit information:
B19: (1) | C19: Full name, designation and head Quarters of auditing officer. | I19: =+TIT!D9 -> Shri. Bharat C. Boridkar | K19: =+TIT!F9 -> Govt. Certified Panel Auditor
I20: =+TIT!D11 -> Boridkar House, Pandurang Bhoir Road, Dahisar - West, Mumbai, Mumbai - 400 068
B22: (2) | C22: Period covered during the present audit. | I22: =+TIT!D7&+" to "&TIT!D8 -> 1st April, 2025 to 31st March, 2026
B23: (3) Dates on which | D23: (1)Audit was commenced and continued. | I23: =+TIT!D14 -> 46266 | J23: to | K23: =+TIT!D15 -> 45909
D24: (2) Audit was completed | I24: =+TIT!D15 -> 45909
D25: (3) Audit memo was submitted. | I25: =+TIT!D16 -> 46275
A26: 2 | B26: Membership:
B27: (i) | C27: No.of Members: | E27: (a) Individual: | F27: (I) Ordinary | J27: 30
F28: (ii) Nominal
F29: (iii) Sympathiser | J29: 0
E30: (b) Societies. | J30: 0
E31: (c) Others | J31: 0
E32: Give details of the other members, if any
E33: Total | J33: =SUM(J27:J32) -> 30
B34: (ii) | C34: Have new members been duly admitted? | I34: Yes,
C35: Have they paid entrance fees? | I35: Yes,
B36: (iii) | C36: Are their written applications in order and are they filed properly? | I36: Yes,
B38: (iv) | C38: Is the members’ register kept in Form `I’ prescribed under Rules 32 and 65(I) of the M. C. S.Rules 1961? | I38: Yes
B41: (v) | C41: Is a list of members’ kept in Form `J’ under Rule 33 of the M. C. S.Rules 1961? | I41: Yes
B43: (vi) | C43: Have due remarks been passed against names of the deceased, dismissed, or resigned members in the members’ register? | I43: Yes
B46: (vii) | C46: Are resignations in order and are they duly accepted? | I46: Yes
B48: (viii) | C48: Have nominations made under rule 25 of the M. C. S. Rules 1961 been duly entered in the member's register under rule 26? | I48: =+I43 -> Yes
A51: 3 | B51: Shares:
B52: (i) | C52: Are applications for shares in order? | I52: Yes
B53: (ii) | C53: Is share register written up-to-date? | I53: Yes
B54: (iii) | C54: Do the entries in share register tally with the Entries in the cash book? | I54: Yes
B56: (iv) | C56: Is share ledger written up-to-date? | I56: Yes
B57: (v) | C57: Do the total of share ledger balances tally with the figures of share capital in the balance sheet? | I57: Yes
B59: (vi) | C59: Have share certificates been issued to the share holders for all the shares subscribed? | I59: Yes
B61: (vii) | C61: Are share transfers and refunds in accordance with the provisions of the Bye-laws, Act and Rules? | I61: Yes
A64: 4 | B64: Outside Borrowings:
B65: (i) | C65: What is the limit fixed in the Bye-laws for borrowings of the society? | I65: As per Rule 35 of MSC Rules, 1961.
I66: (Ten times of Share Capital + Reserve & Surplus - Accumulated losses)
B67: (ii) | C67: Has it been exceeded? | I67: No
B68: (iii) | C68: If so, state whether necessary permission has been obtained from the competent authority? | I68: Not applicable
A70: 5 | B70: Meetings:
B71: (i) | C71: Give dates of:-
C72: (a) Annual General Meeting | I72: =+TIT!D17 -> 45928
C73: (b) Special General Meeting | I73: =+TIT!D18 -> 16-11-2024 & 16-02-2025
B74: (ii) | C74: State the No. of meetings held during the period as follows: -
C76: (a) Board or Managing Committee Meetings | I76: =+TIT!D19 -> 10 | J76: Meetings
C77: (b) Executive or Sub-Committee meetings. | I77: Nil
C78: (c) Other Meetings | I78: Nil
A79: 6 | B79: Rectification of Reports:
B80: (i) | C80: Has the society submitted audit rectification reports of the previous audit memos? If so, give dates of submission. If not, state the reason for non-submission. | I80: Not submitted
I81: Not applicable
B84: (ii) | C84: Have any important points mentioned in the previous audit memos been neglected by the society? If so, state them in general remarks. | I84: Refer to General Remarks
A87: 7 | B87: Audit Fees
B88: (i) | C88: Give amount of audit fees last assessed- | I88: ="Rs. "&+TIT!D22&"/-" -> Rs. 3000/-
C89: State period for which assessed: | I89: =+TIT!D23 -> 01-04-202 | J89: to | K89: =+TIT!E23 -> 45382
C90: State the date of recovery of audit fees, name of Treasury and amount credited (Give No. and date of Treasury Challan.)
B93: (ii) | C93: If audit fees have not been paid by the society, give details about outstanding audit fees and reasons for non-payment. | I93: Not Applicable
A96: 8 | B96: Internal or Local Audit:
B97: (i) | C97: If there is internal or local audit, state by whom done, period covered and whether memo is on the record of the society. | I97: No Internal Audit
B100: (ii) | C100: State whether there is a proper co-ordination between Statutory Auditor and Internal Auditor. | I100: Not Applicable
A102: 9 | B102: (A) | C102: Managing Director/Manager/Secretary
B103: (i) | C103: Name of the Officer | I103: =+TIT!D25 -> Shri. Dilip Kalgutkar
B104: (ii) | C104: Pay drawn:
C105: Grade: | I105: Not Applicable
B106: (iii) | C106: State other allowances, if any, any facilities given such as rent free quarters etc: | I106: Nil
B108: (iv) | C108: State whether he is a member. | I108: Yes
B109: (v) | C109: If so, whether he has borrowed or has been given any credit facilities? State the amount borrowed and the amounts of overdue, if any. | I109: Not Applicable
B112: (vi) | C112: If other amounts are due from him, give details. | I112: Nil | K112: Not Applicable
B114: (B) | C114: Obtain a list of staff showing names, designations, qualifications, scales, present pay and allowances given, dates from which employed, security furnished etc. | I114: Yes
I115: Paid only to Sweeper & Watchmen
A118: 10 | B118: Breaches:
B119: (i) | C119: Does the Society posses a copy of the Act, Rules and its registered Bye-laws? | I119: a) Act & Rules | K119: Yes
I120: b) Bye-laws | K120: Yes
B121: (ii) | C121: Give only numbers of breaches of the Act, Rules and Bye-laws?
C123: 1. Section Nos. | I123: As per General Remarks
C124: 2. Rules Nos.
C125: 3. Bye-laws Nos.
B126: (iii) | C126: Have any rules been framed under the Bye-laws? Are they approved by appropriate authority? Are they properly followed?
I127: Yes
C129: (These breaches should be discussed in brief in general remarks)
A131: 11 | B131: Profit and Loss:
B132: 1. | C132: What is the amount of profit earned or loss incurred during the last co-operative year? | I132: Excess of Income Over Expenditure | L132: ="Rs. "&+ROUND('I&E'!H36,0) -> Rs. 0
B134: 2. | C134: State how the net profits are distributed? (In case of non-business societies, figures of surplus or deficit may be given against querry No. 11(1) above).
A138: 12 | B138: Cash, Bank Balances and securities:
B139: (a) | C139: Cash:
B140: 1 | C140: 1. Count cash and sign the cash Book stating the amount so counted and date on which counted. | I140: Cash was not counted
J141: -
B142: 2 | C142: Who produced the cash for counting? | I142: NA
C143: Give his name and designation. Is he authorised to keep cash?
...

Sheet F-28
A1: =+'F-1'!I5 -> NAVANAND CO-OPERATIVE. HOUSING SOCIETY LTD.
A2: FORM NO.28
A3: Audit Memo (Co-opertive Housing societies)
A4: Part - II
A5: 1. | B5: Borrowings :-
B6: (i) | C6: State the loans obtained by the Society for various purposes from Government and other agencies
A7: Agency Sanctioning loan | E7: Purpose for which the loan is sanctioned | G7: Amount of loan sanctioned | I7: Maximum amount drawn | J7: Repayment made | K7: Outstanding | L7: Amount overdue, if any | M7: Remarks
A10: 1 | E10: 2 | G10: 3 | I10: 4 | J10: 5 | K10: 6 | L10: 7 | M10: 8
A12: Not Applicable
B14: (ii) | C14: Are repayments of loans punctual? | I14: Not Applicable
B15: (iii) | C15: Are all conditions laid down for grant of various loans and credits observed ? Note breaches, if any. | I15: Not Applicable
B17: (iv) | C17: Are necessary documents executed in favour of the authority sanctioning the loan? | I17: Not Applicable
A19: 2. | B19: Government Financial Assistance :-
B20: (i) | C20: What is the amount of Government subsidy santioned and received by the society? | I20: Not Applicable
B22: (ii) | C22: Has Government sanctioned any amount for land development ? If so, state the amount. Have development expenses exceeded the said amount? | I22: Not Applicable
A25: 3. | B25: Membership :-
B26: (i) | C26: State whether in case of backward class co-operative housing societies, certificates from the social werlfare officers are obtained for their eligibility to membership and obtaining of financial asitance? | I26: Not Applicable
B30: (ii) | C30: State whether certificates are obtained from officers of the concerned industry in case of the subsidised industrial housing scheme. | I30: Not Applicable
B33: (iii) | C33: Have declarations been obtained from members that they and their family members do not own lands or houses in the area of operation of the society as per provisions in the bye-laws? | I33: Not Applicable
A37: 4. | B37: Lands and their developments :-
B38: (i) | C38: State whether lands for constructions of houses have been secured, purchased or obtained on lease. Give details of the lands, stating total area, survey Nos. and C.R.S. Nos. if any, price for which purchased, lease rent etc. | I38: =+TIT!D6 -> Maratha Colony Road, Dahisar - East, Mumbai - 400 068
I40: Conveyance of the property is executed
B43: (ii) | C43: See the title deeds and ascertain whether they are properly executed in favour of the Society? | I43: Yes
B45: (iii) | C45: State how the lands has been utilised for:-
B46: (a) | C46: Construction of houses. | I46: Yes As per approved plan.
B47: (b) | C47: Construction of roads.
B48: (c) | C48: Open spaces.
B49: (d) | C49: Other purposes. (give details)
B50: (iv) | C50: Have the layouts and plans for development been approved by the Municipal authorities before actual commencement of the work? | I50: Already Constructed
B53: (v) | C53: Have completion certificates been obtained from appropriate authorities for drainage, water supply, roads, etc. before construction work of buildings is commenced? | I53: Already Constructed
A57: 5. | B57: Construction of Buildings :-
B58: {i) | C58: (a) Have building constructions commenced? | I58: Already Constructed
C59: (b) State the No. of houses or flats constructed and under construction. | I59: Already Constructed | K59: 30 Flats
C61: (c) Have the completed houses and flats allotted to members? | I61: Already Constructed
B63: (ii) | C63: Are building constructed on contract basis? See the terms and conditions of contracts and state whether they have been properly observed. Note breaches, if any. | I63: Already Constructed
B67: (iii) | C67: Are these contracts properly sanctioned by the competent authority as per bye-laws of the society? | I67: Already Constructed
B69: (iv) | C69: Have tenders or quotations been called after giving due advertisements in local newspapers? If the work are not given to the contractors quoting the lowest figures, see whether reasons for the same are recorded. | I69: Already Constructed
B73: (v) | C73: Are contractors paid after necessary work progress certificates are obtained from the Architects ? Are running and final bills obtained before payments are made to the contractors? | I73: Already Constructed
B77: (vi) | C77: See the terms on which the architects are employed. Are there any breaches? | I77: Already Constructed
B79: (vii) | C79: See whether completion certificates have been obtained from the qualified engineers and architects, stating that the constructions have been completed according to approved plans, specifications and other terms of contracts. | I79: Already Constructed
B84: (viii) | C84: Is a property register kept in proper form? | I84: Yes
C85: Is it written up-to-date?
B86: (ix) | C86: When buildings are built departmentally, state whether the following books are kept and written up-to-date:- | I86: Already Constructed
C88: (a) Job registers & measurement books. | I88: Already Constructed
C89: (b) Stock registers. | I89: Already Constructed
C90: (c) Are valuation certificates from qualified engineers and/ or architects obtained? | I90: Already Constructed
C92: (d) Is expenditure allocated properly between items of capital and revenue nature? | I92: Already Constructed
B94: (x) | C94: State whether buildings have been constructed according to the original plans and estimates submitted with the loan applications and which are approved by the competent authority. Are there any deviations? If so, are they got approved from the competent authority | I94: Already Constructed
B99: (xi) | C99: In case of flat-owners societies, see whether titles to the land have been transferred in the name of the society. | I99: Yes
B102: (xii) | C102: Are buildings and other constructions got insured? | I102: Yes
B103: (xiii) | C103: In case of flat-owners societies, have the promoters fulfilled their obligations as per agreements entered with them by the members prior to the registration of the society? | I103: Not applicable
B107: (xiv) | C107: Examine the agreements entered into with the promoters and see whether they are in the interest of the society. | I107: Not applicable
B109: (xv) | C109: Has the society executed lease deeds in favour of members for giving plots and/ or buildings on lease to them? | I109: Not Applicable
B112: (xvi) | C112: Has the society created sinking fund as per provisions of the bye-laws? | I112: Yes
B114: (xvii) | C114: Examine the basis on which monthly rents or contributions are fixed in case of tenant co-partnership societies or flat owners societies and see that the following items are adequately covered -
C118: (i) Amounts required for repayment of loan instalments. | I118: Not Applicable
C119: (ii) Municipal and other taxes. | I119: Yes
C120: (iii) Lease rent. | I120: No
C121: (iv) Service charges and common expenses. | I121: Yes
C122: (v) Contribution to the sinking fund. | I122: Yes
A123: 6. | B123: Loans to Members :-
B124: (i) | C124: Are recoveries of loans punctual? | I124: Not Applicable
B125: (ii) | C125: State the amounts of overdues. | I125: Not Applicable
B126: (iii) | C126: State what steps are being taken to recover overdues. | I126: Not Applicable
A127: 7. | B127: Expenditure :-
C128: Has the expenditure been approved by the Managing Committee from time to time? | I128: No
I132: Signature and Designation of Auditing Staff
I133: =+TIT!D9 -> Shri. Bharat C. Boridkar
I134: ="[Empanelment No.: "&TIT!D10&"" -> [Empanelment No.: Mumbai-4/C1/1011404
I135: Govt. Certified Panel Auditor
A136: =+TIT!D12 -> 46275 | I136: =TIT!B11&": "&TIT!D11 -> Address: Boridkar House, Pandurang Bhoir Road, Dahisar - West, Mumbai, Mumbai - 400 068

Sheet SCHAR (2)
A1: =TIT!D2 -> NAVANAND CO-OPERATIVE. HOUSING SOCIETY LTD.
A2: =TIT!D3 -> BOM/WR/HSG/TC/11905 DT. 06/01/2003
A3: =+TIT!D6 -> Maratha Colony Road, Dahisar - East, Mumbai - 400 068
A4: Period:- 01.04.2024 To 31.03.2025
A7: Schedules attached to and forming part of the Audit Report dated :- | J7: =+TIT!D12 -> 46275
A8: Statutory Report as required u/s 81 (2)
A10: SCHEDULE - I
C11: Transactions involving infringment of the provisions of the Act, the Rules & the Bye-laws
D12: - Refer to Audit Memo 1 & General Remarks.
A14: SCHEDULE - II
C15: Particulars of sums which ought to have been but have not been brought into account.
D16: - NIL
A18: SCHEDULE - III
C19: Improper & Irregular payments.
D20: See General Remarks
A22: SCHEDULE - III-A
C23: Irregularities in the realisation of money
D24: - NIL
A26: SCHEDULE - IV
C27: List of doubtful & bad debts
D28: - NIL
A30: SCHEDULE - V
C31: List of the movable & immovable properties & other assets considered doubtful of realisation
D32: - NIL
A34: SCHEDULE - VI
C35: Personal Expenditure debited to revenue
D36: - NIL
C44: =+TIT!D9 -> Shri. Bharat C. Boridkar
C45: Govt. Certified Panel Auditor
C46: [Panel No.: C1-15145]
C47: =+TIT!D12 -> 46275

Sheet GR
A1: =+TIT!D2 -> NAVANAND CO-OPERATIVE. HOUSING SOCIETY LTD.
A2: ="General Remarks and Observations attached to and forming part of the audit report dated "&TEXT(TIT!D12,"dd-mmm-yyyy") -> General Remarks and Observations attached to and forming part of the audit report dated 10-Sep-2026
A4: INTRODUCTION | V4: Department of Cooperation, Marketing and Textile
A5: 1 | B5: Name of the society | F5: :- | G5: =+TIT!D2 -> NAVANAND CO-OPERATIVE. HOUSING SOCIETY LTD. | V5: Date : 18/07/2016 19:17:58
V6: Dear BHARAT CHANDRAKANT BORIDKAR,
A7: 2 | B7: Register Address | F7: :- | G7: =+TIT!D6 -> Maratha Colony Road, Dahisar - East, Mumbai - 400 068 | V7: Audit Order is generated by following users:
F8: :- | V8: Auditor Name:BHARAT CHANDRAKANT
A9: 3 | B9: Reg. No & date | F9: :- | G9: =+TIT!D3 -> BOM/WR/HSG/TC/11905 DT. 06/01/2003 | V9: BORIDKAR
A10: 4 | B10: Period of audit | F10: :- | G10: 01-Apr-2024 To 31-Mar-2025 | V10: Society Name :JATIN CO OP HSG SOC LTD
A11: 5 | B11: Audit classification | F11: :- | G11: "B" | V11: Auditor Type :Certified Auditor Individual
V12: Society Type :Housing societies having less than
A13: GENERAL REMARKS (PART-A) | V13: 100 members
A14: The following are the major discrepancies found during the audit. | V14: Auditor Empanelment Number :1011404 Society District :Mumbai 4
A15: Sr no | B15: Particulars | E15: Instances / Examples which requires reporting | L15: Auditor’s remarks | V15: Society Taluka:Ward R North
A16: 1 | B16: Fraud | E16: 1) Debiting excess amount than the voucher amount / bill amount. | L16: During the year under audit, I have not found any such instance. | V16: Society Village:Borivali
E17: 2) Withdrawing the amount from bank but not crediting in cash book | L17: During the year under audit, I have not found any such instance. However, on a few occasions, cash withdrawals had been recorded in petty cash book on a day(s) prior to actual day(s) of withdrawal of cash from bank. | V17: Regards,
E18: 3) Debiting the bank account without depositing the amount in bank | L18: During the year under audit, I have not found any such instance. | V18: eSahakar
E19: 4) Disbursing loans without sanction / without security / without loan documents / using forge documents | L19: During the year under audit, I have not found any such instance. The society is Housing Society. | V19: Online Audit Management System
E20: 5) Any other transaction with the intention to defraud the society by any person. | L20: On the basis of verification of record made available to me, during the year under audit, I have not found any such instance. | V20: Department of Cooperation, Marketing and Textile
A21: 2 | B21: Misutilisation of funds and properties | E21: 1) purchasing / constructing building without inviting the tenders | L21: During the year under audit, I have not found any such instance.
E22: 2) purchasing the computers / fixed assets without inviting the tenders. | L22: During the year under audit, I have not found any such instance.
E23: 3) selling the movable / immovable properties without inviting bids | L23: During the year under audit, I have not found any such instance.
E24: 4) selling the movable / immovable properties below Reserve Price (Upset price) | L24: During the year under audit, I have not found any such instance.
A25: 3 | B25: Misapplication of funds | E25: 1) Use of sinking fund for day to day maintenance without passing required resolution in General Body. | L25: During the year under audit, I have not found any such instance.
E26: 2) Use of revenue reserve / general reserve for creating Reserve for Bad and Doubtful Debts. | L26: During the year under audit, I have not found any such instance.
A27: 4 | B27: Manipulation of accounts | L27: I have not found any manipulation of accounts during the year under audit.
A28: 5 | B28: Falsification of accounts | L28: I have not found any Falsification of accounts during the year under audit.
A29: 6 | B29: Shortfall in various provisions | L29: There is no material shortfall in recognition of liability for outstanding expenses/provisions
A32: 7 | B32: Infringement of the M C S Act, 1960, Rules, 1961 and the Bye-Laws of the Society
B33: Srn | C33: Act | D33: Rules | E33: Bye-laws @ | G33: Descriptions
B34: 1 | C34: 70 | D34: 54,55 | E34: 15 | G34: Investment of Sinking Fund is short by about Rs. 1.41 lakhs | T34: 288436 | U34: =77368+4761 -> 82129 | V34: =+T34-U34 -> 206307
B35: 2 | E35: 20 | G35: A Sublette / licensee not applied for Nominal Membership of the Society.
B36: 3 | C36: 26(1) | E36: 22 (b) | G36: Increase in minimum contribution of member in share capital to exercise right of membership. [Minimum number of shares 10 per member]
B37: 4 | C37: 73b | E37: 114 | G37: Strength, composition and quorum of the managing committee.
B38: 5 | C38: 24A | G38: Not organising co-operative education and training for members and committee members
B39: 6 | C39: 82 | D39: 73 | E39: 153 (a) | G39: Audit rectification report in “O” form not placed in managing committee meeting and submission to Registering Authority and auditor for her comments.
A41: Sr no | B41: Particulars | E41: Instances / Examples which requires reporting | L41: Auditor’s remarks
A42: 8 | B42: Personal expenses debited to Income and expenditure account. | L42: During the year under audit, I have not found any such instance.
A43: 9 | B43: Transactions with relatives of members of managing committee, companies, firms in which members of managing committee are interested, which are not at the reasonable rates. | L43: During the year under audit, I have not found any such instance.
A44: 10 | B44: No action against overdue in excess of one year | L44: According to the information and explanations given to us and based on our examination of the records of the society, the Following flats have amount outstandings which includes ovedue for a period exceeding one year.
L45: Flat No. 003 | O45: Rs. 87,285/-
L46: During the audit, I have informed that , society has taken legal action for recovery in respect of members having arrears for more than one year.
K53: =+TIT!D9 -> Shri. Bharat C. Boridkar
K54: Govt. Certified Panel Auditor
A55: =+TIT!D12 -> 46275 | K55: [Panel No.: Mumbai-4/C1/15145]
A59: GENERAL REMARKS (PART-B)
A60: INTRODUCTION
B61: ="I have been appointed as the Statutory auditors of "&TIT!D2&" "&TIT!E2&" by members of "&TIT!D2&" in their Annual General Body Meeting Dt. 29-Sep-2024 . Accordingly I have completed the Audit work. " -> I have been appointed as the Statutory auditors of NAVANAND CO-OPERATIVE. HOUSING SOCIETY LTD. by members of NAVANAND CO-OPERATIVE. HOUSING SOCIETY LTD. in their Annual General Body Meeting Dt. 29-Sep-2024 . Accordingly I have completed the Audit work. | T61: DDR Order generated on 30/10/2018 20:34:57 for Statutory audit of NAVANAND CO-OP. HOUSING SOCIETY LTD. - Society Registration No: BOM/WR/HSG/TC/11905 DT. 06/01/2003 for the Financial Year ending on 31-Mar-2019
B62: The audit has been conducted for the period 1st April 2024 to 31st March 2025. This statutory audit is based on the books of accounts, records, financial statements, annexures, and other relevant documents maintained in the computer system, and has been verified accordingly. Both written and oral information provided by the management at the time of the audit has been relied upon during the course of this work. It is assumed that all transactions have been carried out in compliance with the Maharashtra State Co-operative Societies Act, 1960, the Rules of 1961, and the Bye-Laws of the Society. | T62: I have been appointed as the Statutory auditors of VIVEK ENCLAVE CO-OPERATIVE HOUSING SOCIETY LIMITED Mandapeshwar Road, Borivali (W), Mumbai - 400103 by e-Sahakar, Online Audit Management System, Department of Cooperation, Marketing and Textile e-audit order generated Dt. 18/07/2016. Accordingly I have completed the Audit work.
B63: It is presumed that the computer-generated entries and transactions are strictly accurate, in proper working order as per standard software/programming requirements, and free from internal defects. The Society shall be solely responsible for any subsequent changes made to the records.
B64: Information obtained and irregularities observed during the audit are presented in Parts A, B, and C of this report. Upon compliance with the irregularities noted, an Audit Compliance Report is to be submitted.
A66: Management:
B67: The five-yearly election of the Managing Committee of the Society for the period 2024 to 2029 was conducted on 08th June-2025, under the supervision of the Election Officer, Mr. Gautam B. Jadhav (Panel No. 247/2025). Pursuant to the said election, a new Managing Committee has been duly constituted. From among the elected members, the following members have been selected as the Office Bearers of the Managing Committee of the Society.
A68: Management:
B69: The list of management committee as on 31st March 2024 is provided by the Society. The Office bearers for the audit period are as under:
C70: Chairman | G70: - | H70: Shri. Prakash Gogari
C71: Secretary | G71: - | H71: Shri. Dilip G. Kalgutkar
C72: Treasurer | G72: - | H72: Shri. Harshad Shah
C73: Committee Member | G73: - | H73: Shri.S. Vasamsetti
C74: Committee Member | G74: - | H74: Shri. Pravinkumar Gajera
C75: Committee Member | G75: - | H75: Shri. Santosh Pathare
C76: Committee Member | G76: - | H76: Smt. Pradnya Patwardhan
A78: MEETINGS
B79: ="During the year the Annual General Meeting of the members of the society was held on "&TEXT(TIT!D17,"dd-mm-yyyy") -> During the year the Annual General Meeting of the members of the society was held on 28-09-2025
B80: ="During the year the Special General Meeting of the members of the society was held on "&TEXT(TIT!D18,"dd-mm-yyyy") -> During the year the Special General Meeting of the members of the society was held on 16-11-2024 & 16-02-2025
B81: 1 | C81: The attendance of members at the meeting is recorded in the minute book by way of member signing against the flat number serially written. Name of member is not written. Remark "ABSENT" is not recorded against the flat number of member who did not attend the meeting. | S81: =+TIT!D19 -> 10 | T81: =MID(U81,8,(LEN(U81)-6)) -> #NAME? | U81: #NAME?
B82: 2 | C82: Minutes are either written by hand or printouts are pasted.
B83: 3 | C83: In the case of minutes by pasting of printout, it is advised to affix societies seal on each page with authentication by the chairman of the managing committee meeting in which the minutes are confirmed.
B84: 4 | C84: The folios of the minute book are not serially numbered.
B85: 5 | C85: The resolutions passed are not serially numbered as well as name of person who proposed and seconded the resolution is not mentioned.
B86: Managing Committee
B87: =S81&" ["&T81&"] meetings of the Managing Committee of the Society were held during the year." -> #NAME?
B88: 1 | C88: The place and date of signing the minutes by the chairman are not recorded in the minutes.
B89: 2 | C89: The resolutions passed are not serially numbered as well as name of person who proposed and seconded the resolution is not mentioned.
B90: 3 | C90: The folios of the minute book are not serially numbered.
A91: MEMBERS
B92: There are 30 members in the Society. As informed by the management, during the year, there is no case of transfer or transmission .
A94: UNRECTIFIED AUDIT OBJECTIONS OF PREVIOUS AUDIT REPORT
B95: 1 | C95: Not obtaining balance confirmation from the members for the balances as on year end.
B96: 2 | C96: Non payment of contribution toward education fund.
A97: CONTRAVENTION OF PROVISIONS OF OTHER ALLIED ACT | S97: Excess of Income over Expenditure
B98: 1 | C98: Income tax return is not filed.
B99: 2 | C99: TDS return were not filled.
A102: FINANCIAL PERFORMANCE:
B103: ="During the year under audit the society has shown SURPLUS of Rs. "&ROUND(('I&E'!D36+'I&E'!H36),2) &"/- For the year ending 31-Mar-2024." -> During the year under audit the society has shown SURPLUS of Rs. 58504.82/- For the year ending 31-Mar-2024.
A105: OBSERVATION ON THE BALANCE SHEET AS ON 31-03-2024
A107: Sr. No. | C107: Particulars | J107: 45382 | M107: 45016 | P107: Increase/Decrease
C108: LIABILITIES
A109: 1 | C109: Issued,Subscribed & Paid Up Share Capital | J109: =+'Bal-Sheet'!D9 -> 7500 | M109: =+'Bal-Sheet'!A9 -> 7500 | P109: =+J109-M109 -> 0
A110: 2 | C110: Reserve Fund and Other Reserves | J110: =+SUM('Bal-Sheet'!D15:D29) -> 1197753.5 | M110: =+SUM('Bal-Sheet'!A12:A28) -> 1109533.5 | P110: =+J110-M110 -> 88220
A111: 3 | C111: Current Liabilities & Provisions | J111: =+'Bal-Sheet'!D39 -> 214637 | M111: =+SUM('Bal-Sheet'!A34:A39) -> 104511 | P111: =+J111-M111 -> 110126
A112: 4 | C112: Advances from Members | J112: =+'Bal-Sheet'!D43 -> 13861 | M112: =+'Bal-Sheet'!A43 -> 23563 | P112: =+J112-M112 -> -9702
A113: 5 | C113: Property Tax Payable | J113: =+'Bal-Sheet'!D45 -> 251296 | M113: =+'Bal-Sheet'!A45 -> 251296 | P113: =+J113-M113 -> 0
A114: 5 | C114: Income & Expenditure Account | J114: =+'Bal-Sheet'!D51 -> 505284.92 | M114: =+'Bal-Sheet'!A50 -> 446780.1 | P114: =+J114-M114 -> 58504.82
C115: TOTAL :- | J115: =SUM(J109:L114) -> 2190332.5 | M115: =SUM(M109:O114) -> 1943183.6 | P115: =SUM(P109:R114) -> 247148.82
C116: ASSETS
A117: 1 | C117: Cash & Bank Balances | J117: =+'Bal-Sheet'!H9 -> 637224.46 | M117: =+SUM('Bal-Sheet'!E7:E9) -> 360685.64 | P117: =+J117-M117 -> 276538.82
A118: 2 | C118: Investments | J118: =+'Bal-Sheet'!H16+'Bal-Sheet'!H19 -> 1367504 | M118: =+SUM('Bal-Sheet'!E12:E19) -> 1515971 | P118: =+J118-M118 -> -148467
A119: 3 | C119: Fixed Assets (At Cost) | J119: =+SUM('Bal-Sheet'!H30:H40) -> 47431 | M119: =+SUM('Bal-Sheet'!E27:E42) -> 54747 | P119: =+J119-M119 -> -7316
A120: 4 | C120: Security Deposits | J120: =+'Bal-Sheet'!H22 -> 32335 | M120: =+SUM('Bal-Sheet'!E21:E22) -> 32335 | P120: =+J120-M120 -> 0
...

Sheet SCH (2)
A1: =+TIT!D2 -> NAVANAND CO-OPERATIVE. HOUSING SOCIETY LTD.
A2: ="Schedules attached to and forming part of the Annual Account for the year ended "& TIT!D8 -> Schedules attached to and forming part of the Annual Account for the year ended 31st March, 2026
A4: A | B4: Accounting Conventions:
B5: 1 | D5: The financial statements have been prepared under the historical cost convention, in accordance with the generally accepted accounting policies and according to the provisions of the Maharashtra Co op Societies Act, 1960 and Rules framed there under and registered Bye-laws of the society and the same, unless specifically referred otherwise, are adopted consistently by the society.
B10: 2 | C10: Recognition of Income and Expenditure:
D11: The society generally follows accrual system of accounting and recognises significant items of income and expenditure on accrual basis except contributions by members towards Non-Agricultural Tax and its payment, annual contribution towards the education and training fund of the State federal society and ex-gratia to watchmen and sweeper.
B15: 3 | C15: Fixed Assets:
D16: Fixed assets are stated at cost less depreciation. Cost comprises of cost of acquisition and any attributable cost of bringing the asset to condition for its intended use.
B19: 4 | C19: Depreciation:
D20: Depreciation is provided for number of days fixed assets put to use during the year, on written down value (WDV) at the rates prescribed under the Income Tax Act, 1961.
B24: 5 | C24: Investments:
D25: Investments are stated at cost.
B26: 6 | C26: Contingent Liabilities:
D27: Contingent liabilities are not provided for and, if any, the same is disclosed by way of note.
A29: B | B29: Notes on Accounts:
B30: 1 | C30: Previous year figures:
D31: Previous year figures have been re-worked, re-grouped, re-arranged and re-classified wherever necessary to facilitate comparison with the current year figure.
D33: The dues from members and credit balances of members security deposits with MCGM & Adani Electricity are subject to confirmation.
D34: In the opinion of the Managing Committee, the value of other assets is as stated in the financial statement, if realised in the ordinary course of operations of the Society.
B35: 2 | C35: Contingent Liabilities | L35: Nil
H37: ="For "&TIT!$D$2 -> For NAVANAND CO-OPERATIVE. HOUSING SOCIETY LTD.
H42: Chairman Secretary Tresurer
D43: =+TIT!D9 -> Shri. Bharat C. Boridkar
D44: Govt. Certified Panel Auditor
D45: [Panel No.: C1-15145]
D46: =+TIT!D12 -> 46275

Sheet I&E
A1: =+TIT!D2 -> NAVANAND CO-OPERATIVE. HOUSING SOCIETY LTD.
A2: =" "&TIT!A3&" "&TIT!D3&" " -> Registration No. BOM/WR/HSG/TC/11905 DT. 06/01/2003
A3: =+TIT!D6 -> Maratha Colony Road, Dahisar - East, Mumbai - 400 068
A4: INCOME & EXPENDITURE ACCOUNT FOR THE YEAR ENDED 31/03/2026
A5: Previous Year | B5: Expenditure | C5: Current Year | E5: Previous Year | F5: Income | G5: Current Year
B6: TO RENT RATES TAXES | F6: By Collection From Members
A7: 84982 | B7: " Property Tax | C7: 103516 | E7: 84982 | F7: " Property Tax | G7: 139668 | K7: =+G7-C7 -> 36152
A8: 94974 | B8: " Water Charges | C8: 105609 | E8: 69600 | F8: " Water Charges | G8: 69600
A9: 77790 | B9: " Electricity Charges | C9: 80940 | E9: 155658 | F9: " Maintenance Charges | G9: 162000
A10: 0 | B10: " Non-Agricultural Tax | C10: 0 | D10: =SUM(C7:C10) -> 290065 | E10: 10600 | F10: " Non-Occupancy Charges | G10: 8500
B11: TO BUILDING MAINTENANCE EXP | E11: 22680 | F11: " Parking Charges | G11: 23200
A12: 23322 | B12: " Repairs & Maintenance Expenses | C12: 29295 | E12: 152626 | F12: " Additional Maintenance Charges | G12: 51272
A13: 33806 | B13: " Lift Maintenance Expenses | C13: 37293 | E13: 0 | F13: " Additional Property Tax | G13: 9264
A14: 30000 | B14: " Sweepar Labour Charges | C14: 41000 | E14: 14400 | F14: " Insurance Charges | G14: 14400
A15: 163150 | B15: " Security Expenses | C15: 116100 | E15: 52200 | F15: " Electricity Charges | G15: 52200
A16: 5990 | B16: " CCTV Maintenance Expenses | C16: 8812 | E16: 46800 | F16: " Lift Maintenance | G16: 46800
A17: 4100 | B17: " Diwali Bonus to Security/Sweepar | C17: 6500 | E17: 16200 | F17: " Audit & Accounts | G17: 16200
A18: 10970 | B18: " Pest Control Expenses | C18: 8288 | E18: 3600 | F18: " Education & Training | G18: 3600
A19: 13891 | B19: " Building Insurance | C19: 14487 | D19: =SUM(C12:C19) -> 261775 | E19: 10205 | F19: " Interest on Arrears | G19: 13660 | H19: =SUM(G7:G19) -> 610364
B20: TO ADMINISTRATIVE EXPENSES
A21: 680 | B21: " Conveyance expenses | C21: 2425
A22: 6053 | B22: " Printing & Stationary | C22: 1715 | E22: 0 | F22: " MDCC Bank Dividened | H22: 0
A23: 2690 | B23: " Miscellaneous Expenses | C23: 1875
A24: 10000 | B24: " Election Expenses | C24: 0 | F24: By Interest Received
A25: 409.67 | B25: " Bank Charges | C25: 25.18 | F25: Mumbai Dist. Co-Op. Bank - # 87
A26: 12000 | B26: " Account Writting Charges | C26: 12000 | E26: 0 | F26: a) Saving Account | G26: 0
A27: 3000 | B27: " Statutory Audit Fees | C27: 3500 | E27: 2673 | F27: b) Fixed Deposit | G27: 2880 | H27: =+G26+G27 -> 2880
A28: 73000 | B28: " Professional Fees | C28: 3000 | D28: =SUM(C21:C28) -> 24540.18 | F28: Saraswat Co-op Bank #981452
E29: 8517 | F29: a) Saving Account | G29: 15302
A30: 0 | B30: To Income Tax paid | D30: 0 | E30: 86130 | F30: b) Fixed Deposit | G30: =84636-2880 -> 81756 | H30: =+G29+G30 -> 97058
A31: 8489 | B31: To Depreciation - Fixed Assets | D31: =+'Bal-Sheet'!G30+'Bal-Sheet'!G32+'Bal-Sheet'!G34+'Bal-Sheet'!G36+'Bal-Sheet'!G38+'Bal-Sheet'!G40 -> 7316
A32: 50000 | B32: To Redevelopment Expenses | D32: 45000
A33: 3600 | B33: To Transfer to Education & Training Fund | D33: 3600 | E33: 50000 | F33: Tender Money | H33: 0
E34: 4000 | F34: Miscellaneous Income | H34: 0
A35: 19493 | B35: 25% of Surplus Transferred to Reserve Fund | D35: 19501
A36: 58481.33 | B36: " Excess of Income Over Expenditure | D36: 58504.82 | J36: 77974 | K36: =+J36*25% -> 19493.5
A38: =SUM(A7:A37) -> 790871 | B38: TOTAL :- | D38: =SUM(D7:D37) -> 710302 | E38: =SUM(E6:E37) -> 790871 | F38: TOTAL :- | H38: =SUM(H7:H37) -> 710302
A39: As per my report on even date. | I39: CY | J39: PY
E40: =" For "&TIT!D2&" " -> For NAVANAND CO-OPERATIVE. HOUSING SOCIETY LTD. | I40: =+H38-D38 -> 0 | J40: =+E38-A38 -> 0
A43: =+TIT!D9 -> Shri. Bharat C. Boridkar
A44: Govt. Certified Panel Auditor
A45: Empanelment No.: Mumbai-4/C1/1011404 | E45: (Chairman) (Secretary) (Treasurer)
A46: =+TIT!D12 -> 46275
B49: Insurance | D49: 14596 | G49: 28588.6
B50: 24/11/2023 to 31/03/2024 | D50: =7+31+31+29+31 -> 129 | E50: =+D49/366*D50 -> 5144.4918 | G50: 29088.6
B51: 01/04/2024 to 23/11/2024 | D51: =30+31+30+31+31+30+31+23 -> 237 | E51: =+D49-E50 -> 9451.5082 | G51: =+G49-G50 -> -500
D52: =+D50+D51 -> 366
B54: Lift Maint | D54: 32243
B55: 01/10/2023 to 31/03/2024 | D55: =31+30+31+31+29+31 -> 183 | E55: =+D54/366*D55 -> 16121.5
B56: 01/04/2024 to 30/09/2024 | D56: =366-D55 -> 183 | E56: =+D54-E55 -> 16121.5
D57: =+D55+D56 -> 366
B59: Water Chgs | D59: 20932
B60: 25-01-2024 to 31-03-2024 | C60: =7+29+31 -> 67 | D60: 67 | E60: =+D59/90*D60 -> 15582.711
B61: 01-04-2024 To 23-04-2023 | C61: 23 | D61: 23 | E61: =+D59/90*D61 -> 5349.2889
B64: Pest Control | D64: 11000
B65: 01/01/2024 To 31/03/2024 | D65: =31+29+31 -> 91 | E65: =+D64/365*D65 -> 2742.4658
B66: 01/04/2024 to 31/12/2024 | D66: =30+31+30+31+31+30+31+30+31 -> 275 | E66: =+D64-E65 -> 8257.5342
D67: =+D65+D66 -> 366
B69: CCTV | D69: 3500
B70: 01/01/2024 To 31/03/2024 | D70: =31+29+31 -> 91 | E70: =+D69/365*D70 -> 872.60274
B71: 01/04/2024 to 31/12/2024 | D71: =30+31+30+31+31+30+31+30+31 -> 275 | E71: =+D69-E70 -> 2627.3973
D72: =+D70+D71 -> 366

Sheet Bal-Sheet
A1: =+TIT!D2 -> NAVANAND CO-OPERATIVE. HOUSING SOCIETY LTD.
A2: =" "&TIT!A3&" "&TIT!D3&" " -> Registration No. BOM/WR/HSG/TC/11905 DT. 06/01/2003
A3: =+TIT!D6 -> Maratha Colony Road, Dahisar - East, Mumbai - 400 068
A4: BALANCE SHEET AS AT 31/03/2026
A5: Previous Year | B5: L I A B I L I T I E S | C5: Current Year | D5: Current Year | E5: Previous Year | F5: A S S E T S | G5: Current Year | H5: Current Year
B6: SHARE CAPITAL | F6: CASH & BANK BALANCES
A7: 100000 | B7: Authorised 2000 Shares of Rs.50 Each | C7: =2000*50 -> 100000 | E7: 13 | F7: Cash on hand | G7: 698
E8: 12444 | F8: Mumbai Dist. Co-Op. Bank # 87 | G8: 12444
A9: 7500 | B9: Issued, Subscribed & Paid-Up Capital | D9: =150*50 -> 7500 | E9: 348228.64 | F9: Saraswat Co-op Bank # 981452 | G9: 624082.46 | H9: =SUM(G7:G9) -> 637224.46
B10: 150 shares of Rs.50/- each
B11: RESERVE & OTHER FUNDS | F11: INVESTMENT
A12: 415647.54 | B12: a) Reseve Fund | E12: 100 | F12: One share of M.D.C.H.F. Ltd | G12: 100
B13: Balance as per Last Year Balance Sheet | C13: =+A12 -> 415647.54 | E13: 1000 | F13: One share of M.D.C.C. Ltd. | G13: 1000
B14: Add : Transfer Premium Received during the Year | C14: 0 | E14: 33564 | F14: Fixed Deposits with M.D.C.C. Bank at Dahisar | G14: 33564
B15: Add : 25% Surplus Transferred | C15: =+'I&E'!D35 -> 19501 | D15: =+C13+C14+C15 -> 435148.54 | E15: 1189112 | F15: Fixed Deposits with Saraswat Bank at Dahisar | G15: 1025316
A16: 10940 | B16: b) Entrance Fees | E16: 55824 | F16: Interest Accrued on Fixed Deposit | G16: 52834 | H16: =SUM(G12:G16) -> 1112814
B17: Balance as per Last Year Balance Sheet | C17: =+A16 -> 10940 | F17: SINKING FUND INVESTMENT
B18: Add : Received During the Year | C18: 0 | D18: =+C17+C18 -> 10940 | E18: 213458 | F18: Fixed Deposit with M.D.C.C. Bank at Dahisar | G18: 213458
A19: 388258 | B19: c) Sinking Fund | E19: 22913 | F19: Interest Accrued on FD | G19: 41232 | H19: =SUM(G18:G19) -> 254690
B20: Balance as per Last Year Balance Sheet | C20: =+A19 -> 388258
B21: Add : Member's Contribution for the Year | C21: 10800 | E21: 23200 | F21: Security Deposit with BMC Water Department | G21: 23200
B22: Add : Interest on Investment | C22: 18319 | D22: =+C20+C21+C22 -> 417377 | E22: 9135 | F22: Adani Electricity - Security Deposits | G22: 9135 | H22: =+G21+G22 -> 32335 | J22: =+D22 -> 417377
A23: 268198 | B23: d) Repairs & Maintenance Fund | J23: =+H19 -> 254690
B24: Balance as per Last Year Balance Sheet | C24: =+A23 -> 268198 | E24: 26565 | F24: Dues From Members | H24: 51735 | J24: =+J22-J23 -> 162687 | K24: =+J24/100000 -> 1.62687
B25: Add : Member's Contribution for the Year | C25: 36000
B26: Less : Prior Period Adjustments | C26: 0 | D26: =+C24+C25-C26 -> 304198 | F26: FIXED ASSETS
A27: 26490 | B27: e) Education & Training Fund | E27: 2258 | F27: 1) Furniture & Fixtures
B28: Balance as per Last Year Balance Sheet | C28: =+A27 -> 26490 | F28: Balance as per Last Year Balance Sheet | G28: =+E27 -> 2258 | J28: Total Dep
B29: Add : Member's Contribution for the Year | C29: 3600 | D29: =+C28+C29 -> 30090 | F29: Add : Additions During the year | G29: 0 | J29: =+G30+G32+G34+G36+G38+G40 -> 7316
A30: 100000 | B30: f) Common Ammenities Fund | C30: =+A30 -> 100000 | F30: Less : Depreciation for the year | G30: =ROUND((G28+G29)*10%,0) -> 226 | H30: =+G28+G29-G30 -> 2032
B31: Refund to Shanti Home Builder | C31: -100000 | D31: 0 | E31: 6416 | F31: 2) Office Room | G31: =+E31 -> 6416
F32: Less : Depreciation for the year | G32: =ROUND(G31*10%,0) -> 642 | H32: =+G31-G32 -> 5774
B33: CURRENT LIABILITIES & PROVISIONS | E33: 5704 | F33: 3) Vehicle Parking Shed | G33: =+E33 -> 5704
A34: 20890 | B34: Water Charges | C34: 30000 | F34: Less : Depreciation for the year | G34: =ROUND(G33*10%,0) -> 570 | H34: =+G33-G34 -> 5134
A35: 12200 | B35: Account Writting Charges | C35: 12200 | E35: 3566 | F35: 4) Watchmen Cabin | G35: =+E35 -> 3566
A36: 3000 | B36: Statutory Audit Fees | C36: 3000 | F36: Less : Depreciation for the year | G36: =ROUND(G35*10%,0) -> 357 | H36: =+G35-G36 -> 3209
A37: 64269 | B37: Property Tax Payable | C37: 167785 | E37: 11538 | F37: 5) CCTV System | G37: =+E37 -> 11538
A38: 1652 | B38: Subscription Payable | C38: 1652 | F38: Less : Depreciation for the year | G38: =ROUND(G37*15%,0) -> 1731 | H38: =+G37-G38 -> 9807
A39: 2500 | B39: Sweepar Labour Chgs Payable | C39: 0 | D39: =SUM(C34:C39) -> 214637 | E39: 25265 | F39: 6) Water Pump | G39: =+E39 -> 25265
F40: Less : Depreciation for the year | G40: =ROUND((G39)*15%,0) -> 3790 | H40: =+G39-G40 -> 21475
A43: =30064-6501 -> 23563 | B43: Advances From Members | D43: 13861 | F43: Prepaid Expenses
E44: 17785 | F44: Creation Elevators - Lift Maintenance | G44: 19507
A45: 251296 | B45: Property Tax Payable to Members | D45: 251296 | E45: 10157 | F45: Building Insurance | G45: 9782
E46: 8288 | F46: Pest Control Expenses | G46: 0
A47: 6501 | B47: Unidentified Credit | D47: 6501 | E47: 2637 | F47: Prepaid CCTV Expenses | G47: 2625 | H47: =SUM(G44:G47) -> 31914
B49: INCOME & EXPENDITURE A/C | E49: 20514 | F49: TDS on Fixed Deposits | H49: 28690
A50: 446780.1 | B50: Balance as per Last Year Balance Sheet | C50: =+A50 -> 446780.1
B51: Add : Surplus during the year | C51: =+'I&E'!D36 -> 58504.82 | D51: =+C50+C51 -> 505284.92
A53: =SUM(A9:A51) -> 2049684.6 | B53: TOTAL :- | D53: =SUM(D6:D51) -> 2196833.5 | E53: =SUM(E6:E52) -> 2049684.6 | F53: TOTAL :- | H53: =SUM(H6:H51) -> 2196833.5 | J53: CY | K53: PY
J54: =+H53-D53 -> 0 | K54: =+E53-A53 -> 0
A55: As per my report on even date.
E56: =" For "&TIT!D2&" " -> For NAVANAND CO-OPERATIVE. HOUSING SOCIETY LTD.
A59: =+'I&E'!A43 -> Shri. Bharat C. Boridkar
A60: Govt. Certified Panel Auditor
A61: Empanelment No.: Mumbai-4/C1/1011404 | E61: =+'I&E'!E45 -> (Chairman) (Secretary) (Treasurer)
A62: =+TIT!D12 -> 46275

Sheet FD-2025-2026
A1: NAVANAND CO-OP. HOUSING SOCT. LTD.
A2: INVESTMENT DETAILS FOR THE YEAR 2025-2026
A3: Sr. No. | B3: Name of the Bank | C3: Account No. | D3: FD. No. | E3: Date | F3: Amount | G3: Period (Months) | H3: Rate of Interest | I3: Maturity Date | J3: Maturity Value | K3: Previous Accrued Int | L3: Interest Accrued 2025-26 | M3: Interest Recd 2025-26 | N3: TDS - 2025-2026 | O3: Net
A4: 1 | B4: MDCC Bank-Dahisar | C4: 1202828 | E4: 45253 | F4: 213458 | G4: 24 | H4: 0.0775 | I4: 45984 | J4: 248877 | K4: 22913 | L4: 18319 | O4: =+K4+L4+M4-N4 -> 41232
A5: SINKING FUND INVESTMENT (A) | F5: =+F4 -> 213458 | L5: =+L4 -> 18319 | O5: =SUM(O4) -> 41232
A6: 1 | B6: MDCC Bank-Dahisar | C6: 1202829 | E6: 45253 | F6: 33564 | G6: 24 | H6: 0.0775 | I6: 45984 | J6: 39133 | K6: =2673+930 -> 3603 | L6: 2880 | O6: =+K6+L6+M6-N6 -> 6483
A7: 2 | B7: Saraswat Bank - Dahisar | C7: TD0000565751 | F7: 84495 | L7: 392 | N7: 39 | O7: =+K7+L7+M7-N7 -> 353
A8: 3 | B8: Saraswat Bank - Dahisar | C8: TD1000792703 | F8: 80528 | L8: 4060 | N8: 407 | O8: =+K8+L8+M8-N8 -> 3653
A9: 4 | B9: Saraswat Bank - Dahisar | C9: TD0000565754 | F9: 68294 | L9: 1262 | N9: 126 | O9: =+K9+L9+M9-N9 -> 1136
A10: 5 | B10: Saraswat Bank - Dahisar | C10: TD0000565755 | F10: 68386 | L10: 1264 | N10: 127 | O10: =+K10+L10+M10-N10 -> 1137
A11: 6 | B11: Saraswat Bank - Dahisar | C11: TD0000565753 | F11: 68159 | L11: 1260 | N11: 126 | O11: =+K11+L11+M11-N11 -> 1134
A12: 7 | B12: Saraswat Bank - Dahisar | C12: TD0000565756 | F12: 68297 | L12: 1262 | N12: 126 | O12: =+K12+L12+M12-N12 -> 1136
A13: 8 | B13: Saraswat Bank - Dahisar | C13: TD1001162595 | F13: 61434 | L13: 3157 | N13: 315 | O13: =+K13+L13+M13-N13 -> 2842
A14: 9 | B14: Saraswat Bank - Dahisar | C14: TD1001162608 | F14: 61433 | L14: 3157 | N14: 315 | O14: =+K14+L14+M14-N14 -> 2842
A15: 10 | B15: Saraswat Bank - Dahisar | C15: TD1001162619 | F15: 61434 | L15: 3157 | N15: 316 | O15: =+K15+L15+M15-N15 -> 2841
A16: 11 | B16: Saraswat Bank - Dahisar | C16: TD1000756060 | F16: 113819 | L16: 8083 | N16: 809 | O16: =+K16+L16+M16-N16 -> 7274
A17: 15 | B17: Saraswat Bank - Dahisar | C17: TD1001514946 | E17: 45681 | F17: 113802 | K17: 1445 | L17: 8865 | N17: 886 | O17: =+K17+L17+M17-N17 -> 9424
A18: 17 | B18: Saraswat Bank - Dahisar | C18: TD1001514956 | E18: 45681 | F18: 113802 | K18: 1445 | L18: 8865 | N18: 886 | O18: =+K18+L18+M18-N18 -> 9424
A19: 13 | B19: Saraswat Bank - Dahisar | C19: TD1001162632 | F19: 61433 | L19: 3157 | N19: 316 | O19: =+K19+L19+M19-N19 -> 2841
A20: OTHER INVESTMENT : - (B) | F20: =SUM(F6:F19) -> 1058880 | K20: =SUM(K6:K16) -> 3603 | L20: =SUM(L6:L19) -> 50821 | M20: =SUM(M6:M19) -> 0 | N20: =SUM(N6:N19) -> 4794 | O20: =SUM(O6:O19) -> 52520
A23: Total Investment (A + B ) Rs.:- | F23: =+F5+F20 -> 1272338 | L23: =+L20-N20 -> 46027 | M23: `
F26: =+'Bal-Sheet'!E56 -> For NAVANAND CO-OPERATIVE. HOUSING SOCIETY LTD.
F30: Chairman Secretary Treasurer
B43: Saraswat Bank - Dahisar | C43: TD1001162595 | E43: 45393 | F43: 56503 | G43: 15 | H43: 0.075 | I43: 45849 | J43: 62003
B44: Saraswat Bank - Dahisar | C44: TD1001162608 | E44: 45393 | F44: 56502 | G44: 15 | H44: 0.075 | I44: 45849 | J44: 62001
B45: Saraswat Bank - Dahisar | C45: TD1001162619 | E45: 45393 | F45: 56502 | G45: 15 | H45: 0.075 | I45: 45849 | J45: 62001
B46: Saraswat Bank - Dahisar | C46: TD1001162632 | E46: 45393 | F46: 56502 | G46: 15 | H46: 0.075 | I46: 45849 | J46: 62001

Sheet Debtor
A1: =+TIT!D2 -> NAVANAND CO-OPERATIVE. HOUSING SOCIETY LTD.
A2: ="MEMBER'S ARREARS LIST AS ON "&TIT!D8&" " -> MEMBER'S ARREARS LIST AS ON 31st March, 2026
A3: Flat No. | B3: Name | C3: Debit | D3: Credit | H3: 281556.64
A4: 001 | B4: SHREE VAGADVISHA OSWAL MURTIPUJAK JAIN | C4: 0 | H4: 700 | I4: =+H3+G4-H4 -> 280856.64
A5: 002 | B5: SHRE VAGADVISHA OSWAL MURTIPUJAK JAIN | C5: 0 | H5: 6300 | I5: =+I4+G5-H5 -> 274556.64
A6: 003 | B6: SMT. SHEELA P. JOSHI & | C6: 87285 | H6: 7700 | I6: =+I5+G6-H6 -> 266856.64
A7: 004 | B7: SHRI. NEELKANTH N. PATHARE & | C7: 0 | H7: 5000 | I7: =+I6+G7-H7 -> 261856.64
A8: 005 | B8: SHRI. DNYANESHWAR K. MOHOLKAR | D8: 2509 | H8: 2500 | I8: =+I7+G8-H8 -> 259356.64
A9: 101 | B9: SHRI. PRADEEPKUMAR RAJARAM JAISWAL | C9: 0 | H9: 118 | I9: =+I8+G9-H9 -> 259238.64
A10: 102 | B10: SHRI. MADHUKAR R. PEDNEKAR & | D10: 3924 | G10: 2383 | I10: =+I9+G10-H10 -> 261621.64
A11: 103 | B11: SHRI. NARAYAN HARI KADAM | C11: 7731 | H11: 70000 | I11: =+I10+G11-H11 -> 191621.64
A12: 104 | B12: SHRI. SATYANARAYANA VASAMSETTI & | C12: 0 | G12: 3322 | I12: =+I11+G12-H12 -> 194943.64
A13: 105 | B13: SHRI. JAGSHI KARSAN GALA & | C13: 0 | G13: 1530 | I13: =+I12+G13-H13 -> 196473.64
A14: 201 | B14: SMT. JYOTSANABEN P. DOSHI | C14: 370 | G14: 2130 | I14: =+I13+G14-H14 -> 198603.64
A15: 202 | B15: SMT. SARLA GANESH JOSHI | D15: 5246 | G15: 2483 | I15: =+I14+G15-H15 -> 201086.64
A16: 203 | B16: SMT. PRADNYA P. PATWARDHAN & | C16: 0 | G16: 6000 | I16: =+I15+G16-H16 -> 207086.64
A17: 204 | B17: SHRI. MADHUKAR RAMCHANDRA ALWE | D17: 1940 | G17: 2000 | I17: =+I16+G17-H17 -> 209086.64
A18: 205 | B18: SHRI. PRAKASH P. PATWARDHAN | C18: 0 | G18: 2130 | I18: =+I17+G18-H18 -> 211216.64
A19: 301 | B19: SMT. ARUNDHATI JAYRAM RANE | C19: 6489 | G19: 1604 | I19: =+I18+G19-H19 -> 212820.64
A20: 302 | B20: SMT. SMITA VINOD SAVE | C20: 0 | G20: 1764 | I20: =+I19+G20-H20 -> 214584.64
A21: 303 | B21: SHRI. SURENDRA GOPAL RAHATE | C21: 0 | G21: 2972 | I21: =+I20+G21-H21 -> 217556.64
A22: 304 | B22: SHRI. P. DEVENDRA RAO | C22: 0 | G22: 1000 | I22: =+I21+G22-H22 -> 218556.64
A23: 305 | B23: SHRI. MILIND D. MOHOLKAR | C23: 9476 | G23: 2500 | I23: =+I22+G23-H23 -> 221056.64
A24: 401 | B24: SHRI. DILIP G. KALGUTKAR | D24: 3169 | G24: 1823 | I24: =+I23+G24-H24 -> 222879.64
A25: 402 | B25: SHRI. TEJAS BATAVIA | C25: 25 | G25: 1543 | I25: =+I24+G25-H25 -> 224422.64
A26: 403 | B26: SHRI. RAJESH MURJI NISHAR | D26: 1929 | G26: 13314 | I26: =+I25+G26-H26 -> 237736.64
A27: 404 | B27: SHRI. ACHYUT NAVANAND BAGWE | C27: 0 | G27: 13540 | I27: =+I26+G27-H27 -> 251276.64
A28: 405 | B28: SHRI. UNMESH NAVANAND BAGWE | D28: 706 | G28: 2014 | I28: =+I27+G28-H28 -> 253290.64
A29: 501 | B29: SHRI. PRAVINKUMAR K. GAJERA & | C29: 0 | G29: 1560 | I29: =+I28+G29-H29 -> 254850.64
A30: 502 | B30: CAPT. NAKKIRAN WELUSWAMU MUDLIAR & | C30: 6600 | G30: 5258 | I30: =+I29+G30-H30 -> 260108.64
A31: 503 | B31: SHRI NEERAV P. DOSHI & | C31: 4467 | G31: 100000 | I31: =+I30+G31-H31 -> 360108.64
A32: 504 | B32: SHRI. PRAKASH C. GOGARI & | D32: 1954 | G32: 1763 | H32: 431 | I32: =+I31+G32-H32 -> 361440.64
A33: 505 | B33: SMT. KOKILA H. SHAH & | C33: 0
A34: ZZZ | B34: UNKNOWN MEMBERS | D34: 6501
B35: TOTAL | C35: =SUM(C4:C34) -> 122443 | D35: =SUM(D4:D34) -> 27878
I36: 341234 | K36: =2483*2 -> 4966
I37: 343364
B38: =+TIT!D2 -> NAVANAND CO-OPERATIVE. HOUSING SOCIETY LTD. | I38: =+I37-I36 -> 2130
B42: =+'Bal-Sheet'!E61 -> (Chairman) (Secretary) (Treasurer)

Sheet FD-2024-2025
A1: NAVANAND CO-OP. HOUSING SOCT. LTD.
A2: INVESTMENT DETAILS FOR THE YEAR 2024-2025
A3: Sr. No. | B3: Name of the Bank | C3: Account No. | D3: FD. No. | E3: Date | F3: Amount | G3: Period (Months) | H3: Rate of Interest | I3: Maturity Date | J3: Maturity Value | K3: Previous Accrued Int | L3: Interest Accrued 2025-26 | M3: Interest Recd 2025-26 | N3: TDS - 2025-2026 | O3: Net
A4: 1 | B4: MDCC Bank-Dahisar | C4: 1202828 | E4: 45253 | F4: 213458 | G4: 24 | H4: 0.0775 | I4: 45984 | J4: 248877 | K4: 22913 | O4: =+K4+L4+M4-N4 -> 22913
A5: SINKING FUND INVESTMENT (A) | F5: =+F4 -> 213458 | L5: =+L4 -> 0
A6: 2 | B6: MDCC Bank-Dahisar | C6: 1202829 | E6: 45253 | F6: 33564 | G6: 24 | H6: 0.0775 | I6: 45984 | J6: 39133 | K6: =2673+930 -> 3603 | O6: =+K6+L6+M6-N6 -> 3603
A7: 3 | B7: Saraswat Bank - Dahisar | C7: TD0000565751 | E7: 45693 | F7: 78881 | G7: 13 | K7: 791 | M7: 5359 | N7: 536 | O7: =+K7+L7+M7-N7 -> 5614 | P7: =+O7+F7 -> 84495
B8: Saraswat Bank - Dahisar | C8: TD0000565751 | F8: 84495 | L8: 392 | N8: 39 | O8: =+K8+L8+M8-N8 -> 353
A9: 4 | B9: Saraswat Bank - Dahisar | C9: TD1000792703 | E9: 45296 | F9: 75259 | K9: 3826 | M9: 1604 | N9: 161 | O9: =+K9+L9+M9-N9 -> 5269 | P9: =+O9+F9 -> 80528
B10: Saraswat Bank - Dahisar | C10: TD1000792703 | F10: 80528 | L10: 4060 | N10: 407
A11: 5 | B11: Saraswat Bank - Dahisar | C11: TD0000565754 | E11: 45620 | F11: 63734 | K11: 1463 | M11: 3442 | N11: 345 | O11: =+K11+L11+M11-N11 -> 4560 | P11: =+O11+F11 -> 68294
B12: Saraswat Bank - Dahisar | C12: TD0000565754 | F12: 68294 | L12: 1262 | N12: 126
A13: 6 | B13: Saraswat Bank - Dahisar | C13: TD0000565755 | E13: 45620 | F13: 63736 | K13: 1462 | M13: 3442 | N13: 254 | O13: =+K13+L13+M13-N13 -> 4650 | P13: =+O13+F13 -> 68386
B14: Saraswat Bank - Dahisar | C14: TD0000565755 | F14: 68386 | L14: 1264 | N14: 127
A15: 7 | B15: Saraswat Bank - Dahisar | C15: TD0000565753 | E15: 45620 | F15: 63607 | K15: 1459 | M15: 3436 | N15: 343 | O15: =+K15+L15+M15-N15 -> 4552 | P15: =+O15+F15 -> 68159
B16: Saraswat Bank - Dahisar | C16: TD0000565753 | F16: 68159 | L16: 1260 | N16: 126 | O16: =+K16+L16+M16-N16 -> 1134
A17: 8 | B17: Saraswat Bank - Dahisar | C17: TD0000565756 | E17: 45620 | F17: 63737 | K17: 1462 | M17: 3442 | N17: 344 | O17: =+K17+L17+M17-N17 -> 4560 | P17: =+O17+F17 -> 68297
B18: Saraswat Bank - Dahisar | C18: TD0000565756 | F18: 68297 | L18: 1262 | N18: 126
A19: 9 | B19: Saraswat Bank - Dahisar | C19: TD1001162595 | E19: 45393 | F19: 56503 | K19: 3803 | M19: 1253 | N19: 125 | O19: =+K19+L19+M19-N19 -> 4931 | P19: =+O19+F19 -> 61434
B20: Saraswat Bank - Dahisar | C20: TD1001162595 | F20: 61434 | L20: 3157 | N20: 315
A21: 10 | B21: Saraswat Bank - Dahisar | C21: TD1001162608 | E21: 45393 | F21: 56502 | K21: 3804 | M21: 1253 | N21: 126 | O21: =+K21+L21+M21-N21 -> 4931 | P21: =+O21+F21 -> 61433
B22: Saraswat Bank - Dahisar | C22: TD1001162608 | F22: 61433 | L22: 3157 | N22: 315
A23: 11 | B23: Saraswat Bank - Dahisar | C23: TD1001162619 | E23: 45393 | F23: 56502 | K23: 3804 | M23: 1253 | N23: 125 | O23: =+K23+L23+M23-N23 -> 4932 | P23: =+O23+F23 -> 61434
B24: Saraswat Bank - Dahisar | C24: TD1001162619 | F24: 61434 | L24: 3157 | N24: 316
A25: 12 | B25: Saraswat Bank - Dahisar | C25: TD1000756060 | E25: 45033 | F25: 100000 | G25: 24 | H25: 0.0725 | I25: 45764 | J25: 115454 | K25: =7114+6391 -> 13505 | M25: 349 | N25: 35 | O25: =+K25+L25+M25-N25 -> 13819 | P25: =+O25+F25 -> 113819
B26: Saraswat Bank - Dahisar | C26: TD1000756060 | F26: 113819 | L26: 8083 | N26: 809
A27: 13 | B27: Saraswat Bank - Dahisar | C27: TD1001305000 | F27: 226545 | K27: 9835 | M27: 6495 | N27: 650 | O27: =+K27+L27+M27-N27 -> 15680 | P27: =+O27+F27 -> 242225
B28: Saraswat Bank - Dahisar | C28: TD1001305000 | F28: 242225 | L28: 1234 | N28: 213
A29: 15 | B29: Saraswat Bank - Dahisar | C29: TD1001514946 | E29: 45681 | F29: 113802 | K29: 1445 | M29: 8865 | N29: 886 | O29: =+K29+L29+M29-N29 -> 9424 | P29: =+O29+F29 -> 123226
A30: 17 | B30: Saraswat Bank - Dahisar | C30: TD1001514956 | E30: 45681 | F30: 113802 | K30: 1445 | M30: 8865 | N30: 886 | O30: =+K30+L30+M30-N30 -> 9424 | P30: =+O30+F30 -> 123226
A31: 18 | B31: Saraswat Bank - Dahisar | C31: TD1001162632 | F31: 56502 | K31: 3803 | M31: 1253 | N31: 125 | O31: =+K31+L31+M31-N31 -> 4931 | P31: =+O31+F31 -> 61433
A32: 18 | B32: Saraswat Bank - Dahisar | C32: TD1001162632 | F32: 61433 | L32: 3157 | N32: 316
A33: OTHER INVESTMENT : - (B) | F33: =SUM(F6:F32) -> 2262613 | K33: =SUM(K6:K32) -> 55510 | L33: =SUM(L6:L32) -> 31445 | M33: =SUM(M6:M32) -> 50311 | N33: =SUM(N6:N32) -> 8176 | O33: =SUM(O6:O32) -> 102367
A36: Total Investment (A + B ) Rs.:- | F36: =+F5+F33 -> 2476071 | M36: `
F39: =+'Bal-Sheet'!E56 -> For NAVANAND CO-OPERATIVE. HOUSING SOCIETY LTD.
F43: Chairman Secretary Treasurer
B56: Saraswat Bank - Dahisar | C56: TD1001162595 | E56: 45393 | F56: 56503 | G56: 15 | H56: 0.075 | I56: 45849 | J56: 62003
B57: Saraswat Bank - Dahisar | C57: TD1001162608 | E57: 45393 | F57: 56502 | G57: 15 | H57: 0.075 | I57: 45849 | J57: 62001
B58: Saraswat Bank - Dahisar | C58: TD1001162619 | E58: 45393 | F58: 56502 | G58: 15 | H58: 0.075 | I58: 45849 | J58: 62001
B59: Saraswat Bank - Dahisar | C59: TD1001162632 | E59: 45393 | F59: 56502 | G59: 15 | H59: 0.075 | I59: 45849 | J59: 62001

Sheet First Page (2)
A13: =+TIT!D2 -> NAVANAND CO-OPERATIVE. HOUSING SOCIETY LTD.
A15: =+TIT!D3 -> BOM/WR/HSG/TC/11905 DT. 06/01/2003
A16: =+TIT!D6 -> Maratha Colony Road, Dahisar - East, Mumbai - 400 068
A19: ACCOUNT BOOKS FOR THE YEAR 2022-2023
B23: 1 | C23: TRIAL BALANCE
B24: 2 | C24: CASH - BANK BOOK
B25: 3 | C25: GENERAL LEDGER
B26: 4 | C26: JOURNAL REGISTER
B27: 5 | C27: MEMBER ACCOUNT
B28: 6 | C28: MEMBER CONTROL ACCOUNT

Sheet mEETING
C1: Meeting-1 | D1: Meeting-2 | E1: Meeting-3 | F1: Meeting-4 | G1: Meeting-5 | H1: Meeting-6 | I1: Meeting-7 | J1: Meeting-8 | K1: Meeting-9 | L1: Meeting-10 | M1: Meeting-11 | N1: Meeting-12 | O1: Meeting-13
A2: Name of the Trustee | B2: Designation | C2: 45018 | D2: 45039 | E2: 45074 | F2: 45103
A3: Shri. Prakash Gogari | B3: Chairman
A4: Shri. Dilip G. Kalgutkar | B4: Secretary
A5: Shri. Harshad Shah | B5: Treasurer
A6: Shri.S. Vasamsetti | B6: Committee Member
A7: Shri. Pravinkumar Gajera | B7: Committee Member
A8: Shri. Santosh Pathare | B8: Committee Member
A9: Smt. Pradnya Patwardhan | B9: Committee Member
A13: AGM | B13: 45200
A15: SGM-1 | B15: 44913
A16: Meeting conducted to discuss redevelopment project
A18: MC meeting | B18: 45039 | C18: Minutes not written | H18: Sign
B19: 45074 | C19: Signatures of Members were not taken
B20: 45103 | C20: Signatures of Members were not taken
B21: 45135 | C21: Signatures of Members were not taken
A23: 25-04-2025 - 25-07-2025 | B23: 45863 | C23: 18554
A24: 25-07-2025 - 25-10-2025 | B24: 45955 | C24: 21267
B25: =+B24+91 -> 46046 | C25: 35788
A27: Creation Elevators | B27: 39015 | C27: 45931 | D27: 46295 | E27: 45931 | F27: 46112 | G27: 19508
E28: 46113 | F28: 46295 | G28: =+B27-G27 -> 19507
A29: Yogita Bavdhankar - CCTV | B29: 3500 | C29: 46023 | D29: 46387 | G29: =3500/12 -> 291.66667 | H29: =+G29*3 -> 875
A31: Clean Tek | B31: 11000 | C31: 46077 | D31: 46441 | E31: 46077 | F31: 46112 | G31: 36 | H31: 1085
E32: 46113 | F32: 46441 | G32: =365-36 -> 329 | H32: =11000-1085 -> 9915
A34: 10-12-2025 - 31-03-2026 | B34: =22+31+28+31 -> 112 | C34: 4330 | F34: 14112
A35: 46365 | B35: =365-112 -> 253 | C35: 9782

Sheet PETTY-CASH
A2: Sr. | B2: Date | C2: Month | D2: Particular | E2: Total | F2: Printing & Stn | G2: Miscellaneous Exp | H2: Repairs & Maint | I2: Diwali Bonus | J2: Function & Festival | K2: Conveyance | L2: Diff
A3: 37 | B3: 45390 | C3: 45383 | D3: Nilkanth Stationery | E3: 49 | F3: 49 | L3: =+E3-SUM(F3:K3) -> 0
A4: 38 | B4: 45392 | C4: 45383 | D4: Ollwyn Xerox | E4: 94 | F4: 94 | L4: =+E4-SUM(F4:K4) -> 0
A5: 70 | B5: 45397 | C5: 45383 | D5: Conveyance to visit Builder Office | E5: 150 | K5: 150 | L5: =+E5-SUM(F5:K5) -> 0
A6: 39 | B6: 45404 | C6: 45383 | D6: Ollwyn Xerox | E6: 130 | F6: 130 | L6: =+E6-SUM(F6:K6) -> 0
A7: 71 | B7: 45417 | C7: 45413 | D7: Conveyance to visit Builder Office | E7: 80 | K7: 80 | L7: =+E7-SUM(F7:K7) -> 0
A8: 72 | B8: 45417 | C8: 45413 | D8: Tea & Snacks | E8: 125 | G8: 125 | L8: =+E8-SUM(F8:K8) -> 0
A9: 30 | B9: 45440 | C9: 45413 | D9: Nilkanth Stationery | E9: 50 | F9: 50 | L9: =+E9-SUM(F9:K9) -> 0
A10: 36 | B10: 45442 | C10: 45413 | D10: Nilkanth Stationery | E10: 30 | F10: 30 | L10: =+E10-SUM(F10:K10) -> 0
A11: 34 | B11: 45446 | C11: 45444 | D11: Nilkanth Stationery | E11: 99 | F11: 99 | L11: =+E11-SUM(F11:K11) -> 0
A12: 31 | B12: 45452 | C12: 45444 | D12: Nilkanth Stationery | E12: 26 | F12: 26 | L12: =+E12-SUM(F12:K12) -> 0
A13: 33 | B13: 45452 | C13: 45444 | D13: Shree Ganesh Stores | E13: 250 | F13: 250 | L13: =+E13-SUM(F13:K13) -> 0
A14: 32 | B14: 45458 | C14: 45444 | D14: Nomination Form | E14: 60 | F14: 60 | L14: =+E14-SUM(F14:K14) -> 0
A15: 74 | B15: 45458 | C15: 45444 | D15: Conveyance to visit Builder Office | E15: 125 | K15: 125 | L15: =+E15-SUM(F15:K15) -> 0
A16: 73 | B16: 45463 | C16: 45444 | D16: Tea & Snacks to labours - cleaning water tank | E16: 100 | G16: 100 | L16: =+E16-SUM(F16:K16) -> 0
A17: 79 | B17: 45464 | C17: 45444 | D17: Repairing watch at watchman cabin | E17: 210 | H17: 210 | L17: =+E17-SUM(F17:K17) -> 0
A18: 29 | B18: 45465 | C18: 45444 | D18: Nilkanth Stationery | E18: 25 | F18: 25 | L18: =+E18-SUM(F18:K18) -> 0
A19: 35 | B19: 45465 | C19: 45444 | D19: Ollwyn Xerox | E19: 336 | F19: 336 | L19: =+E19-SUM(F19:K19) -> 0
A20: 27 | B20: 45488 | C20: 45474 | D20: Ollwyn Xerox | E20: 216 | F20: 216 | L20: =+E20-SUM(F20:K20) -> 0
A21: 75 | B21: 45488 | C21: 45474 | D21: Conveyance to visit Advocate Office | E21: 175 | K21: 175 | L21: =+E21-SUM(F21:K21) -> 0
A22: 28 | B22: 45489 | C22: 45474 | D22: Nilkanth Stationery | E22: 18 | F22: 18 | L22: =+E22-SUM(F22:K22) -> 0
A23: 24 | B23: 45496 | C23: 45474 | D23: Nilkanth Stationery | E23: 42 | F23: 42 | L23: =+E23-SUM(F23:K23) -> 0
A24: 26 | B24: 45496 | C24: 45474 | D24: Nilkanth Stationery | E24: 40 | F24: 40 | L24: =+E24-SUM(F24:K24) -> 0
A25: 78 | B25: 45498 | C25: 45474 | D25: Paid to watchman for electrical repairs | E25: 200 | H25: 200 | L25: =+E25-SUM(F25:K25) -> 0
A26: 21 | B26: 45499 | C26: 45474 | D26: Nilkanth Stationery | E26: 18 | F26: 18 | L26: =+E26-SUM(F26:K26) -> 0
A27: 25 | B27: 45499 | C27: 45474 | D27: Selection Centre | E27: 80 | F27: 80 | L27: =+E27-SUM(F27:K27) -> 0
A28: 80 | B28: 45500 | C28: 45474 | D28: Cleaning Society premises | E28: 150 | H28: 150 | L28: =+E28-SUM(F28:K28) -> 0
A29: 23 | B29: 45503 | C29: 45474 | D29: Nilkanth Stationery | E29: 215 | F29: 215 | L29: =+E29-SUM(F29:K29) -> 0
A30: 22 | B30: 45504 | C30: 45717 | D30: Nilkanth Stationery | E30: 66 | F30: 66 | L30: =+E30-SUM(F30:K30) -> 0
A31: 55 | B31: 45522 | C31: 45505 | D31: Water | E31: 160 | G31: 160 | L31: =+E31-SUM(F31:K31) -> 0
A32: 54 | B32: 45524 | C32: 45505 | D32: Nilkanth Stationery | E32: 103 | F32: 103 | L32: =+E32-SUM(F32:K32) -> 0
A33: 82 | B33: 45529 | C33: 45505 | D33: Repairing Tap of overhead water tank | E33: 500 | H33: 500 | L33: =+E33-SUM(F33:K33) -> 0
A34: 53 | B34: 45532 | C34: 45505 | D34: Nilkanth Stationery | E34: 135 | F34: 135 | L34: =+E34-SUM(F34:K34) -> 0
A35: 58 | B35: 45536 | C35: 45536 | D35: Nilkanth Stationery | E35: 61 | F35: 61 | L35: =+E35-SUM(F35:K35) -> 0
A36: 60 | B36: 45547 | C36: 45536 | D36: Nilkanth Stationery | E36: 36 | F36: 36 | L36: =+E36-SUM(F36:K36) -> 0
A37: 48 | B37: 45548 | C37: 45536 | D37: The Mumbai District Co-op Housing Federation Ltd. | E37: 230 | F37: 230 | L37: =+E37-SUM(F37:K37) -> 0
A38: 57 | B38: 45548 | C38: 45536 | D38: Nilkanth Stationery | E38: 35 | F38: 35 | L38: =+E38-SUM(F38:K38) -> 0
A39: 56 | B39: 45550 | C39: 45536 | D39: Nilkanth Stationery | E39: 300 | F39: 300 | L39: =+E39-SUM(F39:K39) -> 0
A40: 51 | B40: 45559 | C40: 45536 | D40: Nilkanth Stationery | E40: 325 | F40: 325 | L40: =+E40-SUM(F40:K40) -> 0
A41: 50 | B41: 45562 | C41: 45536 | D41: Selection Centre | E41: 80 | F41: 80 | L41: =+E41-SUM(F41:K41) -> 0
A42: 49 | B42: 45563 | C42: 45536 | D42: Shree Ganesh Stores | E42: 200 | G42: 200 | L42: =+E42-SUM(F42:K42) -> 0
A43: 81 | B43: 45563 | C43: 45536 | D43: Cleaning Society premises | E43: 150 | H43: 150 | L43: =+E43-SUM(F43:K43) -> 0
A44: 47 | B44: 45569 | C44: 45566 | D44: Nilkanth Stationery | E44: 85 | F44: 85 | L44: =+E44-SUM(F44:K44) -> 0
A45: 45 | B45: 45580 | C45: 45566 | D45: Nilkanth Stationery | E45: 40 | F45: 40 | L45: =+E45-SUM(F45:K45) -> 0
A46: 46 | B46: 45580 | C46: 45566 | D46: Nilkanth Stationery | E46: 40 | F46: 40 | L46: =+E46-SUM(F46:K46) -> 0
A47: 44 | B47: 45581 | C47: 45566 | D47: Nilkanth Stationery | E47: 34 | F47: 34 | L47: =+E47-SUM(F47:K47) -> 0
A48: 43 | B48: 45583 | C48: 45566 | D48: Nilkanth Stationery | E48: 190 | F48: 190 | L48: =+E48-SUM(F48:K48) -> 0
A49: 63 | B49: 45588 | C49: 45566 | D49: Diwali Bonus to Watchman | E49: 1500 | I49: 1500 | L49: =+E49-SUM(F49:K49) -> 0
A50: 64 | B50: 45588 | C50: 45566 | D50: Diwali Bonus to Watchman | E50: 100 | I50: 100 | L50: =+E50-SUM(F50:K50) -> 0
A51: 65 | B51: 45588 | C51: 45566 | D51: Diwali Bonus to Sweepar | E51: 1500 | I51: 1500 | L51: =+E51-SUM(F51:K51) -> 0
A52: 66 | B52: 45588 | C52: 45566 | D52: Diwali Toran | E52: 200 | J52: 200 | L52: =+E52-SUM(F52:K52) -> 0
A53: 67 | B53: 45588 | C53: 45566 | D53: Diwali Bonus to Postman | E53: 200 | I53: 200 | L53: =+E53-SUM(F53:K53) -> 0
A54: 68 | B54: 45588 | C54: 45566 | D54: Diwali Bonus to BMC Labour | E54: 400 | I54: 400 | L54: =+E54-SUM(F54:K54) -> 0
A55: 69 | B55: 45588 | C55: 45566 | D55: Diwali Bonus to BMC - Pest Control | E55: 400 | I55: 400 | L55: =+E55-SUM(F55:K55) -> 0
A56: 41 | B56: 45589 | C56: 45566 | D56: Shree Chamunda Dairy | E56: 1320 | G56: 1320 | L56: =+E56-SUM(F56:K56) -> 0
A57: 42 | B57: 45593 | C57: 45566 | D57: Om Sai Medical & General Stores | E57: 36 | H57: 36 | L57: =+E57-SUM(F57:K57) -> 0
A58: 62 | B58: 45602 | C58: 45597 | D58: Ollwyn Xerox | E58: 86 | F58: 86 | L58: =+E58-SUM(F58:K58) -> 0
A59: 76 | B59: 45612 | C59: 45597 | D59: Colddrinks during meeting | E59: 175 | G59: 175 | L59: =+E59-SUM(F59:K59) -> 0
A60: 61 | B60: 45631 | C60: 45627 | D60: Mahavir Collection | E60: 80 | F60: 80 | L60: =+E60-SUM(F60:K60) -> 0
A61: 77 | B61: 45636 | C61: 45627 | D61: Conveyance to visit Architect's Office | E61: 150 | K61: 150 | L61: =+E61-SUM(F61:K61) -> 0
A62: 85 | B62: 45641 | C62: 45627 | D62: Repairing parking shade | E62: 700 | H62: 700 | L62: =+E62-SUM(F62:K62) -> 0
A63: 19 | B63: 45692 | C63: 45689 | D63: Nilkanth Stationery | E63: 30 | F63: 30 | L63: =+E63-SUM(F63:K63) -> 0
A64: 84 | B64: 45704 | C64: 45689 | D64: Tea & Snacks during meeting | E64: 150 | G64: 150 | L64: =+E64-SUM(F64:K64) -> 0
A65: 18 | B65: 45705 | C65: 45689 | D65: Nilkanth Stationery | E65: 40 | F65: 40 | L65: =+E65-SUM(F65:K65) -> 0
A66: 17 | B66: 45706 | C66: 45689 | D66: Nilkanth Stationery | E66: 68 | F66: 68 | L66: =+E66-SUM(F66:K66) -> 0
A67: 20 | B67: 45707 | C67: 45689 | D67: Shrinath Plastics - Water Bottles | E67: 160 | G67: 160 | L67: =+E67-SUM(F67:K67) -> 0
A68: 16 | B68: 45708 | C68: 45689 | D68: Mahavir Collection | E68: 20 | F68: 20 | L68: =+E68-SUM(F68:K68) -> 0
A69: 15 | B69: 45710 | C69: 45689 | D69: Nilkanth Stationery | E69: 98 | F69: 98 | L69: =+E69-SUM(F69:K69) -> 0
A70: 52 | B70: 45716 | C70: 45689 | D70: Mahavir Collection | E70: 29 | F70: 29 | L70: =+E70-SUM(F70:K70) -> 0
A71: 14 | B71: 45720 | C71: 45717 | D71: Nilkanth Stationery | E71: 26 | F71: 26 | L71: =+E71-SUM(F71:K71) -> 0
A72: 12 | B72: 45722 | C72: 45717 | D72: Mahavir Collection | E72: 200 | F72: 200 | L72: =+E72-SUM(F72:K72) -> 0
A73: 13 | B73: 45722 | C73: 45717 | D73: Nilkanth Stationery | E73: 306 | F73: 306 | L73: =+E73-SUM(F73:K73) -> 0
A74: 10 | B74: 45726 | C74: 45717 | D74: Nilkanth Stationery | E74: 24 | F74: 24 | L74: =+E74-SUM(F74:K74) -> 0
A75: 11 | B75: 45726 | C75: 45717 | D75: Nilkanth Stationery | E75: 40 | F75: 40 | L75: =+E75-SUM(F75:K75) -> 0
A76: 9 | B76: 45727 | C76: 45717 | D76: Nilkanth Stationery | E76: 63 | F76: 63 | L76: =+E76-SUM(F76:K76) -> 0
A77: 6 | B77: 45728 | C77: 45717 | D77: Nilkanth Stationery | E77: 30 | F77: 30 | L77: =+E77-SUM(F77:K77) -> 0
A78: 7 | B78: 45728 | C78: 45717 | D78: Mahavir Collection | E78: 100 | F78: 100 | L78: =+E78-SUM(F78:K78) -> 0
A79: 8 | B79: 45728 | C79: 45717 | D79: Nilkanth Stationery | E79: 13 | F79: 13 | L79: =+E79-SUM(F79:K79) -> 0
... A84: 2 | B84: 45741 | C84: 45717 | D84: Nilkanth Stationery | E84: 12 | F84: 12 | L84: =+E84-SUM(F84:K84) -> 0
A85: 86 | B85: 45746 | C85: 45717 | D85: Toran during Gudhi Padwa | E85: 100 | J85: 100 | L85: =+E85-SUM(F85:K85) -> 0
A86: 40 | B86: 45769 | C86: 45717 | D86: Nilkanth Stationery | E86: 39 | F86: 39 | L86: =+E86-SUM(F86:K86) -> 0
E87: =SUM(E3:E86) -> 14469 | F87: =SUM(F3:F86) -> 5053 | G87: =SUM(G3:G86) -> 2390 | H87: =SUM(H3:H86) -> 1946 | I87: =SUM(I3:I86) -> 4100 | J87: =SUM(J3:J86) -> 300 | K87: =SUM(K3:K86) -> 680 | L87: =SUM(L3:L86) -> 0

Sheet Sheet1
B2: Row Labels | C2: Sum of Total | D2: Sum of Printing & Stn | E2: Sum of Miscellaneous Exp | F2: Sum of Diwali Bonus | G2: Sum of Repairs & Maint | H2: Sum of Function & Festival | I2: Sum of Conveyance
B3: Feb | C3: 595 | D3: 285 | E3: 310
B4: Mar | C4: 1230 | D4: 1130 | H4: 100
B5: Apr | C5: 423 | D5: 273 | I5: 150
B6: May | C6: 285 | D6: 80 | E6: 125 | I6: 80
B7: Jun | C7: 1231 | D7: 796 | E7: 100 | G7: 210 | I7: 125
B8: Jul | C8: 1154 | D8: 629 | G8: 350 | I8: 175
B9: Aug | C9: 898 | D9: 238 | E9: 160 | G9: 500
B10: Sep | C10: 1417 | D10: 1067 | E10: 200 | G10: 150
B11: Oct | C11: 6045 | D11: 389 | E11: 1320 | F11: 4100 | G11: 36 | H11: 200
B12: Nov | C12: 261 | D12: 86 | E12: 175
B13: Dec | C13: 930 | D13: 80 | G13: 700 | I13: 150
B14: Grand Total | C14: 14469 | D14: 5053 | E14: 2390 | F14: 4100 | G14: 1946 | H14: 300 | I14: 680
B18: Month | C18: Sum of Total | D18: Printing & Stn | E18: Miscellaneous Exp | F18: Diwali Bonus | G18: Repairs & Maint | H18: Function & Festival | I18: Conveyance
B19: 45383 | C19: 423 | D19: 273 | I19: 150
B20: 45413 | C20: 285 | D20: 80 | E20: 125 | I20: 80
B21: 45444 | C21: 1231 | D21: 796 | E21: 100 | G21: 210 | I21: 125
B22: 45474 | C22: 1154 | D22: 629 | G22: 350 | I22: 175
B23: 45505 | C23: 898 | D23: 238 | E23: 160 | G23: 500
B24: 45536 | C24: 1417 | D24: 1067 | E24: 200 | G24: 150
B25: 45566 | C25: 6045 | D25: 389 | E25: 1320 | F25: 4100 | G25: 36 | H25: 200
B26: 45597 | C26: 261 | D26: 86 | E26: 175
B27: 45627 | C27: 930 | D27: 80 | G27: 700 | I27: 150
B28: 45689 | C28: 595 | D28: 285 | E28: 310
B29: 45717 | C29: 1230 | D29: 1130 | H29: 100
B30: Grand Total | C30: =SUM(C19:C29) -> 14469 | D30: =SUM(D19:D29) -> 5053 | E30: =SUM(E19:E29) -> 2390 | F30: =SUM(F19:F29) -> 4100 | G30: =SUM(G19:G29) -> 1946 | H30: =SUM(H19:H29) -> 300 | I30: =SUM(I19:I29) -> 680
B35: Lift Maintenance | C35: 35467
B37: 45566 | C37: 45747 | D37: =31+30+31+31+28+31 -> 182 | E37: =ROUND((C35/365)*D37,0) -> 17685
B38: 45748 | C38: 45930 | D38: =30+31+30+31+31+30 -> 183 | E38: =+C35-E37 -> 17782
B41: CCTV | C41: 3500
B43: 45658 | C43: 45747 | D43: =31+28+31 -> 90 | E43: =ROUND((C41/365)*D43,0) -> 863
B44: 45748 | C44: 46022 | D44: =365-D43 -> 275 | E44: =+C41-E43 -> 2637
B47: Insurance | C47: 14596
B49: 45636 | C49: 45747 | D49: =31+28+31+21 -> 111 | E49: =ROUND((C47/365)*D49,0) -> 4439
B50: 45748 | C50: 46000 | D50: =365-D49 -> 254 | E50: =+C47-E49 -> 10157
B52: Pest-Control | C52: 11000
B54: 45658 | C54: 45747 | D54: =31+28+31 -> 90 | E54: =ROUND((C52/365)*D54,0) -> 2712
B55: 45748 | C55: 46022 | D55: =365-D54 -> 275 | E55: =+C52-E54 -> 8288
