Workbook
Name _GoBack: 'Form-1'!$C$58
Name _xlfn_SINGLE: none

Sheet TIT
A2: Name | D2: PRATHAMESH HARMONY "B" WING CO-OPERATIVE HOUSING SOCIETY LTD. | M2: =PROPER(D2) -> Prathamesh Harmony "B" Wing Co-Operative Housing Society Ltd.
A3: Registration No. | D3: MUM/WP/HSG/TC/15332/2012-13
A4: Date of Registration | D4: 2012-2013
A5: Area of operation | D5: As Per Bye-Law
A6: Address | D6: CTS.No. 227,228 & 216, Gautam Buddha Marg, Orlem, Malad - West, Mumbai - 400 064 | M6: Plot No.7&8,Sunder Lane, Orlem, Malad West, Mumbai 400 064.
A7: Accounting Year | B7: from | D7: 1st April, 2025
B8: to | D8: 31st March, 2026
A9: Auditor | B9: Name | D9: Shri. Bharat C. Boridkar | F9: Govt. Certified Panel Auditor
A10: Panel No. | D10: Mumbai-4/C1/1011404
B11: Address | D11: Boridkar House, Pandurang Bhoir Road, Dahisar - West, Mumbai, Mumbai - 400 068
A12: DDR Order Generated
A13: Place & Date of Report | D13: 46277
A14: Sr.No. of the audit memo
A15: Date of commencment | D15: 46266
A16: Date of completion | D16: 46276
A17: Audit memo submitted. | D17: 46277
A18: Annual General Meeting | D18: 45928 | F18: Members Present : ____
A19: Special General Meeting | D19: Nil | N19: 45568 | O19: Minutes not written
A20: M C Meetings | D20: 12
A21: Rectification of Reports: | D21: Submitted
A22: Date of submission
A23: Audit Fees | B23: Amt | D23: 2500
B24: Period | D24: 01/04/2024 to 31/03/2025
B25: Paid on
A26: Secretary | B26: Name | F26: Hon-Secretary
A27: Pay drawn: | D27: Nil
A28: Cash verification | B28: Amt
B29: Date
B30: Name
B31: Designation | D31: Treasurer
B35: AGM

Sheet FirstPage
A3: STATUTORY AUDIT REPORT
A14: =+TIT!D2 -> PRATHAMESH HARMONY "B" WING CO-OPERATIVE HOUSING SOCIETY LTD.
A16: =+TIT!D3 -> MUM/WP/HSG/TC/15332/2012-13
A17: =+TIT!D6 -> CTS.No. 227,228 & 216, Gautam Buddha Marg, Orlem, Malad - West, Mumbai - 400 064
A20: STATEMENT OF AUDIT REPORTS & ACCOUNTS STATEMENTS FOR THE YEAR ENDED 31ST MARCH,2026
A33: ===============================================================================
A34: =+TIT!D9 -> Shri. Bharat C. Boridkar
A35: Govt. Certified Panel Auditor
A36: =+TIT!D11 -> Boridkar House, Pandurang Bhoir Road, Dahisar - West, Mumbai, Mumbai - 400 068
A38: ===============================================================================

Sheet Sheet1
B2: Shri. Bharat C. Boridkar
B3: Govt. Certified Panel Auditor | Q3: The Dy.Registrar, Co-Operative Society, R Ward, 2nd floor, C wing, Municipal Godown Bldg, Nr St Lwarence School, 90 feet Road, Sanskruiti Complex,, Kandivali East,, Mumbai- 400101
B4: Boridkar House, Pandurang Bhoir Road, Dahisar - West, Mumbai, Mumbai - 400 068, )9769556665
P6: Date : 27/03/2019 18:24:30
B7: To,
B8: The Chairman, Members
B9: =+TIT!D2 -> PRATHAMESH HARMONY "B" WING CO-OPERATIVE HOUSING SOCIETY LTD. | P9: Name : | Q9: =+TIT!D2 -> PRATHAMESH HARMONY "B" WING CO-OPERATIVE HOUSING SOCIETY LTD.
B10: =+TIT!D6 -> CTS.No. 227,228 & 216, Gautam Buddha Marg, Orlem, Malad - West, Mumbai - 400 064 | P10: Reg.No | Q10: =+TIT!D3 -> MUM/WP/HSG/TC/15332/2012-13
P11: DDR Order | Q11: =+TIT!D12 -> 0
B13: Sub :-Statutory Audit of your Society for the Financial Year ending on 31st March 2026 | Q13: NINAAD CO-OPERATIVE HOUSING SOCIETY LTD
B15: Enclosed please find 3 [Three only] sets of duly audited, signed and sealed comprising Audit Report in Form-N2, Form -1 along with Sch 1 to 6, Form - 7, General Remarks, Balance Sheet, Income and Expenditure Account along with Schedules forming integral part of the same, Audit Report [Executive Summary] for the Financial Year ended on 31-Mar-2026 for record of the Society. | Q15: H West Ward,, Above Bhandari Co-op. Bank Ltd., Bhavan Hetkari Mahajan Wadi, Ranade Road, Near P. L. Kale Guruji Marg, Dadar - West, Mumbai - 400 028
B16: It is advised that one set to be submitted to, The Dy.Registrar, Co-Operative Society, Ward P , 2nd floor, C wing, Municipal Godown Bldg, Nr St Lwarence School, 90 feet Road, Sanskruiti Complex,, Kandivali East,, Mumbai- 400101 under the Societies covering letter at your earliest. | Q16: It is advised that one set to be submitted to the Deputy Registrar of Co operative Societies, Ward P, 2nd floor, C wing, Municipal Godown Bldg, Nr St Lwarence School, 90 feet Road, Sanskruiti Complex,, Kandivali East,, Mumbai- 400101 under the Societies covering letter at your earliest.
B17: You are requested to upload mandatory returns as prescribed u/s 79 of the MCS Act i.e. 1] Annual Report of Activities, 2] Abridged Audit Report, 3] Balance Sheet, 4] Income and Expenditure Account, 5] Plan for Surplus Distribution, 6] List of Amendment to Bye-Laws, if any, 7] Date of holding AGBM and Election and 8] Name of Auditor for year ended 31-03-2026 and Return Consent on "www.mahasahakar.maharashtra.gov.in" within the time prescribed. | Q17: The Office of the Deputy Registrar Co-operative Societies,K–West, Ground Floor, Room No. 69, MHADA Bldg.,Bandra (E), Mumbai – 400 051
B18: I am also enclosing herewith the invoice for audit fees, with a request to kindly arrange payment at the earliest.
B19: Please Note that the Audit rectification report in Form O duly approved by the managing committee to be submitted to the Registering Authorities within the time permitted i.e. 3 months from the date of audit report under section 82 of the MCS Act. Please make sure that authenticated copy of the same along with soft copy to be provided to me for my comments thereon and uploading thereafter on "www.mahasahakar.maharashtra.gov.in".
B20: In any case, any further information is required, feel free to contact me at your convenience.
B21: Inconvenience, if any, is regretted.
B22: Thanks a lot.
B23: Yours faithfully,
B27: Shri. Bharat C. Boridkar
B28: Govt. Certified Panel Auditor
B29: Co-op Soc Empanelment Number : A-2 / 13395
B30: ="Co-op Soc Empanelment Number : Mumbai-4/C1/1011404" -> Co-op Soc Empanelment Number : Mumbai-4/C1/1011404
B31: =+TIT!D13 -> 46277
B33: Encl: | C33: 1] 3 [three only] sets as above

Sheet AR
B2: Shri. Bharat C. Boridkar
B3: Govt. Certified Panel Auditor | Q3: The Dy.Registrar, Co-Operative Society, R Ward, 2nd floor, C wing, Municipal Godown Bldg, Nr St Lwarence School, 90 feet Road, Sanskruiti Complex,, Kandivali East,, Mumbai- 400101
B4: Boridkar House, Pandurang Bhoir Road, Dahisar - West, Mumbai, Mumbai - 400 068, )9769556665
B7: INDEPENDENT AUDITOR'S REPORT
B8: [As prescribed under section 81 of the Maharashtra Co-operative Societies Act, 1960 and rule 69 (3) of the Maharashtra Co-op Societies Rules.]
B10: To,
B11: The Chairman, Members | O11: Chairman
B12: =+TIT!D2 -> PRATHAMESH HARMONY "B" WING CO-OPERATIVE HOUSING SOCIETY LTD.
B13: =+TIT!D6 -> CTS.No. 227,228 & 216, Gautam Buddha Marg, Orlem, Malad - West, Mumbai - 400 064
B16: Sub :-Statutory audit of your society for Financial Year ending on 31-Mar-2026
C18: Report on the Financial Statements as a Statutory Auditor
B20: 1. | C20: We have audited the accompanying financial statements of PRATHAMESH HARMONY "B" WING CO-OPERATIVE HOUSING SOCIETY LTD., which comprise the Balance Sheet as at 31st MARCH, 2026 and the Statement of Income and Expenditure for the year ended on that date, and a summary of significant accounting policies and other explanatory information incorporated in these financial statements of the Society audited by us for the period 1st April 2025 to 31st March 2026. | O20: Income and Expenditure | P20: =+TIT!D2 -> PRATHAMESH HARMONY "B" WING CO-OPERATIVE HOUSING SOCIETY LTD. | U20: 1. We have audited the accompanying financial statements of-----------------------------------, Income and Expenditure Account and Receipt and payment for the year then ended, and a summary of significant accounting policies and other explanatory information incorporated in these financial statements of the society audited by us for the period 1st April 2019 to 31st March 2020.
C22: Management’s Responsibility for the Financial Statements | P22: PRATHAMESH HARMONY "B" CO-OPERATIVE HOUSING SOCIETY LTD.
B23: 2. | C23: Management is responsible for the preparation of these financial statements that give a true and fair view of the financial position and financial performance of the Society in accordance with the accounting principles generally accepted in India, the Maharashtra Co-operative Societies Act, 1960 and Rules there under. This responsibility includes maintenance of adequate accounting records in accordance provisions of the Act for safeguarding the assets of the society and for preventing and detecting frauds and other irregularities; selection and application of appropriate accounting policies; making judgments and estimates that are reasonable and prudent; and design, implementation and maintenance of adequate internal financial controls, that were operating effectively for ensuring the accuracy and completeness of the accounting records, relevant to the preparation and presentation of the financial statements that give a true and fair view and are free from material misstatement, whether due to fraud or error.
C25: Auditor’s Responsibility
B26: 3. | C26: Our responsibility is to express an opinion on these financial statements based on our audit. We have taken into account the provisions of the Act, the accounting and auditing standards and matters which are required to be included in the audit report under the provisions of the Act and Rules made there under. We have conducted our audit in accordance with the applicable standards issued by the Institute of Chartered Accountants of India and under the Maharashtra Cooperative Societies (MCS) Act, 1960. Those standards require that we comply with ethical requirements and plan and perform the audit to obtain reasonable assurance about whether the financial statements are free from material misstatement.
B28: 4. | C28: An audit involves performing procedures to obtain audit evidence about the amounts and disclosures on the financial statements. The procedures selected depend on the auditor’s judgment, including the assessment of the risks of material misstatement of the financial statements, whether due to fraud or error. In making those risk assessments, the auditor considers internal control relevant to the societies preparation and fair presentation of the financial statements in order to design audit procedures that are appropriate in the circumstances, but not for the purpose of expressing an opinion of the effectiveness of the societies internal control. An audit also includes evaluating the appropriateness of accounting policies used and the reasonableness of the accounting estimates made by management, as well as evaluating the overall presentation of the financial statements.
B30: 5. | C30: We believe that the audit evidence we have obtained is sufficient and appropriate to provide a basis for our audit opinion on the financial statements.
C35: Opinion
B36: 6. | C36: In our opinion and to the best of our information and according to the explanations given to us, the said financial statements together with the notes thereon give the information required as per the Maharashtra Cooperative Societies Act , 1960 and the Maharashtra Co-Operative Societies Rules 1961, and any other applicable Acts, and or circulars issued by the Registrar, in the manner so required and give a true and fair view in conformity with the accounting principles generally accepted in India:
C38: i. | D38: In the case of the Balance Sheet, of the state of affairs of the Society as at 31st MARCH, 2026
C40: ii. | D40: In the case of the Statement of Income and Expenditure, of the Excess of Expenditure over Income of the Society for the year ended on that date; and | O40: Surplus / Deficit see F1 I132
C43: Report on Other Legal and Regulatory Matters
C44: As required by the Maharashtra Co-operative Societies Act, 1960 and Rules made there under and in terms of circular No 976/2014 Dated 28/10/2014 we give in part A, B & C a statement on the matter specified in the said parts to the extent applicable.
B45: 7. | C45: The Balance sheet, Income and Expenditure Account have been drawn up in accordance with the provisions of the Maharashtra State Co-operative Act, 1960.
B47: 8. | C47: We report that :
C48: (a) | D48: We have obtained all the information and explanations which to the best of our knowledge and belief were necessary for the purpose of our audit and have found them to be satisfactory.
C50: (b) | D50: The transactions of the Society, which have come to my notice, have been within the powers of the Society.
B52: 9. | C52: In our opinion, the Balance sheet, Income and Expenditure account and Receipt and Payment Account comply with applicable Accounting Standards.
B54: 10. | C54: We further report that :
C55: i. | D55: The Balance Sheet and Income and Expenditure Account dealt with by this report, are in agreement with the books of account and the returns and give true & fair view of statements of affairs. | O55: N
C57: ii. | D57: ii. in our opinion, proper books of account as required by law have been kept by the Society so far as appears from our examination of these books
B59: Audit Classification:- | O59: B | P59: Audit classification:-
C60: The Society has been awarded "B" Audit Classification for the Co-op. financial year 2025-2026. | P60: The Society has been awarded "C" Audit Classification for the Co-op. financial year 2019-2020.
C67: Shri. Bharat C. Boridkar
C68: Govt. Certified Panel Auditor
C69: Co-op Soc Empanelment Number : A-2 / 13395
C70: ="Co-op Soc Empanelment Number : Mumbai-4/C1/1011404" -> Co-op Soc Empanelment Number : Mumbai-4/C1/1011404
C71: =+TIT!D13 -> 46277

Sheet Form-1
A1: FORM NO. 1
A2: FOR ALL TYPE OF CO-OPERATIVE SOCIETIES
A3: PART – A
A4: I | B4: SR. NO. | C4: SOCIETY INFORMATION | D4: PARTICULARS TO BE FILED BY THE AUDITOR
A5: 1 | B5: 2 | C5: 3 | D5: 4
A6: I | B6: 1 | C6: Name of the Society | D6: =+TIT!D2 -> PRATHAMESH HARMONY "B" WING CO-OPERATIVE HOUSING SOCIETY LTD.
B7: 2 | C7: a) Society Registration Number and Date | D7: =+TIT!D3 -> MUM/WP/HSG/TC/15332/2012-13
C8: Designation of Registering Officer
C9: b) Classification and Sub Classification as per Buy-laws | D9: Co-Operative Housing Society
B10: 3 | C10: Area of Operation of the Society | D10: P Ward, Malad - West
B11: 4 | C11: Types of Society as per Rules 1969 | D11: Co-Partnership
B12: 5 | C12: Number of Branches of Society | D12: Not Applicable
B13: 6 | C13: Full address of Society with Pin Code Number | D13: =+TIT!D6 -> CTS.No. 227,228 & 216, Gautam Buddha Marg, Orlem, Malad - West, Mumbai - 400 064
B14: 7 | C14: Current Audit Period | D14: Date 01.04.2025 From
D15: Date 31.03.2026 To
B16: 8 | C16: Class of previous Audits | D16: F. Year Class
D17: 1. 2024-2025 : B
D18: 2. 2023-2024 : B
D19: 3. 2022-2023 : B
B21: 9 | C21: Class of current Audit, if necessary enclosed classification of marks chart. | D21: Class - B
A23: II | B23: AUDITOR INFORMATION
B24: 1 | C24: Name of the Auditor / Firm Name | D24: =+TIT!D9 -> Shri. Bharat C. Boridkar
B25: 2 | C25: Registered Address | D25: =+TIT!D11 -> Boridkar House, Pandurang Bhoir Road, Dahisar - West, Mumbai, Mumbai - 400 068
B26: 3 | C26: Firm Registration Number | D26: NA
B27: 4 | C27: Individual Auditor’s Membership Number | D27: NA
B28: 5 | C28: Panel Number | D28: =+TIT!D10 -> Mumbai-4/C1/1011404
B29: 6 | C29: Partnership: Partners Name, Address and Membership Number. | D29: NA
B30: 7 | C30: Panel Number | D30: NA
B31: 8 | C31: Class of Auditor as per Panel | D31: =+TIT!F9 -> Govt. Certified Panel Auditor
B32: 9 | C32: Society AGBM date and Resolution Number | D32: ="Date : "&TEXT(TIT!D18,"dd-mm-yyyy") -> Date : 28-09-2025
B33: 10 | C33: Date of Auditor’s Appointment letter | D33: Date : 16-08-2026
B34: 11 | C34: Date of Auditor’s Acceptance letter | D34: Date : 18-08-2026
B35: 12 | C35: Date of Auditor’s Acceptance received by the Society | D35: Date : 20-08-2026
B36: 13 | C36: Date of Audit Commenced | D36: ="Date : "&TEXT(TIT!D15,"dd-mm-yyyy") -> Date : 01-09-2026
B37: 14 | C37: Date of AuditCompleted | D37: ="Date : "&TEXT(TIT!D16,"dd-mm-yyyy") -> Date : 11-09-2026
B38: 15 | C38: Date of Managing Committee in which discussions on Audit Report | D38: Date : 11-09-2026
B39: 16 | C39: Date of Audit Report Submitted to the Society. | D39: ="Date : "&TEXT(TIT!D13,"dd-mm-yyyy") -> Date : 12-09-2026
C40: .
B41: 17 | C41: Date of Special Report Submitted (if any) | D41: Date : NA
B43: 18 | C43: Government Report Submitted (if any) | D43: Date : NA
B45: 19 | C45: Audit Fees and Other Charges | D45: Rs. 2500/-
C47: a) Audit Fees | D47: Rs. 2500/-
C48: b) Other Expenses as per Guidelines | D48: -
C49: c) Other Expenses out of Guidelines | D49: Nil
C50: d) LFAR Fees of Bank | D50: Nil
B52: PART – B
A54: II | B54: WORKING OF THE SOCIETY
A55: 1 | B55: MEMBERSHIP
B56: 1 | C56: For Admission of member entrance fees, application, required minimum share amount and resolution for membership of BOD / MC as the case may be complied with. | D56: Yes
B57: 2 | C57: State the No. of Members
C58: a) Shareholder Members | D58: 18
C59: b) Nominal Members | D59: 0
C60: Total Members | D60: =+D58+D59 -> 18
C61: Joint or Associates Members
B62: 3 | C62: Classification of Members as per Maharashtra Co-operative Act – 1960. | D62: Not Applicable and hence no comments are necessary in Audit Report.
C63: a) Active Member
C64: b) Non- Active Member
B65: 4 | C65: Whether procedure for acceptance of resignation of members as per byelaws of the society is duly complied with. If not, give the remarks in audit report. | D65: Yes
B66: 5 | C66: If any members is expelled during the period of audit, whether due procedure as per Section 35 and Rule 28 & 29 is followed or not. If not, comment in audit report | D66: NA
A68: 2 | B68: SHARE CAPITAL
B69: 1 | C69: Whether the limit of authorised share capital is adhered to or not? If not suggest the society to amend the byelaws accordingly. Comment report in audit the report | D69: Yes
B70: 2 | C70: If society has called the money for partially paid shares and the members have paid the said amount, if not, whether any action has been taken by the society as per bye-laws. | D70: Yes
B71: 3 | C71: If society has refunded the share capital, whether amount is refunded as per Rule 23 by valuing the shares as per last audited balance sheet. Whether any excess payment than the valuation has been recovered by the society, if not, comment in the audit report. | D71: No
A74: 3 | B74: MANAGEMENT
B75: 3.1 | C75: MEETINGS
B76: 1 | C76: Date of Annual General Body Meeting | D76: =+TIT!D18 -> 45928
B77: 2 | C77: Date of Special General Body Meeting | D77: =+TIT!D19 -> Nil
B78: 3 | C78: Numbers of Meetings :-
C79: i) Managing Committee Meeting | D79: =+TIT!D20 -> 12
C80: ii) Working Committee Meeting
C81: iii) Purchasing Committee Meeting
C82: iv) Loan Committee Meeting
C83: v) Investments Committee Meeting
C84: vi) Audit Committee Meeting
C85: vii) Other Committee if any
B86: 4 | C86: Whether meetings are held as per the proper quorum, if not comment in the audit Report. | D86: As per Audit Remarks
B88: 3.2 | C88: MANAGING COMMITTEE
B89: 1 | C89: Date of Managing Committee Election held | D89: Details Not available for verification
B90: 2 | C90: Period of Managing Committee | D90: Date : From
D91: Date : To
C92: Whether the management has informed to the Co-operative Election Authority about expiry of term of management committee, prior to 6 months. | D92: Details Not available for verification
B93: 3 | C93: If the period of the committee is over and still it is working, whether the committee has informed the same to the State Co-operative Election Authority for further process or not? | D93: =+D92 -> Details Not available for verification
B94: 4 | C94: State the names of the members of Managing Committee during the period covered under audit. | D94: Chairman : Mr. Aicod Raja
D95: Secretary : Mrs. Nisha Fernandes
D96: Member : Ms. Shilpa Panchal
D97: Member : Mr. Wilson D'silva
B98: 5 | C98: Whether the members of the Board have complied with the terms and conditions to be continued as member of board. | D98: Yes
B100: 3.3 | C100: DECISIONS OF THE MANAGING COMMITTEE
B102: 1 | C102: Read the minutes of committees and offer comments regarding the decisions taken by the Managing Committee affecting financial irregularities and impact of it on the financial status of the society. | D102: Yes
B103: 2 | C103: Any losses / damages have been occurred from such decisions, whether special report is made or not. If yes, state the date of special report. | D103: No
B104: 3 | C104: Whether any decisions of BoD are in contravention of provisions of Act, Rules and Byelaws. If yes, comment in audit report. | D104: No
B106: 3.4 | C106: SUB COMMITTEES
B108: 1 | C108: Whether the Sub Committees are delegated powers under bye-laws or by resolution of the Managing Committee. | D108: Not Applicable and hence no comments are necessary in Audit Report.
B109: 2 | C109: Powers delegated are according to the Act, Rules, Byelaws and directives issued by CRCS, RBI, NABARD or any competent authority under any Law. | D109: Not Applicable and hence no comments are necessary in Audit Report.
B110: 3 | C110: Read the minutes of sub committees and state whether the sub committees are working within the powers, duties assigned to them, if not comment in General Remarks. | D110: Not Applicable and hence no comments are necessary in Audit Report.
B114: 3.5 | C114: CHIEF EXECUTIVE OFFICER
B116: 1 | C116: Name of the Chief Executive Officer. | D116: Not Applicable and hence no comments are necessary in Audit Report.
B117: 2 | C117: The Designation assigned him . | D117: Not Applicable and hence no comments are necessary in Audit Report.
B118: 3 | C118: Educational Qualification (Section 74). | D118: Not Applicable and hence no comments are necessary in Audit Report.
B119: 4 | C119: Whether he fulfils the criteria laid down by the competent authority for the post he has held. | D119: Not Applicable and hence no comments are necessary in Audit Report.
...

Sheet Form-7
A1: FORM NO. 7
A2: FOR CO-OP. HOUSING SOCIETIES
A3: PART C
A4: 1 | B4: 2 | C4: SOCIETY INFORMATION | D4: Particulars to be filed by the Auditor
C6: 3 | D6: 4
A7: I | B7: 1 | C7: Name of the Society | D7: =+TIT!D2 -> PRATHAMESH HARMONY "B" WING CO-OPERATIVE HOUSING SOCIETY LTD.
B8: 2 | C8: Sub Classification of the Society | D8: Tenant Co-Partnership
B9: A | C9: Tenant Ownership Housing Society | D9: No
B10: B | C10: Tenant Co-partnership Housing Society | D10: Yes
B11: C | C11: Other Housing Society | D11: No
A13: II | B13: WORKING OF THE SOCIETY
B14: Financial Management
A16: 1 | B16: Government / Financial Institute – Assistance, Loan etc.
B17: 1.1 | C17: Whether the society has obtained Government Assistance for the Construction of the houses / Flats / Bungalows etc. | D17: No
B18: 1.3 | C18: State the financial assistance not utilised and remained balance with the society, reasons of non-utilisation and action taken by the Society for its utilisation. | D18: No
B19: 1.4 | C19: If any financial assistance is mis-utilised for the purpose other than its sanction, state the amount, purpose of utilisation and persons responsible for mis-utilisation and modus operandious of mis-utilisation, persons benefited by such amount of financial assistance. | D19: No
B20: A | C20: Loan from government / government undertaking
B21: 1 | C21: Sanctioned amount and date of sanction | D21: N.A.
B22: 2 | C22: Amount actually received upto audit period | D22: N.A.
B23: 3 | C23: Amount utilised upto audit period | D23: N.A.
B24: 4 | C24: Amount remained with Society for utilisation | D24: N.A.
B25: 5 | C25: Date of submission of utilisation certificates and amounts thereof | D25: N.A.
C26: i) | D26: N.A.
C27: ii) | D27: N.A.
C28: iii) | D28: N.A.
B29: B | C29: Other financial assistance from government / government undertakings (Specify)....
B30: 1 | C30: Sanctioned amount and date of sanction | D30: N.A.
B31: 2 | C31: Amount actually received upto audit period | D31: N.A.
B32: 3 | C32: Amount utilised upto audit period | D32: N.A.
B33: 4 | C33: Amount remained with Society for utilisation | D33: N.A.
B34: 5 | C34: Date of submission of utilisation certificates and amounts thereof | D34: N.A.
C35: i) | D35: N.A.
C36: ii) | D36: N.A.
C37: iii) | D37: N.A.
A41: 2 | B41: Finance from other financial institutions (individual loans taken by members which is not accounted in the Society’s books, no comments are required by auditor for the following points)
B42: a | C42: Sanctioned Amount | D42: N.A.
B43: b | C43: Amount actually received | D43: N.A.
B44: c | C44: Amount utilised | D44: N.A.
B45: d | C45: Amount remained with Society for utilisation | D45: N.A.
B46: e | C46: State the financial assistance not utilised and remained balance with the Society, state the reasons of non-utilisation and action taken by the Society for its utilisation | D46: N.A.
B48: f | C48: If any financial assistance is mis-utilised for the purpose other than its sanction, state the amount, purpose of utilisation and persons responsible for mis-utilisation and modus operandious of mis-utilisation persons benefited by such amount of financial assistance. | D48: N.A.
B50: 3 | C50: Whether the members of the society have availed loan from financial institutions in the personal capacity? Necessary permission from the society has been taken and the charge on the assets of the society has been created state the No. Of members and amount of loan and charge on the assets? Verify the register maintained for the same from the information submitted by the members and comments on them in the audit report. | D50: N.A.
B51: 4 | C51: Whether the loans taken by the Society or by the members (in respect of government employees from the government / government undertakings) are repaid in time and verify the over dues and comment thereupon. | D51: N.A.
B52: 5 | C52: Whether the necessary documents i.e. NOC of the Society, mortgage deed, etc. have been executed by the Society or members with the financial Institutions or the Government as the case may be. Verify them and comment in the audit report. | D52: N.A.
B53: 6 | C53: Whether the term and conditions laid down by the Financial Institutions / Government have been followed by the Society / members or not? If not, comment in the audit report. | D53: N.A.
B54: 7 | C54: Whether the Society has maintained loan register with details of sanction, disbursement, repayment, balance and NOC after full repayment. | D54: N.A.
B55: 8 | C55: Whether the Society has obtained certificate regarding full payment of loan from concerned government department for release of mortgage? | D55: N.A.
A57: 3 | B57: Land and Construction of the buildings
B58: 3.1 | C58: Lands
C59: a) Whether the land is owned by the Society ,state S. No. , Area, City Servey No., date of purchase, amount of purchase and amount spent on development of land. State the registration number of purchase deed and date. | D59: =+TIT!D6 -> CTS.No. 227,228 & 216, Gautam Buddha Marg, Orlem, Malad - West, Mumbai - 400 064 | F59: Required CTS No.
C60: b) If the land is taken on lease, state the lesson, lease period, lease rent and amount of lease rent paid so for? Verify agreement for Lease comment on registration, terms and conditions of lease. Whether lease register is maintained or not? Whether tri-party agreements is executed for land originally lease by MHADA , HUDCO, CIDCO or any other such authority and such leased to Society? | D60: NO
C63: c) If the land belongs to owner and given to development to the developer, state the owner, developer agreement of development, its terms and conditions and whether sale deed are made with member by the developer and owner or as per power of attorney, the auditor should verify the documents and comments in the audit report regarding title of land and building. (whether the Society has get its conveyance of land and building) | D63: NO
C64: d) If the Society has purchased land, necessary permission for non agricultural land has been obtained from the competent authority or not? If not comment in the audit report. | D64: NO
B66: 3.2 | C66: Constructions
B67: 1 | C67: (a) Whether the construction has commenced or not and necessary permissions from local authority have been taken or not? | D67: N.A.
C68: (b) State total number of flats / houses / bunglows / commercial units out of which are completed, under construction and constructions yet to be commenced. | D68: Residential 18 Flats
C69: (c) Whether flats / houses / bunglows / commercial units are allotted to the members? Whether allotment register is maintained or not? Whether any member is remained unalloted? What action has been taken against such members as per bye-laws? | D69: YES
B71: 2 | C71: Whether building has been constructed on contract basis? Whether the terms and conditions of the contract are followed? Verify and comment in the audit report. | D71: N.A.
B72: 3 | C72: Whether these contracts are sanctioned by competent authority (AGBM). | D72: N.A.
B73: 4 | C73: Whether tender have been called by publishing in local newspaper with rates? If the tender is allotted to the contractor other than lowest bid. Reasons thereof are given in the proceeding of sanction of tender. Verify and comment in audit report. | D73: N.A.
B74: 5 | C74: Whether the amount paid to the contractor on the basis of progress report by architect or not? Whether the running bills and final bill are taken before payment to the contractor. | D74: N.A.
B75: 6 | C75: On what terms and conditions, an architect was appointed? Whether the appointment is permitted by AGBM? | D75: N.A.
B76: 7 | C76: Whether there is any breach of terms and conditions by contractors or architect? Give remarks and state financial impact on the Society. | D76: N.A.
B77: 8 | C77: Whether prior to construction, the Society has obtained certificates regarding drainage, water supply, roads and sanction to final layout. | D77: N.A.
B78: 9 | C78: Whether Society has obtained completion / occupancy certificate from the local authorities / sanctioning authority? | D78: N.A.
B79: 10 | C79: Whether any changes have been made to the sectional plans, approvals are obtained from the competent authority? If not, comment in audit report. | D79: N.A.
B80: 11 | C80: Whether buildings and constructions are insured or not? | D80: No
A82: 4 | B82: Conveyance Deed
B83: 4.1 | C83: Whether constructions are made by Builders / developers and sale agreement are executed with members? | D83: N.A.
B84: 4.2 | C84: Whether the land has been transferred to the Society by the builder / developer or not? | D84: Yes
B87: 4.3 | C87: Whether for transfer of land in the name of Society, Conveyance Deed has been executed by the builders / developers or not? If not, what action has been taken for the Conveyance? | D87: Conveyance Deed Executed
A88: 5 | B88: Redevelopment
B89: 5.1 | C89: Whether the approval for redevelopment of the building as per bye-laws? | D89: Not Applicable
B90: 5.2 | C90: Whether tender have been invited for redevelopment? | D90: =+D89 -> Not Applicable
B91: 5.3 | C91: Whether proposals of redevelopment have been considered by the AGBM with quorum required by bye-laws? | D91: =+D90 -> Not Applicable
B92: 5.4 | C92: Whether the Society has appointed an architect and legal advisor for preparation of redevelopment of plan and scrutiny of tenders received for redevelopment. | D92: =+D91 -> Not Applicable
B93: 5.5 | C93: Whether agreements have been executed between society and architect / legal advisor? | D93: =+D92 -> Not Applicable
B94: 5.6 | C94: Whether comparative study in terms of financial and technical aspects of all proposals has been made? | D94: =+D93 -> Not Applicable
B95: 5.7 | C95: State the criteria’s adopted by the board for approval of proposal out of proposals received | D95: =+D94 -> Not Applicable
B96: 5.8 | C96: Whether approval of AGBM has been obtained for the final proposal? | D96: =+D95 -> Not Applicable
B97: 5.9 | C97: Whether agreement for redevelopment is executed between the Society and Developer? Whether the certified copy of the agreement is available with the Society? Give list of other agreements / documents executed between the Society and the redeveloper. | D97: =+D96 -> Not Applicable
B98: 5.1 | C98: Check-up whether any terms and conditions of redevelopment agreements are prejudicial to the interest of the Society and its members, If yes, state the same. | D98: =+D97 -> Not Applicable
B99: 5.11 | C99: Comment upon progress of reconstruction as per the terms of redevelopment agreement. | D99: =+D98 -> Not Applicable
B100: 5.12 | C100: Whether there is any breach of terms and conditions of the agreement between the redeveloper and Society? If yes, comment upon the same along with its financial impact on Society and members. | D100: =+D99 -> Not Applicable
B101: 5.13 | C101: Whether any member of the Society is related with the redeveloper in any way and if yes, whether the interest has been disclosed by the said member to the AGBM? | D101: =+D100 -> Not Applicable
... B105: 5.17 | C105: Whether any changes have been made to the sanctioned plans, approvals are obtained from the competent authority? If not, comment in audit report. | D105: =+D104 -> Not Applicable
B106: 5.18 | C106: Whether buildings and constructions are insured or not? | D106: No
B109: 5.19 | C109: Whether new members are admitted in process of redevelopment? If yes, whether procedure for admission of membership has been followed or not as per the bye-laws? | D109: N.A.
A110: 6 | B110: Monthly Contribution for Maintenance
B111: 6.1 | C111: Whether the Society has decided contribution for maintenance as per bye-laws and sanction of AGBM has been taken? | D111: YES
B112: 6.2 | C112: Whether the contribution is according to parameters set in the bye-laws and as per directions of the Registrar? | D112: YES
B113: 6.3 | C113: Whether any amount of such contribution is outstanding and overdue as per bye-laws? State the name of the concerned member and amount. | D113: YES
B114: 6.4 | C114: Whether the Society has charged and recovered penal interest on the overdue contribution amount. | D114: YES
A115: 7 | B115: Funds Management
B116: 7.1 | C116: Whether the Society has provided for Sinking Fund, Repairs and Maintenance Fund, Election Fund as per bye-laws? | D116: YES
B117: 7.2 | C117: Whether rules for utilisation of sinking fund and repairs and maintenance fund have been prepared and approved by the AGBM? | D117: No
B118: 7.3 | C118: Whether such funds are utilised during the period of audit, necessary permissions have been taken from the competent authority? | D118: No
B119: 7.4 | C119: Whether surplus funds are invested as per Act ,Rules and bye-laws separately or not? Comment in the Audit Report. | D119: Remarks in the Audit Report
A120: 8 | B120: Transfer of Flats / Houses / Bunglows by members
B121: 8.1 | C121: Whether during the period of audit any transfer of flats / houses / bunglows by members have been taken place? | D121: YES
...

Sheet SCHAR (2)
A1: =+TIT!D2 -> PRATHAMESH HARMONY "B" WING CO-OPERATIVE HOUSING SOCIETY LTD.
A2: =+TIT!D3 -> MUM/WP/HSG/TC/15332/2012-13
A3: =+TIT!D6 -> CTS.No. 227,228 & 216, Gautam Buddha Marg, Orlem, Malad - West, Mumbai - 400 064
A4: Period:- 01.04.2025 To 31.03.2026
A7: Schedules attached to and forming part of the Audit Report dated :- | J7: =+TIT!D13 -> 46277
A8: Statutory Report as required u/s 81 (2)
A10: SCHEDULE - I
C11: Transactions involving infringment of the provisions of the Act, the Rules & the Bye-laws
D12: - Refer to Audit Memo 1 & General Remarks.
A14: SCHEDULE - II
C15: Particulars of sums which ought to have been but have not been brought into account.
D16: - NIL
A18: SCHEDULE - III
C19: Improper & Irregular payments.
D20: See General Remarks
A22: SCHEDULE - III-A
C23: Irregularities in the realisation of money
D24: - NIL
A26: SCHEDULE - IV
C27: List of doubtful & bad debts
D28: - NIL
A30: SCHEDULE - V
C31: List of the movable & immovable properties & other assets considered doubtful of realisation
D32: - NIL
A34: SCHEDULE - VI
C35: Personal Expenditure debited to revenue
D36: - NIL
C44: =+TIT!D9 -> Shri. Bharat C. Boridkar
C45: ="["&TIT!A10&": "&TIT!D10&"]" -> [Panel No.: Mumbai-4/C1/1011404]
C46: Govt. Certified Panel Auditor
C47: =+TIT!D13 -> 46277

Sheet GR
A1: =+TIT!D2 -> PRATHAMESH HARMONY "B" WING CO-OPERATIVE HOUSING SOCIETY LTD.
A2: ="General Remarks and Observations attached to and forming part of the audit report dated "&TEXT(TIT!D13,"dd-mmm-yyyy") -> General Remarks and Observations attached to and forming part of the audit report dated 12-Sep-2026
A4: INTRODUCTION | V4: Department of Cooperation, Marketing and Textile
A5: 1 | B5: Name of the society | F5: :- | G5: =+TIT!D2 -> PRATHAMESH HARMONY "B" WING CO-OPERATIVE HOUSING SOCIETY LTD. | V5: Date : 18/07/2016 19:17:58
V6: Dear BHARAT CHANDRAKANT BORIDKAR,
A7: 2 | B7: Register Address | F7: :- | G7: =+TIT!D6 -> CTS.No. 227,228 & 216, Gautam Buddha Marg, Orlem, Malad - West, Mumbai - 400 064 | V7: Audit Order is generated by following users:
F8: :- | V8: Auditor Name:BHARAT CHANDRAKANT
A9: 3 | B9: Reg. No & date | F9: :- | G9: =+TIT!D3 -> MUM/WP/HSG/TC/15332/2012-13 | V9: BORIDKAR
A10: 4 | B10: Period of audit | F10: :- | G10: 01-Apr-2025 To 31-Mar-2026 | V10: Society Name :JATIN CO OP HSG SOC LTD
A11: 5 | B11: Audit classification | F11: :- | G11: "B" | V11: Auditor Type :Certified Auditor Individual
V12: Society Type :Housing societies having less than
A13: GENERAL REMARKS (PART-A) | V13: 100 members
A14: The following are the major discrepancies found during the audit. | V14: Auditor Empanelment Number :1011404 Society District :Mumbai 4
A15: Sr no | B15: Particulars | E15: Instances / Examples which requires reporting | L15: Auditor’s remarks | V15: Society Taluka:Ward R North
A16: 1 | B16: Fraud | E16: 1) Debiting excess amount than the voucher amount / bill amount. | L16: During the year under audit, I have not found any such instance. | V16: Society Village:Borivali
E17: 2) Withdrawing the amount from bank but not crediting in cash book | L17: During the year under audit, I have not found any such instance. | V17: Regards,
E18: 3) Debiting the bank account without depositing the amount in bank | L18: During the year under audit, I have not found any such instance. | V18: eSahakar
E19: 4) Disbursing loans without sanction / without security / without loan documents / using forge documents | L19: During the year under audit, I have not found any such instance. The society is Housing Society. | V19: Online Audit Management System
E20: 5) Any other transaction with the intention to defraud the society by any person. | L20: On the basis of verification of record made available to me, during the year under audit, I have not found any such instance. | V20: Department of Cooperation, Marketing and Textile
A21: 2 | B21: Misutilisation of funds and properties | E21: 1) purchasing / constructing building without inviting the tenders | L21: During the year under audit, I have not found any such instance.
E22: 2) purchasing the computers / fixed assets without inviting the tenders. | L22: During the year under audit, I have not found any such instance.
E23: 3) selling the movable / immovable properties without inviting bids | L23: During the year under audit, I have not found any such instance.
E24: 4) selling the movable / immovable properties below Reserve Price (Upset price) | L24: During the year under audit, I have not found any such instance.
A25: 3 | B25: Misapplication of funds | E25: 1) Use of sinking fund for day to day maintenance without passing required resolution in General Body. | L25: During the year under audit, I have not found any such instance.
E26: 2) Use of revenue reserve / general reserve for creating Reserve for Bad and Doubtful Debts. | L26: During the year under audit, I have not found any such instance.
A27: 4 | B27: Manipulation of accounts | L27: I have not found any manipulation of accounts during the year under audit.
A28: 5 | B28: Falsification of accounts | L28: I have not found any Falsification of accounts during the year under audit.
A29: 6 | B29: Shortfall in various provisions | L29: There is no material shortfall in recognition of liability for outstanding expenses/provisions | T29: There is no material shortfall in recognition of liability for outstanding expenses/provisions
A32: 7 | B32: Infringement of the M C S Act, 1960, Rules, 1961 and the Bye-Laws of the Society
B33: Srn | C33: Act | D33: Rules | E33: Bye-laws @ | G33: Descriptions
B34: 1 | C34: 70 | D34: 54,55 | E34: 15 | G34: Investment of Funds
B35: 2 | C35: 73b | E35: 114 | G35: Strength, composition and quorum of the managing committee.
B36: 3 | D36: 107 C | E36: 144 | G36: Cash in hand beyond the prescribed limit.
B37: 4 | C37: 81 | D37: 107 D | E37: 145 | G37: Payments made by means other than crossed account payee cheque
B38: 5 | E38: 160 | G38: The society shall insure its building necessarily against risk of fire and earthquake and flood
B39: 6 | E39: 20 | G39: A Sublette / licensee not applied for Nominal Membership of the Society.
B40: 7 | D40: 26 | E40: 32 | G40: Nomination not fully received.
B41: 8 | C41: 82 | D41: 73 | E41: 153 (a) | G41: Audit rectification report in “O” form not placed in managing committee meeting and submission to Registering Authority and auditor for his comments.
A43: Sr no | B43: Particulars | E43: Instances / Examples which requires reporting | L43: Auditor’s remarks
A44: 8 | B44: Personal expenses debited to Income and expenditure account. | L44: During the year under audit, I have not found any such instance.
A45: 9 | B45: Transactions with relatives of members of managing committee, companies, firms in which members of managing committee are interested, which are not at the reasonable rates. | L45: During the year under audit, I have not found any such instance.
A46: 10 | B46: No action against overdue in excess of one year | L46: During the year under audit, I have not found any such instance.
K52: Shri. Bharat C. Boridkar
K53: Govt. Certified Panel Auditor
A54: =+TIT!$D$13 -> 46277 | K54: [Panel No.: Mumbai-4/C1/1011404]
A57: GENERAL REMARKS (PART-B) | T57: =+TIT!D2 -> PRATHAMESH HARMONY "B" WING CO-OPERATIVE HOUSING SOCIETY LTD.
A58: INTRODUCTION
B59: ="I have been appointed as the Statutory auditors of "&TIT!D2&" "&TIT!D6&" by members of the Society in their Annual General Body Meeting Dt. "&TEXT(TIT!D18,"dd-mmm-yyyy")&" and Accordingly I have completed the Audit work. " -> I have been appointed as the Statutory auditors of PRATHAMESH HARMONY "B" WING CO-OPERATIVE HOUSING SOCIETY LTD. CTS.No. 227,228 & 216, Gautam Buddha Marg, Orlem, Malad - West, Mumbai - 400 064 by members of the Society in their Annual General Body Meeting Dt. 28-Sep-2025 and Accordingly I have completed the Audit work.
B60: The audit has been conducted for the period 1st April 2025 to 31st March 2026. This statutory audit is based on the books of accounts, records, financial statements, annexures, and other relevant documents maintained in the computer system, and has been verified accordingly. Both written and oral information provided by the management at the time of the audit has been relied upon during the course of this work. It is assumed that all transactions have been carried out in compliance with the Maharashtra State Co-operative Societies Act, 1960, the Rules of 1961, and the Bye-Laws of the Society.
B61: It is presumed that the computer-generated entries and transactions are strictly accurate, in proper working order as per standard software/programming requirements, and free from internal defects. The Society shall be solely responsible for any subsequent changes made to the records.
B62: Information obtained and irregularities observed during the audit are presented in Parts A, B, and C of this report. Upon compliance with the irregularities noted, an Audit Compliance Report is to be submitted.
A64: Management:
B65: The list of management committee as on 31st March 2026 is provided by the Society. The Office bearers for the audit period are as under:
C66: Chairman | G66: - | H66: Mr. Aicod Raja
C67: Secretary | G67: - | H67: Mrs. Nisha Fernandes
C68: Member | G68: - | H68: Mrs. Shilpa Panchal
C69: Member | G69: - | H69: Mr. Wilson D'silva
A71: MEETINGS :-
C72: During the year of Audit following meetings were held.
C73: Sr. No. | D73: Meeting Name | J73: No. of Meetings | M73: Meetings Date
C74: 1 | D74: Managing Committee Meetings | J74: =+TIT!D20 -> 12 | M74: 19-04-2025, 20-05-2025, 17-06-2025, 28-07-2025, 17-08-2025, 19-09-2025, 17-10-2025, 15-11-2025, 12-12-2025, 05-01-2026, 11-02-2026, 27-03-2026
C75: 2 | D75: Annual General Meetings | J75: 1 | M75: =+TIT!D18 -> 45928
C76: 3 | D76: Special General Meetings | J76: 0 | M76: =+TIT!D19 -> Nil
B78: Annual General Meeting :-
B79: 1 | C79: ="The Annual General Body Meeting was held on "&TEXT(TIT!D18,"dd mmmm yyyy")&". We found that minutes of the meetings are maintained. The minutes of the above meetings are print outs pasted in the minute book." -> The Annual General Body Meeting was held on 28 September 2025. We found that minutes of the meetings are maintained. The minutes of the above meetings are print outs pasted in the minute book.
B80: 2 | C80: In the case of minutes by pasting of printout, it is advised to affix societies seal on each page with authentication by the chairman of the managing committee meeting in which the minutes are confirmed.
B81: 3 | C81: The folios of the minute book are not serially numbered.
B83: Managing Committee | S83: 9
B84: 1 | C84: The minutes of the above meetings are handwritten in the minute book.
B85: 2 | C85: The folios of the minute book are not serially numbered.
B86: 3 | C86: The resolution regarding reading and confirming the minutes of previous managing committee meeting and signing the same by the chairman of the meeting in which the minutes are read is not recorded in the minutes.
B87: 4 | C87: The place and date of signing the minutes by the chairman are not recorded in the minutes.
B88: 5 | C88: Managing committee resolution for approval of periodic expenditure incurred, acceptance of quotations of vendor, rectification report in form O, are not available in the minutes.
A90: MEMBERS | T90: Flat No. 401 transfer from Mr. Philip Lobo to Mrs. Aurora Lobo & Ms. Annie Lobo by nomination after death of Original Member.
B91: The Society has 18 members as on date. However, the details of Transfers or Transmissions of shares, if any, effected during the year have not been provided by the Management. | T91: The Society has 18 members as on date. However, the details of Transfers or Transmissions of shares, if any, effected during the year have not been provided by the Management.
A93: FINANCIAL PERFORMANCE:
B94: During the year under audit the society has incurred a DEFICIT of Rs. 1,17,952.10/- for the year ending 31-Mar-2026, as against a surplus of Rs. 27,001.74/- in the preceding year.
A97: OBSERVATION ON THE BALANCE SHEET AS ON 31-03-2026
A99: Sr. No. | C99: Particulars | J99: 46112 | M99: 45747 | P99: Increase/Decrease
C100: LIABILITIES
A101: 1 | C101: Issued,Subscribed & Paid Up Share Capital | J101: 9000 | M101: 9000 | P101: =+J101-M101 -> 0
A102: 2 | C102: Reserve and Other Funds | J102: 2135141 | M102: 1881820 | P102: =+J102-M102 -> 253321
A103: 3 | C103: Contribution from Members towards Bldg | J103: 17803000 | M103: 17803000 | P103: =+J103-M103 -> 0
A104: 4 | C104: Current Liabilities & provisions | J104: 159238 | M104: 480519 | P104: =+J104-M104 -> -321281
A105: 5 | C105: Advances from Members | J105: 1021 | M105: 9748 | P105: =+J105-M105 -> -8727
A106: 6 | C106: Income & Expenditure Acount | J106: 123463.89 | M106: 241415.99 | P106: =+J106-M106 -> -117952.1
C107: TOTAL :- | J107: =SUM(J101:L106) -> 20230864 | M107: =SUM(M101:O106) -> 20425503 | P107: =SUM(P101:R106) -> -194639.1
C108: ASSETS
A109: 1 | C109: Cash & Bank Balances | J109: 137015.34 | M109: 268624.94 | P109: =+J109-M109 -> -131609.6
A110: 2 | C110: Investments | J110: 1979039 | M110: 1892363 | P110: =+J110-M110 -> 86676
A111: 3 | C111: Contribution towards Building | J111: 17803000 | M111: 17803000 | P111: =+J111-M111 -> 0
A112: 4 | C112: Other Fixed Assets | J112: 55257 | M112: 64759.5 | P112: =+J112-M112 -> -9502.5
A113: 5 | C113: Other Current Assets | J113: 253219.53 | M113: 386589.53 | P113: =+J113-M113 -> -133370
A114: 6 | C114: Prepaid Expenses | J114: 3333 | M114: 10166 | P114: =+J114-M114 -> -6833 | T114: 5924829.7
C115: TOTAL :- | J115: =SUM(J109:L114) -> 20230864 | M115: =SUM(M109:O114) -> 20425503 | P115: =SUM(P109:R114) -> -194639.1
A117: ANALYSIS OF BALANCE SHEET :-
A119: SECTION I: CAPITAL AND LIABILITIES
B120: 1 | C120: AUTHORISED SHARE CAPITAL:
C121: As per approved Bye-Laws of society, Authorised Share Capital was Rs. 1,00,000/- divided into 2000 shares of Rs.50/- each.
B123: 2 | C123: PAID-UP SHARE CAPITAL:
...

Sheet SCH (2)
A1: =+TIT!D2 -> PRATHAMESH HARMONY "B" WING CO-OPERATIVE HOUSING SOCIETY LTD.
A2: Schedules attached to and forming part of the Annual Account for the year ended 31st March, 2026
A4: A | B4: Accounting Conventions:
B5: 1 | D5: The financial statements have been prepared under the historical cost convention, in accordance with the generally accepted accounting policies and according to the provisions of the Maharashtra Co op Societies Act, 1960 and Rules framed there under and registered Bye-laws of the society and the same, unless specifically referred otherwise, are adopted consistently by the society.
B10: 2 | C10: Recognition of Income and Expenditure:
D11: The society generally follows accrual system of accounting and recognises significant items of income and expenditure on accrual basis except contributions by members towards Non-Agricultural Tax and its payment, annual contribution towards the education and training fund and its utilisations.
B15: 3 | C15: Fixed Assets:
D16: Fixed assets are stated at cost less depreciation. Cost comprises of cost of acquisition and any attributable cost of bringing the asset to condition for its intended use.
B19: 4 | C19: Depreciation:
D20: Depreciation is provided for number of days fixed assets put to use during the year, on written down value (WDV) at the rates prescribed under the Income Tax Act, 1961.
B24: 5 | C24: Investments:
D25: Investments are stated at cost.
B26: 6 | C26: Contingent Liabilities:
D27: Contingent liabilities are not provided for and, if any, the same is disclosed by way of note.
A29: B | B29: Notes on Accounts:
B30: 1 | C30: Previous year figures:
D31: Previous year figures have been re-worked, re-grouped, re-arranged and re-classified wherever necessary to facilitate comparison with the current year figure.
D33: The dues from members and credit balances of members security deposits with Adani Electricity are subject to confirmation.
D34: In the opinion of the Managing Committee, the value of other assets is as stated in the financial statement, if realised in the ordinary course of operations of the Society.
H37: ="For "&TIT!$D$2 -> For PRATHAMESH HARMONY "B" WING CO-OPERATIVE HOUSING SOCIETY LTD.
H42: Chairman Secretary Treasurer
D43: =+TIT!D9 -> Shri. Bharat C. Boridkar
D44: ="["&TIT!A10&": "&TIT!D10&"]" -> [Panel No.: Mumbai-4/C1/1011404]
D45: Govt. Certified Panel Auditor
D46: =+TIT!D13 -> 46277

Sheet Audit-Remarks
B2: INFRIGMENT OF THE M.C.S. ACT 1960 RULES 1961 & THE BYE-LAWS OF THE SOCIETY
B4: Sr.No. | C4: Act | D4: Rules | E4: Bye-Laws | F4: Details Of Infringements
B5: 1 | C5: 38 | D5: 32 | E5: 141(i) | F5: Member’s register in I form.
B6: 2 | C6: -- | D6: 26 | E6: 32 | F6: NOMINATION NOT FULLY RECEIVED | H6: Nomination Not Fully Received
B7: 3 | D7: 33 | E7: 141(2) | F7: List of members in “j” form not kept on record
B8: 4 | C8: 82 | D8: 73 | E8: 153 | F8: Audit rectification report in prescribed “O” form submission to registrar witin prescribed limit.
B9: 5>>> | E9: 154 | F9: Conveyance of the property
B10: 6>>> | E10: 160 | F10: Insurance of building
B11: 7 | C11: 071 (a) | F11: Defaulter member 3 months
B12: 8 | E12: 127 (i) | F12: Managing committee meeting
B13: 9>>> | E13: 145 | F13: Payment beyond the limit in cash
B14: 10 | C14: 75(iI) | E14: 95(9) | F14: A G M within prescribed limit
B15: 11>>> | C15: 24(a) | E15: 14 | F15: Education & Training fund collection
B16: 12>>> | C16: 70 | D16: 54,55 | E16: 15 | F16: Investment of fund
B17: 13>>> | D17: 65 | E17: 141 (I to 16) | F17: Required registers to be kept (property reg.)
B18: 14 | C18: 73 | E18: 115 | F18: Reservation for female member on the managing committee.
B19: 15 | C19: 73FF | E19: 119 B | F19: Disqualification for membership of managing committee.
B20: 16 | C20: 29 | F20: Restriction of transfer of shares & property.
B21: 17 | E21: 9 | F21: Issue of share certificates to the members witin the prescribed limit.
B23: 18 | D23: 61 | E23: 146(a) | F23: Drafting financial statement after the prescribed limit.
B24: 19 | E24: 144 | F24: Cash in hand beyond the prescribed limit..
B25: 20 | C25: 160 | E25: 124 | F25: Handover the charge to new committee.
B26: 22>>> | C26: 73 b 73 c | E26: 114 | F26: Strength of the meeting.

Sheet Meeting
A1: Managing Committee meeting attendance - FY 2025-26 (to be completed from the Minute Book)
B3: Meet-1 | C3: Meet-2 | D3: Meet-3 | E3: Meet-4 | F3: Meet-5 | G3: Meet-6 | H3: Meet-7 | I3: Meet-8 | J3: Meet-9 | K3: Meet-10 | L3: Meet-11 | M3: Meet-12
A4: Member name

Sheet Pending Inputs
A1: PRATHAMESH HARMONY "B" CHS LTD. - FY 2025-26 : information to be filled in before the report is signed
A3: Sr. | B3: Sheet / Cell | C3: Particulars | D3: Provisional entry now in the file
A4: 1 | B4: TIT!D13, D15, D16, D17 | C4: Date of report, date of commencement, date of completion, date of submission of the audit memo | D4: 17-09-2026 / 10-09-2026 / 17-09-2026 / 17-09-2026
A5: 2 | B5: TIT!D18, F18 | C5: Date of the AGBM held during 2025-26 and the number of members present | D5: 30-09-2025 assumed; members present blank
A6: 3 | B6: TIT!D19 | C6: Special General Body Meeting, if any | D6: Nil
A7: 4 | B7: TIT!D20 | C7: Number of Managing Committee meetings held during the year | D7: 0 - to be entered
A8: 5 | B8: TIT!D23, D24 | C8: Audit fees for the previous audit and the period covered | D8: Rs. 2,500 for 2024-25
A9: 6 | B9: Form-1!D33, D34, D35 | C9: Dates of the auditor's appointment letter, acceptance letter and its receipt by the Society | D9: blank
A10: 7 | B10: Form-1!D38 | C10: Date of the Managing Committee meeting at which the audit report is discussed | D10: blank
A11: 8 | B11: Form-1!D94:D97 and GR!H68:H71 | C11: Names of the Chairman, Secretary and Committee members for 2025-26 | D11: blank
A12: 9 | B12: Form-1!D21, AR!C62, GR!G11 | C12: Audit classification awarded for 2025-26 | D12: "B" carried forward from last year - to be confirmed
A13: 10 | B13: GR!M76 and GR!C91 | C13: Dates of the Managing Committee meetings and the months in which no meeting was held | D13: blank
A14: 11 | B14: GR!J78 | C14: Number of Special General Body Meetings held | D14: 0
A15: 12 | B15: Meeting sheet | C15: Attendance record of Managing Committee meetings for 2025-26 | D15: cleared - last year's sheet carried another society's names
A16: 13 | B16: Form-1!D45, D47 | C16: Audit fees fixed for 2025-26 | D16: Rs. 2,500 as provided in the accounts
B18: Cells carrying a provisional entry are shaded yellow in the respective sheets. This sheet is a working note and is outside the print areas of the report.
